Workbook
Name Slicer_Business_Unit: #N/A
Name Slicer_Department: #N/A
Name Slicer_Employee_ID: #N/A
Name Slicer_Employment_Status: #N/A
Name Slicer_Gender: #N/A
Name Slicer_Job_Level: #N/A
Name Slicer_Promotion_Status: #N/A
Name Slicer_Training_Hours: #N/A

Sheet 01_raw_data
A1: 01 - Raw Messy Employee Data
A2: HR extract with extra spaces, mixed cases, missing values, wrong spellings, invalid dates, duplicate IDs, negative values and mapping gaps
A4: Employee ID | B4: Employee Name | C4: Gender | D4: Age | E4: Date of Birth | F4: Department | G4: Business Unit | H4: Designation | I4: Job Level | J4: Manager ID | K4: Manager Name | L4: Location | M4: Country | N4: State | O4: Joining Date | P4: Exit Date | Q4: Employment Status | R4: Salary | S4: Bonus | T4: Performance Rating | U4: Training Hours | V4: Leave Taken | W4: Overtime Hours | X4: Employee Engagement Score | Y4: Promotion Status | Z4: Education Level | AA4: Recruitment Source | AB4: Work Mode | AC4: Cost Center | AD4: Employee Type | AE4: Productivity Score
A5: E0001 | B5: Tess Martin | C5: Male | D5: 56 | E5: 25373 | F5: Data & Analytics | G5: Data & AI | H5: Senior Data Analyst | I5: L6 | J5: M003 | K5: Sarah Lopez | L5: Valencia | M5: Spain | N5: Valencian Community | O5: 44869 | Q5: A | R5: 134000 | S5: 4000 | T5: 2 | U5: 35 | V5: 20 | W5: 10 | X5: 74 | Y5: Not Promoted | Z5: Master's | AA5: University Hiring | AB5: HYBRID | AC5: EU-CC103 | AD5: Contract | AE5: 57.6
A6: E0002 | B6: Miguel Gonzalez | C6: Male | D6: 25 | E6: 37009 | F6: Finance | G6: Corporate Services | H6: Financial Analyst | I6: L4 | J6: M007 | K6: Astrid Bakker | L6: Hamburg | M6: Germany | N6: Hamburg | O6: 43226 | Q6: Active | R6: 107000 | S6: 5400 | T6: 3 | U6: 28 | V6: 15 | W6: 26 | X6: 44 | Y6: Not promoted | Z6: Bachelor's | AA6: Agency | AB6: Hybrid | AC6: EU-CC301 | AD6: Full Time | AE6: 49.4
A7: E0003 | B7: Hannah Wilson | C7: Male | D7: 24 | E7: 37238 | F7: Product | G7: Product & Technology | H7: Product Analyst | I7: L2 | K7: Sophia Moreau | L7: Krakow | M7: poland | N7: Lesser Poland | O7: 45858 | Q7: active | R7: 44000 | S7: 2200 | T7: 3 | U7: 35 | V7: 25 | W7: 16 | X7: 74 | Y7: Not Promoted | Z7: Bachelor's | AA7: Agency | AB7: Remote | AC7: EU-CC102 | AD7: full time | AE7: 63.6
A8: E0004 | B8: Bram Visser | C8: Male | D8: 28 | E8: 12-01-1997 | F8: Legal | G8: risk & compliance | H8: Contracts Analyst | I8: L5 | J8: M011 | K8: Julia Marino | L8: Milan | M8: italy | N8: Lombardy | O8: 44343 | Q8: Active | R8: 118000 | S8: 1200 | T8: 1 | U8: 27 | V8: 20 | W8: 27 | X8: 26 | Y8: Not Promoted | Z8: Bachelor's | AA8: Company Careers Page | AB8: Hybrid | AC8: EU-CC501 | AD8: Contract | AE8: 24.9
A9: E0005 | B9: Kacper Brown | C9: Male | D9: 38 | E9: 32217 | F9: Marketing | G9: Revenue | H9: marketing executive | I9: L6 | J9: M006 | K9: Aleksander Fischer | L9: MADRID | M9: Spain | N9: COMMUNITY OF MADRID | O9: 43996 | Q9: Active | R9: 157000 | S9: 9400 | T9: three | U9: 15 | V9: 12 | W9: 11 | X9: 63 | Y9: Not Promoted | Z9: MBA | AA9: University Hiring | AB9: Hybrid | AC9: EU-CC203 | AD9: FULL-TIME | AE9: 57.3
A10: E0006 | B10: Kacper Gustafsson | C10: Male | D10: 29 | E10: not available | F10: CUSTOMER SUCCESS | G10: Revenue | H10: Client Success Associate | I10: L3 | J10: M054 | K10: Isla Eriksson | L10: Stockholm | M10: Sweden | N10: Stockholm County | O10: 44665 | Q10: A | R10: 79000 | S10: 7100 | T10: 4 | U10: -31 | V10: 23 | W10: 0 | X10: 84 | Y10: Not Promoted | Z10: Bachelor's | AA10: Agency | AB10: Hybrid | AC10: EU-CC202 | AD10: FULL-TIME | AE10: 83.2
A11: E0007 | B11: Ines Martinez | C11: Male | D11: 32 | E11: 34162 | F11: TECH | G11: Product & Technology | H11: Engineering Lead | I11: L3 | J11: M048 | K11: Jack Schmidt | L11: Hamburg | M11: Germany | N11: Hamburg | O11: 45404 | Q11: ACTIVE | R11: 85000 | S11: 1700 | T11: 2 | U11: 57 | V11: 20 | W11: 0 | X11: 46 | Y11: Not Promoted | Z11: Bachelor's | AA11: University Hiring | AB11: hybrid | AC11: EU-CC101 | AD11: Full Time | AE11: 54.1
A12: E0008 | B12: ALESSANDRO JANSEN | C12: Male | D12: 22 | E12: 38098 | F12: Operations | G12: Operations | H12: Workforce Planner | I12: L2 | J12: M010 | K12: Lotte Muller | L12: Eindhvn | M12: NETHERLANDS | N12: North Brabant | O12: 45703 | P12: 01-08-2026 | Q12: Exited | R12: 56000 | S12: 7800 | T12: 5 | U12: 48 | V12: 10 | W12: 1 | X12: 57 | Y12: Not Promoted | Z12: Bachelor's | AA12: European Job Board | AB12: Remote | AC12: EU-CC401 | AD12: full time | AE12: 84.5
A13: E0009 | B13: Javier Ricci | C13: Male | D13: 37 | E13: 32347 | F13: Data & Analytics | G13: Data & AI | H13: Data Scientist | I13: L4 | J13: M020 | K13: Alessandro Lewandowski | L13: Munich | M13: Germany | N13: Bavaria | O13: 42863 | Q13: Active | R13: 109000 | S13: 5400 | T13: 3 | U13: 29 | V13: 18 | W13: 7 | X13: 47 | Y13: Not Promoted | Z13: Diploma | AA13: Company Careers Page | AB13: Hybrid | AC13: EU-CC103 | AD13: Full Time | AE13: 57.2
A14: E0010 | B14: Sophia Petit | C14: Female | D14: 46 | E14: 29087 | F14: Security | G14: risk & compliance | H14: Security Lead | I14: L1 | J14: M056 | K14: Emily Olsson | L14: London | M14: United Kingdom | N14: england | O14: 00/00/0000 | Q14: Active | R14: 49000 | S14: 2400 | T14: 3 | U14: 21 | V14: 2 | W14: 20 | X14: 54 | Y14: Not Promoted | Z14: Bachelor's | AA14: European Job Board | AB14: Office | AC14: EU-CC503 | AD14: Full Time | AE14: 51.1
A15: E0011 | B15: Francesco Ferreira | C15: male | D15: 51 | E15: 27494 | F15: Corp Strategy | G15: Corporate Services | H15: Transformation Lead | I15: L3 | J15: M015 | K15: Lea Ryan | L15: Manchester | M15: United Kingdom | N15: England | O15: 44414 | P15: 45280 | Q15: EXITED | R15: 71000 | S15: 3600 | T15: 3 | U15: 18 | V15: 31 | W15: 0 | X15: 68 | Y15: Not Promoted | Z15: Bachelor's | AA15: LinkedIn | AB15: Remote | AC15: EU-CC303 | AD15: Full Time | AE15: 65.3
A16: E0012 | B16: Emily Fernandes | C16: Female | D16: 24 | E16: 37406 | F16: Rev Ops Unknown | G16: Risk & Compliance | H16: Security Analyst | I16: L2 | J16: M014 | K16: Elena Szymanski | L16: Berlin | M16: Germany | N16: Berlin | O16: 44246 | Q16: Active | R16: 57000 | S16: 2800 | T16: THREE | U16: 12 | V16: 22 | W16: 25 | X16: 57 | Y16: Not Promoted | Z16: Master's | AA16: Indeed | AB16: Remote | AC16: EU-CC503 | AD16: Full Time | AE16: 50
A17: E0013 | B17: Arthur Mulder | C17: Female | D17: 46 | E17: 29183 | F17: Purchasing | G17: Operations | H17: Vendor Manager | I17: L2 | J17: M013 | K17: Ebba Kelly | L17: Stockholm | M17: Sweden | N17: Stockholm County | O17: 44155 | Q17: Active | R17: 66000 | S17: 3300 | T17: 0 | U17: 38 | V17: 17 | W17: 10 | X17: 60 | Y17: Not Promoted | Z17: Master's | AA17: LinkedIn | AB17: Remote | AC17: EU-CC402 | AD17: contract | AE17: 62.5
A18: E0014 | B18: Maximilian Romano | C18: Female | D18: 51 | E18: 27197 | F18: ENGINEERING | G18: product & technology | H18: Platform Engineer | I18: L2 | J18: M051 | K18: Eva Bianchi | L18: MUNICH | M18: Germany | N18: Bavaria | O18: 25/09/2024 | Q18: ACTIVE | R18: 60000 | S18: 5400 | T18: four | U18: 21 | V18: 28 | W18: 13 | X18: 65 | Y18: Not Promoted | Z18: Bachelor's | AA18: European Job Board | AB18: Hybrid | AC18: EU-CC101 | AD18: Full Time | AE18: 67.5
A19: E0015 | B19: Aleksander Brown | C19: female | D19: 42 | E19: 30754 | F19: Customer Success | G19: Revenue | H19: Client Success Associate | I19: L2 | J19: M050 | K19: Louis Szymanski | L19: Munich | M19: GERMANY | N19: Bavaria | O19: 44699 | P19: 45180 | Q19: inactive | R19: 53000 | S19: 4800 | T19: 4 | U19: 24 | V19: 4 | W19: 5 | X19: 52 | Y19: Not Promoted | Z19: Master's | AA19: Employee Referral | AB19: HYBRID | AC19: EU-CC202 | AD19: full time | AE19: 67.7
A20: E0016 | B20: Milan Mulder | C20: Female | D20: 45 | E20: 29509 | F20: Marketing | G20: Revenue | H20: SEO Specialist | I20: L2 | J20: M006 | K20: Aleksander Fischer | L20: Frankfrt | M20: Germany | N20: Hesse | O20: 44325 | Q20: Active | R20: 63000 | S20: 3200 | T20: 3 | U20: 22 | V20: 0 | W20: 9 | X20: 57 | Y20: Not Promoted | Z20: Master's | AA20: Internal Transfer | AB20: hybrid | AC20: EU-CC203 | AD20: Part Time | AE20: 58
A21: E0017 | B21: valeria olsson | C21: Male | D21: 28 | E21: 35861 | F21: Data & Analytics | G21: Data & AI | H21: Analytics Engineer | I21: L2 | J21: M003 | K21: Sarah Lopez | L21: Stockholm | M21: Sweden | N21: stockholm county | O21: 42737 | Q21: active | R21: 64000 | S21: 1300 | T21: 2 | U21: 33 | V21: 9 | W21: 20 | X21: 45 | Y21: Not Promoted | Z21: Bachelor's | AA21: European Job Board | AB21: Hybrid | AC21: EU-CC103 | AD21: part time | AE21: 42
A22: E0018 | B22: Luuk Rodriguez | C22: Male | D22: 26 | E22: 36486 | F22: Customer Success | G22: Revenue | H22: Customer Success Manager | I22: L3 | J22: M024 | K22: Noah Ryan | L22: DUB | M22: Ireland | N22: Leinster | O22: 44684 | Q22: ACTIVE | R22: 72000 | S22: 6500 | T22: 4 | U22: 7 | V22: 7 | W22: 13 | X22: -5 | Y22: Not Promoted | Z22: Bachelor's | AA22: Company Careers Page | AB22: Hybrid | AC22: EU-CC202 | AD22: Full Time | AE22: 70.7
A23: E0019 | B23: Linnea Costa | C23: male | D23: 35 | E23: 07-29-1990 | F23: Product | G23: Product & Technology | H23: PRODUCT MANAGER | I23: L3 | J23: M028 | K23: Sara Fernandes | L23: Dublin | M23: Ireland | N23: Leinster | O23: 42749 | Q23: Active | R23: 85000 | S23: 4200 | T23: 3 | U23: 26 | V23: 25 | W23: 9 | X23: 52 | Y23: Not promoted | Z23: Master's | AA23: Internal Transfer | AB23: WFH | AC23: EU-CC102 | AD23: FULL-TIME | AE23: 57.2
A24: E0020 | B24: Camille Bianchi | C24: Male | D24: 36 | E24: 32707 | F24: Software Engg | G24: Product & Technology | H24: Senior Software Engineer | I24: L2 | J24: M001 | K24: Milan Leroy | L24: London | M24: UNITED KINGDOM | N24: England | O24: 45589 | Q24: ACTIVE | R24: 70000 | S24: 3500 | T24: 3 | U24: 13 | V24: 16 | W24: 6 | X24: 70 | Y24: Not Promoted | Z24: Bachelor's | AA24: European Job Board | AB24: Office | AC24: EU-CC101 | AD24: full time | AE24: 61.8
A25: E0021 | B25: Sofia Costa | C25: Male | D25: 38 | E25: 32295 | F25: ENGINEERING | G25: PRODUCT & TECHNOLOGY | H25: Platform Engineer | I25: L6 | J25: M048 | K25: Jack Schmidt | L25: REMOTE | M25: Europe | N25: Remote | O25: 45988 | Q25: A | R25: 149000 | S25: 14900 | T25: 4 | U25: 6 | V25: 16 | W25: 16 | X25: 65 | Y25: Not promoted | Z25: Master's | AA25: European Job Board | AB25: Remote | AC25: EU-CC101 | AD25: Full Time | AE25: 62.2
A26: E0022 | B26: Marco Wisniewski | C26: M | D26: 28 | E26: 1998/03/24 | F26: Commercial | G26: Revenue | H26: Enterprise Account Manager | I26: L4 | J26: M026 | K26: Sergio Rodrigues | L26: WROCLAW | M26: Poland | N26: Lower Silesian | O26: 44776 | Q26: active | R26: 68000 | S26: 9500 | T26: 5 | U26: 12 | V26: 19 | W26: 25 | X26: 72 | Y26: Not Promoted | Z26: Bachelor's | AA26: University Hiring | AB26: Hybrid | AC26: EU-CC201 | AD26: Full Time | AE26: 73.2
A27: E0023 | B27: Manuel Murphy | C27: Male | D27: 25 | E27: 36952 | F27: Data & Analytics | G27: Data & AI | H27: Analytics Engineer | I27: L2 | J27: M058 | K27: Lukas Esposito | L27: BRU | M27: Belgium | N27: Brussels-Capital | O27: 44582 | Q27: ACTIVE | R27: 52000 | S27: -1000 | T27: 2 | U27: 9 | V27: 12 | W27: 35 | X27: 75 | Y27: Not Promoted | Z27: MBA | AA27: European Job Board | AB27: Work From Home | AC27: EU-CC103 | AD27: FTE | AE27: 46.5
A28: E0024 | B28: Laura Fernandez | C28: Female | D28: 40 | E28: 31317 | F28: Human Resources | G28: Corporate Services | H28: People Operations Analyst | I28: L3 | J28: M060 | K28: Matteo Wagner | L28: BER | M28: Germany | N28: Berlin | O28: 44749 | Q28: Active | R28: 80000 | S28: 7200 | T28: 4 | U28: 30 | V28: 10 | W28: 14 | X28: 57 | Y28: Not Promoted | Z28: Bachelor's | AA28: LinkedIn | AB28: Hybrid | AC28: EU-CC302 | AD28: Full Time | AE28: 66.5
A29: E0025 | B29: Elsa Eriksson | C29: Non-Binary | D29: 53 | E29: 26753 | F29: Customer Success | G29: Revenue | H29: Client Success Associate | I29: L3 | J29: M054 | K29: Isla Eriksson | L29: Lyon | M29: France | N29: AUVERGNE-RHONE-ALPES | O29: 2020/04/23 | Q29: Active | R29: 71000 | S29: 6400 | T29: 4 | U29: 15 | V29: 18 | W29: 0 | X29: 76 | Y29: Not Promoted | Z29: PhD | AA29: Indeed | AB29: hybrid | AC29: EU-CC202 | AD29: Full Time | AE29: 76.3
A30: E0026 | B30: Sergio Larsson | C30: Male | D30: 28 | E30: 35735 | F30: TECH | G30: Product & Technology | H30: Software Engineer | I30: L5 | J30: M051 | K30: Eva Bianchi | L30: Dublin | M30: Ireland | N30: Leinster | O30: 2024/03/03 | Q30: Actve | R30: 167000 | S30: 10000 | T30: 3 | U30: 17 | V30: 5 | W30: 22 | X30: 43 | Y30: no | Z30: Master's | AA30: Company Careers Page | AB30: remote | AC30: EU-CC101 | AD30: Full Time | AE30: 46.3
A31: E0027 | B31: Hugo Gomez | C31: Male | D31: 26 | E31: 36571 | F31: Finance | G31: Corporate Services | H31: Finance Manager | I31: L5 | J31: M007 | K31: Astrid Bakker | L31: Lyon | M31: France | N31: Auvergne-Rhone-Alpes | O31: 43062 | Q31: Active | R31: 131000 | S31: 13100 | T31: 4 | U31: 27 | V31: 13 | W31: 14 | X31: 60 | Y31: Not promoted | Z31: Bachelor's | AA31: Company Careers Page | AB31: hybrid | AC31: EU-CC301 | AD31: full time | AE31: 66.8
A32: E0028 | B32: Gabriel Dubois | C32: Male | D32: 46 | E32: 29069 | F32: HUMAN RESOURCES | G32: Corporate Services | H32: Talent Acquisition Specialist | I32: L3 | J32: M033 | K32: Pieter Perez | L32: LILLE | M32: France | N32: Hauts-de-France | O32: 43607 | P32: 45602 | Q32: inactive | R32: 79000 | S32: 1600 | T32: 2 | U32: -14 | V32: 22 | W32: 5 | X32: 41 | Y32: no | Z32: BACHELOR'S | AA32: Internal Transfer | AB32: On-site | AC32: EU-CC302 | AD32: Full Time | AE32: 43.4
A33: E0029 | B33: Diego Fischer | C33: Male | D33: 58 | E33: 24820 | F33: Marketing | G33: REVENUE | H33: Content Specialist | I33: L7 | J33: M006 | K33: Aleksander Fischer | L33: Remote - Europe | M33: Europe | N33: Remote | O33: 45047 | Q33: Active | R33: 233000 | S33: 23300 | T33: 4 | U33: 39 | V33: 17 | W33: 0 | X33: 72 | Y33: NO | Z33: Master's | AA33: Agency | AB33: Office | AC33: EU-CC203 | AD33: full time | AE33: 81
A34: E0030 | B34: Luuk Byrne | C34: Female | D34: 30 | E34: 34909 | F34: ENGINERING | G34: Product & Technology | H34: Software Engineer | I34: L3 | J34: M039 | K34: Freya Martinez | L34: KRAKOW | M34: poland | N34: lesser poland | O34: 42545 | Q34: Active | R34: 60000 | S34: 3000 | T34: 3 | U34: 17 | V34: 17 | W34: 16 | X34: 39 | Y34: Not Promoted | Z34: Bachelor's | AA34: Internal Transfer | AB34: Remote | AC34: EU-CC101 | AD34: Full Time | AE34: 46.9
A35: E0023 | B35: Diego De Jong | C35: Female | D35: 43 | E35: 30423 | F35: Customer Success | G35: Revenue | H35: Support Specialist | I35: L1 | J35: M054 | K35: Isla Eriksson | L35: Remote - Europe | M35: Europe | N35: Remote | O35: 45446 | Q35: Active | R35: 32000 | S35: 1600 | T35: 3 | U35: 6 | V35: 17 | W35: 6 | X35: 51 | Y35: Not Promoted | Z35: Master's | AA35: Agency | AB35: On-site | AC35: EU-CC202 | AD35: FTE | AE35: 53.3
A36: E0032 | B36: Arthur Gustafsson | C36: F | D36: 57 | E36: 25201 | F36: Purchasing | G36: Operations | H36: Procurement Analyst | I36: L2 | J36: M049 | K36: Marco Gonzalez | L36: MILAN | M36: Italy | N36: LOMBARDY | O36: 45798 | Q36: Active | R36: 45000 | S36: 6300 | T36: 5 | U36: 19 | V36: 22 | W36: 27 | X36: 88 | Y36: Promoted | Z36: Bachelor's | AA36: Company Careers Page | AB36: hybrid | AC36: EU-CC402 | AD36: Full Time | AE36: 80.5
A37: E0033 | B37: Leonardo Walsh | C37: Male | D37: 53 | E37: 26514 | F37: Commercial | G37: Revenue | H37: Account Executive | I37: L6 | J37: M023 | K37: Alice Greco | L37: BERLIN | M37: Germany | N37: berlin | O37: 44314 | Q37: active | R37: 204000 | S37: 12200 | T37: 3 | U37: 38 | V37: 9 | W37: 18 | X37: 66 | Y37: Not Promoted | Z37: mba | AA37: European Job Board | AB37: ONSITE | AC37: EU-CC201 | AD37: Full Time | AE37: 60.6
A38: E0034 | B38: alice taylor | C38: Male | D38: 43 | E38: 30357 | F38: Corp Strategy | G38: corporate services | H38: Business Analyst | I38: L4 | J38: M015 | K38: Lea Ryan | L38: MILAN | M38: Italy | N38: lombardy | O38: 44841 | Q38: Active | R38: 88000 | S38: 7900 | T38: 4 | U38: 27 | V38: 5 | W38: 7 | X38: 98 | Y38: Not Promoted | Z38: Bachelor's | AA38: Indeed | AB38: Office | AC38: EU-CC303 | AD38: Contract | AE38: 83.5
A39: E0035 | B39: Sofia Jones | C39: Male | D39: 37 | E39: 32372 | F39: Sale | G39: Revenue | H39: Account Executive | I39: L2 | J39: M016 | K39: Juliette Williams | L39: Londoon | M39: Poland | N39: Masovian | O39: 44898 | Q39: Active | R39: 45000 | S39: 2200 | T39: 6 | U39: 35 | V39: 20 | W39: 14 | X39: 62 | Y39: Not Promoted | Z39: MASTER'S | AA39: Internal Transfer | AB39: Hybrid | AC39: EU-CC201 | AD39: part time | AE39: 60.5
A40: E0036 | B40: Sophia Rodriguez | C40: F | D40: 49 | E40: 2026-15-09 | F40: ENGINEERING | G40: Product & Technology | H40: frontend engineer | I40: L4 | J40: M001 | K40: Milan Leroy | L40: Brussels | M40: Belgium | N40: Brussels-Capital | O40: 43893 | Q40: ACTIVE | R40: 109000 | S40: 5400 | T40: 3 | U40: 21 | V40: 8 | W40: 5 | X40: 59 | Y40: Not Promoted | Z40: bachelor's | AA40: Company Careers Page | AB40: Office | AC40: EU-CC101 | AD40: Full Time | AE40: 60.4
A41: E0037 | B41: Oscar Ferreira | C41: Female | D41: 49 | E41: 28059 | F41: Compliance | G41: Risk & Compliance | H41: Regulatory Specialist | I41: L3 | J41: M025 | K41: Elias De Jong | L41: Paris | M41: France | N41: Ile-de-France | O41: 42927 | Q41: Active | R41: 79000 | S41: 1600 | T41: 2 | U41: 27 | V41: 13 | W41: 13 | X41: 53 | Y41: Not Promoted | Z41: Diploma | AA41: Agency | AB41: remote | AC41: EU-CC502 | AD41: FTE | AE41: 46.8
A42: E0038 | B42: Elsa Johansson | C42: Female | D42: 29 | E42: 35385 | F42: Commercial | G42: Revenue | H42: Sales Development Representative | I42: L3 | J42: M004 | K42: Giovanni Leroy | L42: Remote - Europe | M42: Europe | N42: Remote | O42: 45081 | Q42: Active | R42: 66000 | S42: 5900 | T42: 4 | U42: 24 | V42: 18 | W42: 16 | X42: 60 | Y42: Not Promoted | Z42: Master's | AA42: Company Careers Page | AB42: Remote | AC42: EU-CC201 | AD42: Part Time | AE42: 65
A43: E0039 | B43: MOLLY SVENSSON | C43: Female | D43: 57 | E43: 25355 | F43: Finance | G43: Corporate Services | H43: Payroll Specialist | I43: L3 | J43: M007 | K43: Astrid Bakker | L43: Dublin | M43: Ireland | N43: Leinster | O43: 45057 | Q43: Active | R43: 74000 | S43: 1500 | T43: 2 | U43: 21 | V43: 12 | W43: 10 | X43: 26 | Y43: Not Promoted | Z43: Diploma | AA43: University Hiring | AB43: Hybrid | AC43: EU-CC301 | AD43: Full Time | AE43: 37.4
A44: E0040 | B44: Lucas Zielinski | C44: Male | D44: 42 | E44: 30557 | F44: Marketing | G44: Revenue | H44: Growth Marketer | I44: L5 | J44: M006 | K44: Aleksander Fischer | L44: Warsaw | M44: Poland | N44: Masovian | O44: 42409 | Q44: Actve | R44: 101000 | S44: 6100 | T44: 3 | U44: 16 | V44: 17 | W44: 3 | X44: 64 | Y44: Not Promoted | Z44: DIPLOMA | AA44: European Job Board | AB44: Hybrid | AC44: EU-CC203 | AD44: Full Time | AE44: 61.9
A45: E0041 | B45: lea rossi | C45: Non-Binary | D45: 25 | E45: 37053 | F45: PMO Product | G45: Product & Technology | H45: Product Manager | I45: L6 | J45: M031 | K45: Felix Pereira | L45: Munich | M45: Germany | N45: bavaria | O45: 42971 | Q45: Active | R45: 178000 | S45: 10700 | T45: 3 | U45: 25 | V45: 23 | W45: 7 | X45: 55 | Y45: Not Promoted | Z45: Bachelor's | AA45: LinkedIn | AB45: Hybrid | AC45: EU-CC102 | AD45: Full Time | AE45: 59
A46: E0042 | B46: Charlotte Kowalski | C46: F | D46: 58 | E46: 24796 | F46: IT | G46: Product & Technology | H46: IT Support Analyst | I46: L3 | J46: M041 | K46: Javier Jansen | L46: Londn | M46: United Kingdom | N46: England | O46: 44119 | Q46: Active | R46: 96000 | S46: 1900 | T46: two | U46: 29 | V46: 10 | W46: 2 | X46: 51 | Y46: Not Promoted | Z46: Bachelor's | AA46: Internal Transfer | AB46: Hybrid | AC46: EU-CC104 | AD46: Full Time | AE46: 52.1
A47: E0043 | B47: Gabriel Walker | C47: Female | D47: 29 | E47: 35324 | F47: CUSTOMER SUCCESS | G47: Revenue | H47: Client Success Associate | I47: L5 | J47: M050 | K47: Louis Szymanski | L47: Gothenburg | M47: Sweden | N47: Vastra Gotaland | O47: 08/03/2024 | P47: 45711 | Q47: Exited | R47: 122000 | S47: 7300 | T47: THREE | U47: 19 | V47: 11 | W47: 13 | X47: 42 | Y47: no | Z47: Master's | AA47: European Job Board | AB47: Hybrid | AC47: EU-CC202 | AD47: Contract | AE47: 50
A48: E0044 | B48: Molly Nowak | C48: F | D48: 42 | E48: 1984/03/29 | F48: Customer Sucess | G48: Revenue | H48: Client Success Associate | I48: L3 | J48: M047 | K48: Alice Andersson | L48: MAD | M48: Spain | N48: Community of Madrid | O48: 43871 | Q48: Active | R48: 58000 | S48: 2900 | T48: 3 | U48: 20 | V48: 24 | W48: 15 | X48: 63 | Y48: Not promoted | Z48: Master's | AA48: Company Careers Page | AB48: Hybrid | AC48: EU-CC202 | AD48: Full Time | AE48: 56.5
A49: E0045 | B49: Amelia Ricci | C49: female | D49: 58 | E49: 24670 | F49: Product | G49: Product & Technology | H49: Lead Product Manager | I49: L3 | J49: M027 | K49: Miguel Persson | L49: Remote - Europe | M49: Europe | N49: Remote | O49: 44370 | P49: 45783 | Q49: Exited | R49: 65000 | S49: 3200 | T49: 3 | U49: 10 | V49: 18 | W49: 16 | X49: 65 | Y49: Not Promoted | Z49: Bachelor's | AA49: Company Careers Page | AB49: Remote | AC49: EU-CC102 | AD49: Full Time | AE49: 54.2
A50: E0046 | B50: Ava Murphy | C50: F | D50: 26 | E50: 36523 | F50: Engineering | G50: Product & Technology | H50: Backend Engineer | I50: L4 | J50: M039 | K50: Freya Martinez | L50: Gothenburg | M50: Sweden | N50: Vastra Gotaland | O50: 45227 | Q50: Active | R50: 87000 | S50: 7800 | T50: 4 | U50: 32 | V50: 11 | W50: 4 | X50: 56 | Y50: YES | Z50: Master's | AA50: Employee Referral | AB50: Hybrid | AC50: EU-CC101 | AD50: Full Time | AE50: 71.6
A51: E0047 | B51: Kacper Wagner | C51: Female | D51: 55 | E51: 26051 | F51: Finance | G51: Corporate Services | H51: Payroll Specialist | I51: L3 | J51: M007 | K51: Astrid Bakker | L51: Frankfurt | M51: Germany | N51: Hesse | O51: 43201 | Q51: ACTIVE | R51: 81000 | S51: 4000 | T51: THREE | U51: 27 | V51: 17 | W51: 14 | X51: 59 | Y51: Not promoted | Z51: Master's | AA51: LinkedIn | AB51: Hybrid | AC51: EU-CC301 | AD51: Contract | AE51: 57.4
A52: E0048 | B52: Agnes Wagner | C52: Female | D52: 31 | E52: 34781 | F52: PMO Product | G52: product & technology | H52: Lead Product Manager | I52: L4 | J52: M027 | K52: Miguel Persson | L52: Gothenburg | M52: Sweden | N52: Vastra Gotaland | O52: 42543 | Q52: A | S52: 5700 | T52: 3 | U52: 24 | V52: 2 | W52: 12 | X52: 73 | Y52: NO | Z52: MBA | AA52: European Job Board | AB52: Remote | AC52: EU-CC102 | AD52: Full Time | AE52: 62.5
A53: E0049 | B53: Liam Colombo | C53: male | D53: 40 | E53: 31382 | F53: Customer Success | G53: Revenue | H53: Support Specialist | I53: L3 | J53: M032 | K53: Hannah Wagner | L53: Wroclaw | M53: Poland | N53: Lower Silesian | O53: 43222 | Q53: Active | R53: 59000 | S53: 3000 | T53: 3 | U53: 42 | V53: 23 | W53: 16 | X53: 55 | Y53: Not Promoted | Z53: Master's | AA53: Internal Transfer | AB53: Hybrid | AC53: EU-CC202 | AD53: Full Time | AE53: 58.2
A54: E0050 | B54: Giulia Schmidt | C54: F | D54: 36 | E54: 32808 | F54: Regulatory | G54: Risk & Compliance | H54: Regulatory Specialist | I54: L5 | J54: M012 | K54: Zofia Petit | L54: Paris | M54: France | N54: Ile-de-France | O54: 44015 | Q54: Active | R54: 130000 | S54: 19500 | T54: 5 | U54: 33 | V54: 6 | W54: 13 | X54: 69 | Y54: Not Promoted | Z54: Master's | AA54: Indeed | AB54: Hybrid | AC54: EU-CC502 | AD54: FTE | AE54: 80.9
A55: E0051 | B55: freja smith | C55: Female | D55: 23 | E55: 37655 | F55: Product | G55: PRODUCT & TECHNOLOGY | H55: Lead Product Manager | I55: L2 | J55: M053 | K55: Hugo Costa | L55: PAR | M55: France | N55: Ile-de-France | O55: 45392 | P55: 45726 | Q55: EXITED | R55: 58000 | S55: 5200 | T55: 4 | U55: 43 | V55: 24 | W55: 10 | X55: 61 | Y55: Not Promoted | Z55: Bachelor's | AA55: University Hiring | AB55: Hybrid | AC55: EU-CC102 | AD55: Full Time | AE55: 72.3
A56: E0052 | B56: Oliver Svensson | C56: Male | D56: 58 | E56: 24790 | F56: Product Mgmt | G56: Product & Technology | H56: Lead Product Manager | I56: L3 | J56: M038 | K56: Sophia Moreau | L56: London | M56: United Kingdom | N56: England | O56: 44830 | Q56: Active | R56: 86000 | S56: 4300 | T56: 3 | U56: 7 | V56: 16 | W56: 18 | X56: 62 | Y56: Not Promoted | Z56: HIGH SCHOOL | AA56: Employee Referral | AB56: Hybrid | AC56: EU-CC102 | AD56: full time | AE56: 51.5
A57: E0053 | B57: Leon Sousa | C57: Female | D57: 43 | E57: 30413 | F57: ENGINERING | G57: Product & Technology | H57: Engineering Lead | I57: L3 | J57: M030 | K57: Sem Thomas | L57: Milano | M57: Italy | N57: Lombardy | O57: 12-16-2023 | Q57: Active | R57: 77000 | S57: 1500 | T57: 2 | U57: 26 | V57: 7 | W57: 11 | X57: 61 | Y57: Not Promoted | Z57: Bachelor's | AA57: LinkedIn | AB57: Hybrid | AC57: EU-CC101 | AD57: Full Time | AE57: 50.3
A58: E0054 | B58: Matteo Gomez | C58: Male | D58: 24 | E58: 37090 | F58: Product | G58: Product & Technology | H58: Product Analyst | I58: L2 | J58: M038 | K58: Sophia Moreau | L58: Munich | M58: Germany | N58: Bavaria | O58: 45486 | Q58: Active | R58: 69000 | S58: 3400 | T58: THREE | U58: 37 | V58: 13 | W58: 0 | X58: 66 | Y58: Not Promoted | Z58: Bachelor's | AA58: Employee Referral | AB58: Hybrid | AC58: EU-CC102 | AD58: FULL-TIME | AE58: 69.3
A59: E0055 | B59: ASTRID THOMAS | C59: Female | D59: 42 | E59: 30795 | F59: Engineering | G59: Product & Technology | H59: BACKEND ENGINEER | I59: L3 | J59: M044 | K59: Sophia Russo | L59: Madrid | M59: Spain | N59: Community of Madrid | O59: 44545 | Q59: Active | R59: 58000 | S59: 5200 | T59: 4 | U59: 0 | V59: 34 | W59: 8 | X59: 98 | Y59: Not Promoted | Z59: Diploma | AA59: Company Careers Page | AB59: Hybrid | AC59: EU-CC101 | AD59: Full Time | AE59: 76.3
A60: E0056 | B60: Lucas Brown | C60: Male | D60: 60 | E60: 23925 | F60: Operations | G60: Operations | H60: Operations Analyst | I60: L1 | J60: M010 | K60: lotte muller | L60: Krakow | M60: POLAND | N60: Lesser Poland | O60: 44031 | P60: 27/08/2021 | Q60: Exited | R60: 29000 | S60: 4100 | T60: 5 | U60: 25 | V60: 5 | W60: 3 | X60: 67 | Y60: Not Promoted | Z60: Master's | AA60: University Hiring | AB60: Remote | AC60: EU-CC401 | AD60: Full Time | AE60: 83.2
A61: E0057 | B61: Nathan Fernandez | C61: Female | D61: 57 | E61: 25308 | F61: Data & Analytics | G61: Data & AI | H61: Data Scientist | I61: L2 | J61: M020 | K61: Alessandro Lewandowski | L61: REMOTE | M61: Europe | N61: REMOTE | O61: 44050 | P61: 45886 | Q61: Exited | R61: 45000 | S61: 900 | T61: 2 | U61: 45 | V61: 14 | W61: 37 | X61: 39 | Y61: Not Promoted | Z61: Master's | AA61: Employee Referral | AB61: Hybrid | AC61: EU-CC103 | AD61: Full Time | AE61: 41.6
A62: E0058 | B62: Fleur Martin | C62: Female | D62: 33 | E62: 33949 | F62: Customer Success | G62: REVENUE | H62: support specialist | I62: L2 | J62: M024 | K62: Noah Ryan | L62: Berlin | M62: Germany | N62: Berlin | O62: 44730 | Q62: ACTIVE | R62: 57000 | S62: 8000 | T62: 5 | U62: 41 | V62: 25 | W62: 20 | X62: 79 | Y62: Not Promoted | Z62: Bachelor's | AA62: Company Careers Page | AB62: Hybrid | AC62: EU-CC202 | AD62: Contract | AE62: 82.7
A63: E0059 | B63: Freya Wagner | C63: Non-Binary | D63: 26 | E63: 1999/10/28 | F63: Customer Success | G63: Revenue | H63: Support Specialist | I63: L3 | J63: M024 | K63: Noah Ryan | L63: Warsaw | M63: Poland | N63: masovian | O63: 43006 | P63: 43604 | Q63: Exited | R63: 58000 | S63: 2900 | T63: 3 | U63: 28 | V63: 31 | W63: 4 | X63: 56 | Y63: NO | Z63: Diploma | AA63: University Hiring | AB63: Hybrid | AC63: EU-CC202 | AD63: Full Time
A64: E0060 | B64: hannah murphy | C64: Male | D64: 56 | E64: 25686 | F64: Customer Success | G64: Revenue | H64: SUPPORT SPECIALIST | I64: L2 | J64: M024 | K64: Noah Ryan | L64: Barcelona | M64: Spain | N64: Catalonia | O64: 45210 | Q64: Actve | R64: 51000 | S64: 4600 | T64: 4 | U64: 27 | V64: 15 | W64: 4 | X64: 59 | Y64: Not Promoted | Z64: Master's | AA64: Company Careers Page | AB64: HYBRID | AC64: EU-CC202 | AD64: Full Time | AE64: 71.4
A65: E0061 | B65: Claudia De Jong | C65: Female | D65: 41 | E65: 30965 | F65: Data & Analytics | G65: Data & AI | H65: Data Scientist | I65: L4 | J65: M037 | K65: Elsa Andersson | L65: LYON | M65: France | N65: Auvergne-Rhone-Alpes | O65: 45000 | Q65: ACTIVE | R65: 99000 | S65: 5000 | T65: three | U65: 38 | V65: 25 | W65: 0 | X65: 98 | Y65: Not Promoted | Z65: Bachelor's | AA65: Company Careers Page | AB65: Office | AC65: EU-CC103 | AD65: Full Time | AE65: 80.8
A66: E0062 | B66: Axel Fischer | C66: M | D66: 51 | E66: 13/04/1975 | F66: Data & Analytics | G66: Data & AI | H66: data analyst | I66: L2 | J66: M003 | K66: Sarah Lopez | L66: Munich | M66: Germany | N66: Bavaria | O66: 44483 | Q66: Active | R66: 69000 | S66: 1400 | T66: 2 | U66: 16 | V66: 23 | W66: 6 | X66: 77 | Y66: Not Promoted | Z66: Bachelor's | AA66: European Job Board | AB66: Hybrid | AC66: EU-CC103 | AD66: Full Time | AE66: 56
A67: E0063 | B67: Thomas Schmidt | C67: Female | D67: 54 | E67: 26230 | F67: Security | G67: Risk & Compliance | H67: SOC Analyst | I67: L2 | J67: M014 | K67: Elena Szymanski | L67: London | M67: United Kingdom | N67: England | O67: 44887 | Q67: Active | R67: 62000 | S67: 5600 | T67: 4 | U67: 1 | V67: 21 | W67: 9 | X67: 50 | Y67: Not Promoted | Z67: BACHELOR'S | AA67: University Hiring | AB67: HYBRID | AC67: EU-CC503 | AD67: Full Time | AE67: 59.2
A68: E0064 | B68: Klara Lopez | C68: Male | D68: 57 | E68: 25225 | F68: Unknown Dept | G68: Operations | H68: Operations Analyst | I68: L3 | J68: M010 | K68: Lotte Muller | L68: Remote - Europe | M68: EUROPE | N68: Remote | O68: 44365 | Q68: Active | R68: 78000 | S68: 3900 | T68: 3 | U68: 9 | V68: 14 | W68: 16 | X68: 65 | Y68: Not Promoted | Z68: Bachelor's | AA68: European Job Board | AB68: Hybrid | AC68: EU-CC401 | AD68: full time | AE68: 54
A69: E0065 | B69: SOFIA BECKER | C69: Male | D69: 61 | E69: 23744 | F69: ENGG | G69: Product & Technology | H69: Engineering Lead | I69: L7 | J69: M057 | K69: Emma Karlsson | L69: MUNICH | M69: Germany | N69: Bavaria | O69: 44092 | Q69: Active | R69: 264000 | S69: 15800 | T69: 3 | U69: 34 | V69: 15 | W69: 19 | X69: 71 | Y69: Not Promoted | Z69: Bachelor's | AA69: LinkedIn | AB69: Hybrid | AC69: EU-CC101 | AD69: Full Time | AE69: 60.8
A70: E0066 | B70: hugo nilsson | C70: Male | D70: 25 | E70: 36758 | F70: Client Success | G70: Revenue | H70: Implementation Consultant | I70: L3 | J70: M024 | K70: Noah Ryan | L70: Milan | M70: Italy | N70: lombardy | O70: 43761 | P70: 43928 | Q70: Exited | R70: 69000 | S70: 3400 | T70: 3 | U70: 28 | V70: 22 | W70: 4 | X70: 48 | Y70: Not Promoted | Z70: Master's | AA70: LinkedIn | AB70: hybrid | AC70: EU-CC202 | AD70: Full Time | AE70: 58.8
A71: E0067 | B71: Axel Nowak | C71: non-binary | D71: 52 | E71: 26925 | F71: Sales | G71: Revenue | H71: Sales Development Representative | I71: L6 | J71: M023 | K71: Alice Greco | L71: Rotterdam | M71: Netherlands | N71: South Holland | O71: 45282 | Q71: active | R71: 181000 | S71: 10900 | T71: 3 | U71: 27 | V71: 19 | W71: 5 | X71: 62 | Y71: no | Z71: PhD | AA71: Internal Transfer | AB71: remote | AC71: EU-CCXXX | AD71: Full Time | AE71: 63
A72: E0068 | B72: Daniel Kowalski | C72: Male | D72: 57 | E72: 25228 | F72: Data & Analytics | G72: Data & AI | H72: Senior Data Analyst | I72: L3 | J72: M058 | K72: Lukas Esposito | L72: Brussels | M72: Belgium | N72: Brussels-Capital | O72: 06-25-2021 | Q72: active | R72: 72000 | S72: 3600 | T72: 3 | U72: 21 | V72: 8 | W72: 5 | X72: 68 | Y72: Not Promoted | Z72: Bachelor's | AA72: University Hiring | AB72: Remote | AC72: EU-CC103 | AD72: Full Time | AE72: 63.5
A73: E0069 | B73: Axel Doyle | C73: Male | D73: 28 | E73: 35645 | F73: IT | G73: Product & Technology | H73: IT Support Analyst | I73: L2 | J73: M045 | K73: Bram Robert | L73: Berlin | M73: Germany | N73: Berlin | O73: 14/02/2019 | Q73: Active | R73: 57000 | S73: 5100 | T73: FOUR | U73: 44 | V73: 28 | W73: 17 | X73: 68 | Y73: Not Promoted | Z73: Master's | AA73: European Job Board | AB73: Hybrid | AC73: EU-CC104 | AD73: FTE | AE73: 71.3
A74: E0070 | B74: Eva Nowak | C74: Male | D74: 25 | E74: 37011 | F74: Finance | G74: Corporate Services | H74: Financial Analyst | I74: L2 | J74: M036 | K74: Beatrice Meyer | L74: PARIS | M74: France | N74: Ile-de-France | O74: 45318 | Q74: Active | R74: 60000 | S74: 8400 | T74: 5 | U74: 50 | V74: 11 | W74: 12 | X74: 75 | Y74: Not Promoted | Z74: Diploma | AA74: Agency | AB74: Hybrid | AC74: EU-CC301 | AD74: INTERN | AE74: 85.2
A75: E0071 | B75: Claudia Perez | C75: Female | D75: 30 | E75: 34972 | F75: Client Success | G75: Revenue | H75: Customer Success Manager | I75: L2 | J75: M050 | K75: Louis Szymanski | L75: Dublin | M75: Ireland | N75: leinster | O75: 44339 | P75: 45937 | Q75: Exited | R75: 57000 | S75: 2800 | T75: 3 | U75: 29 | V75: 24 | W75: 6 | X75: 47 | Y75: Not Promoted | Z75: Bachelor's | AA75: AGENCY | AB75: Office | AC75: EU-CC202 | AD75: Full Time | AE75: 57.7
A76: E0072 | B76: nathan becker | C76: MALE | D76: 37 | E76: 32670 | F76: DATA & ANALYTICS | G76: Data & AI | H76: Analytics Engineer | I76: L2 | J76: M037 | K76: Elsa Andersson | L76: Munich | M76: Germany | N76: Bavaria | O76: 44935 | Q76: A | R76: 65000 | S76: 1300 | T76: 2 | U76: 31 | V76: 19 | W76: 3 | X76: 67 | Y76: Not Promoted | Z76: Master's | AA76: Internal Transfer | AB76: Hybrid | AC76: EU-CC103 | AD76: full time | AE76: 57.7
A77: E0073 | B77: Noor Zielinski | C77: Female | D77: 36 | E77: 32970 | F77: Customer Success | G77: Revenue | H77: Client Success Associate | I77: L3 | J77: M054 | K77: Isla Eriksson | L77: Stockholm | M77: Sweden | N77: Stockholm County | O77: 45926 | Q77: Active | R77: 75000 | S77: 3800 | T77: 3 | U77: 24 | V77: 0 | W77: 20 | X77: 69 | Y77: Not promoted | Z77: Master's | AA77: Employee Referral | AB77: Remote | AC77: EU-CC202 | AD77: Full Time | AE77: 57.1
A78: E0074 | B78: ERIK LOPEZ | C78: Male | D78: 56 | E78: 25657 | F78: ENGG | G78: Product & Technology | H78: Frontend Engineer | I78: L5 | J78: M001 | K78: Milan Leroy | L78: STOCKHOLM | M78: SWEDEN | N78: Stockholm County | O78: 45141 | Q78: Active | R78: 146000 | S78: 4400 | T78: 2 | U78: 32 | V78: 20 | W78: 1 | X78: 53 | Y78: no | Z78: Master's | AA78: Internal Transfer | AB78: Hybrid | AC78: EU-CC101 | AD78: Full Time | AE78: 54
A79: E0075 | B79: Oliver Oliveira | C79: Male | D79: 26 | E79: 36668 | F79: Techh | G79: REVENUE | H79: Regional Sales Manager | I79: L4 | J79: M004 | K79: Giovanni Leroy | L79: Lisbon | M79: Portugal | N79: Lisbon District | O79: 42584 | Q79: ACTIVE | R79: 74000 | S79: 1500 | T79: 2 | U79: 11 | V79: 6 | W79: 20 | X79: 54 | Y79: Not Promoted | Z79: Master's | AA79: European Job Board | AB79: Remote | AC79: EU-CC201 | AD79: Contract | AE79: 39.6
A80: E0076 | B80: Natalia Muller | C80: Female | D80: 56 | E80: 25665 | F80: Finance | G80: Corporate Services | H80: Finance Manager | I80: L2 | J80: M059 | K80: Lars Petit | L80: Rotterdam | M80: Netherlands | N80: south holland | O80: 2023/04/27 | P80: 45179 | Q80: Exited | R80: 63000 | S80: 3200 | T80: 3 | U80: 13 | V80: 18 | W80: 13 | X80: 69 | Y80: Not Promoted | Z80: Bachelor's | AA80: University Hiring | AB80: Remote | AC80: EU-CC301 | AD80: Full Time | AE80: 57.9
A81: E0077 | B81: Elias Williams | C81: Female | D81: 48 | E81: 1977/08/04 | F81: IT | G81: Product & Technology | H81: IT Support Analyst | I81: L5 | J81: M022 | K81: Lucas Ryan | L81: Berlin | M81: Germany | N81: BERLIN | O81: 01-15-2017 | Q81: ACTIVE | R81: -151000 | S81: 1500 | T81: ONE | U81: 23 | V81: 7 | W81: 12 | X81: 60 | Y81: Not Promoted | Z81: Master's | AA81: LinkedIn | AB81: Office | AC81: EU-CC104 | AD81: INTERN | AE81: 39.8
A82: E0078 | B82: Sarah Pereira | C82: Female | D82: 58 | E82: 24697 | F82: Ops | G82: Operations | H82: Operations Manager | I82: L4 | J82: M017 | K82: Ines Karlsson | L82: Europe Hub | M82: Belgium | N82: Brussels-Capital | O82: 45908 | Q82: active | R82: 98000 | S82: 4900 | T82: 3 | U82: 7 | V82: 8 | W82: 18 | X82: 79 | Y82: Not Promoted | Z82: Bachelor's | AA82: LinkedIn | AB82: Remote | AC82: EU-CC401 | AD82: Part Time | AE82: 57.4
A83: E0079 | B83: Emilia Perez | C83: Male | D83: 48 | E83: 28446 | F83: TECH | G83: Product & Technology | H83: PLATFORM ENGINEER | I83: L3 | J83: M044 | K83: Sophia Russo | L83: Berln | M83: Germany | N83: BERLIN | O83: 43804 | Q83: Active | R83: 90000 | S83: 4500 | T83: three | U83: 39 | V83: 13 | W83: 16 | X83: 70 | Y83: no | Z83: Bachelor's | AA83: Employee Referral | AB83: Remote | AC83: EU-CC101 | AD83: Contract | AE83: 63.2
A84: E0080 | B84: Ben Martin | C84: Female | D84: 34 | E84: 33743 | F84: Data & Analytics | G84: DATA & AI | H84: Senior Data Analyst | I84: L4 | J84: M003 | K84: Sarah Lopez | L84: Brussel | M84: Belgium | N84: Brussels-Capital | O84: 2026-15-09 | Q84: Active | R84: 96000 | S84: 4800 | T84: 3 | U84: 32 | V84: 11 | W84: 17 | X84: 58 | Y84: no | Z84: Bachelor's | AA84: Employee Referral | AB84: Hybrid | AC84: EU-CC103 | AD84: Full Time | AE84: 56.8
A85: E0081 | B85: Milan Doyle | C85: Female | D85: 35 | E85: 11-23-1990 | F85: Procurement | G85: Operations | H85: Sourcing Specialist | I85: L3 | J85: M029 | K85: Jan Gonzalez | L85: LILLE | M85: France | N85: hauts-de-france | O85: 45055 | Q85: Active | R85: 79000 | S85: 4000 | T85: three | U85: 30 | V85: 4 | W85: 12 | X85: 53 | Y85: Not Promoted | Z85: Bachelor's | AA85: Agency | AB85: Hybrid | AC85: EU-CC402 | AD85: Full Time | AE85: 57
A86: E0082 | B86: LEA COSTA | C86: Male | D86: 38 | E86: 32025 | F86: Procurement | G86: Operations | H86: Procurement Lead | I86: L3 | J86: M029 | K86: Jan Gonzalez | L86: Dublin | M86: ireland | N86: Leinster | O86: 44031 | Q86: Active | R86: 82000 | S86: 7400 | T86: 4 | U86: 20 | V86: 10 | W86: 22 | X86: 40 | Y86: Not Promoted | Z86: Bachelor's | AA86: Indeed | AB86: hybrid | AC86: EU-CC402 | AD86: FULL-TIME | AE86: 55
A87: E0083 | B87: Lea Ferreira | C87: female | D87: 33 | E87: 33857 | F87: Corporate Strategy | G87: Corporate Services | H87: Strategy Analyst | I87: L6 | J87: M015 | K87: Lea Ryan | L87: Porto | M87: Portugal | N87: porto district | O87: 44940 | Q87: Actve | R87: 133000 | S87: 4000 | T87: two | U87: 28 | V87: 18 | W87: 8 | X87: 59 | Y87: Not Promoted | Z87: Master's | AA87: European Job Board | AB87: hybrid | AC87: EU-CC303 | AD87: Full Time | AE87: 51.6
A88: E0084 | B88: Daniela Andersson | C88: male | D88: 23 | E88: 37515 | F88: Information Tech | G88: Product & Technology | H88: IT Manager | I88: L3 | J88: M009 | K88: Maja Nilsson | L88: Amsterdam | M88: Netherlands | N88: North Holland | O88: 45133 | Q88: Actve | R88: 73000 | S88: 10200 | T88: five | U88: 15 | V88: 14 | W88: 6 | X88: 70 | Y88: Not Promoted | Z88: Master's | AA88: Employee Referral | AB88: Hybrid | AC88: EU-CC104 | AD88: full time | AE88: 80.2
A89: E0085 | B89: Nils Jansen | C89: NB | D89: 36 | E89: 12/01/1990 | F89: Human Resources | G89: Corporate Services | H89: HR Associate | I89: L4 | J89: M008 | K89: Mia Szymanski | L89: Unknown Office | M89: France | N89: Ile-de-France | O89: 02/08/2020 | Q89: ACTIVE | R89: 119000 | S89: 2400 | T89: 2 | U89: 33 | V89: -6 | W89: 0 | X89: 88 | Y89: no | Z89: phd | AA89: LinkedIn | AB89: hybrid | AC89: EU-CC302 | AD89: Contract | AE89: 67
A90: E0086 | B90: Emil Garcia | C90: Male | D90: 26 | E90: 36341 | F90: Procurement | G90: Operations | H90: Procurement Analyst | I90: L5 | J90: M013 | K90: Ebba Kelly | L90: Lisbon | M90: Portugal | N90: Lisbon District | O90: 43940 | Q90: A | R90: 118000 | S90: 11800 | T90: 4 | U90: 33 | V90: 12 | W90: 1 | X90: 65 | Y90: Not Promoted | Z90: Master's | AA90: Agency | AB90: Hybrid | AC90: EU-CC402 | AD90: FTE | AE90: 76.5
A91: E0087 | B91: Lukas Lopez | C91: Female | D91: 44 | E91: 30089 | F91: Engineering | G91: Product & Technology | H91: Software Engineer | I91: L2 | J91: M039 | K91: Freya Martinez | L91: MADRID | M91: Spain | N91: Community of Madrid | O91: 45212 | Q91: A | R91: 47000 | S91: 2400 | T91: 3 | U91: 26 | V91: 7 | W91: 13 | X91: 79 | Y91: Not Promoted | Z91: Bachelor's | AA91: Indeed | AB91: Hybrid | AC91: EU-CC101 | AD91: Full Time | AE91: 64.7
A92: E0088 | B92: Felix Sousa | C92: Female | D92: 37 | E92: 32636 | F92: Engineering | G92: Product & Technology | H92: Engineering Lead | I92: L2 | J92: M057 | K92: Emma Karlsson | L92: Barca | M92: Spain | N92: Catalonia | O92: 45455 | P92: 45550 | Q92: Exited | R92: 57000 | S92: 2800 | T92: 3 | U92: 28 | V92: 16 | W92: 1 | X92: 64 | Y92: no | Z92: Bachelor's | AA92: Employee Referral | AB92: Office | AC92: EU-CC101 | AD92: Full Time | AE92: 65.9
A93: E0089 | B93: Ben Olsson | C93: FEMALE | D93: 42 | E93: 30650 | F93: Engineering | G93: PRODUCT & TECHNOLOGY | H93: Software Engineer | I93: L3 | J93: M051 | K93: Eva Bianchi | L93: Europe Hub | M93: belgium | N93: Brussels-Capital | O93: 45766 | Q93: Active | R93: 82000 | S93: 1600 | T93: 2 | U93: 22 | V93: 20 | W93: 15 | X93: 63 | Y93: no | Z93: Bachelor's | AA93: Internal Transfer | AB93: HYBRID | AC93: EU-CC101 | AD93: Full Time | AE93: 48
A94: E0090 | B94: luuk jansen | C94: Female | D94: 53 | E94: 26525 | F94: Fin | G94: Corporate Services | H94: Finance Manager | I94: L3 | J94: M043 | K94: Martina Pereira | L94: London | M94: United Kingdom | N94: England | O94: 44482 | Q94: Actve | R94: 80000 | S94: 4000 | T94: 3 | U94: 33 | V94: 2 | W94: 16 | X94: 62 | Y94: no | Z94: Bachelor's | AA94: University Hiring | AB94: Hybrid | AC94: EU-CC301 | AD94: Full Time | AE94: 59
A95: E0091 | B95: Matteo Kowalski | C95: Male | D95: 53 | E95: 26535 | F95: Operation | G95: Operations | H95: Process Lead | I95: L2 | J95: M017 | K95: Ines Karlsson | L95: Frankfurt | M95: Germany | N95: Hesse | O95: 45766 | Q95: ACTIVE | R95: 53000 | S95: 4800 | T95: 4 | U95: 43 | V95: 16 | W95: 17 | X95: 66 | Y95: Not promoted | Z95: Master's | AA95: Employee Referral | AB95: Remote | AC95: EU-CC401 | AD95: Full Time | AE95: 70.6
A96: E0092 | B96: Marco Byrne | C96: Female | D96: 41 | E96: 31089 | F96: Data & Analytics | G96: data & ai | H96: Data Scientist | I96: L2 | J96: M058 | K96: Lukas Esposito | L96: london | M96: United Kingdom | N96: England | O96: 45888 | Q96: Active | R96: 62000 | S96: 8700 | T96: 5 | U96: 18 | V96: 6 | W96: 14 | X96: 64 | Y96: Not Promoted | Z96: Bachelor's | AA96: Employee Referral | AB96: Office | AC96: EU-CC103 | AD96: Full Time | AE96: 74.9
A97: E0093 | B97: Zofia Bernard | C97: Female | D97: 24 | E97: 30/08/2001 | F97: Corporate Strategy | G97: Corporate Services | H97: Transformation Lead | I97: L4 | J97: M015 | K97: Lea Ryan | L97: REMOTE - EUROPE | M97: Europe | N97: Remote | O97: 44200 | Q97: Active | R97: 98000 | S97: 4900 | T97: 3 | U97: 10 | V97: 10 | W97: 3 | X97: 69 | Y97: Not Promoted | Z97: Master's | AA97: Indeed | AB97: Hybrid | AC97: EU-CC303 | AD97: Full Time | AE97: 62.1
A98: E0094 | B98: Leon De Jong | C98: Male | D98: 27 | E98: 36266 | F98: Operation | G98: Operations | H98: Process Lead | I98: L4 | J98: M017 | K98: Ines Karlsson | L98: Frankfurt | M98: Germany | N98: Hesse | O98: 45551 | Q98: A | R98: 97000 | S98: 8700 | T98: four | U98: 19 | V98: 15 | W98: 25 | X98: 73 | Y98: Promoted | Z98: Bachelor's | AA98: Employee Referral | AB98: Hybrid | AC98: EU-CC401 | AD98: Full Time | AE98: 66.3
A99: E0095 | B99: Milan Sanchez | C99: MALE | D99: 32 | E99: 34330 | F99: Marketing | G99: REVENUE | H99: Growth Marketer | I99: L6 | K99: Aleksander Fischer | L99: Barcelona | M99: spain | N99: Catalonia | O99: 43418 | Q99: Active | R99: 169000 | S99: 16900 | T99: 4 | U99: 11 | V99: 17 | W99: 18 | X99: 69 | Y99: Not Promoted | Z99: Master's | AA99: Employee Referral | AB99: Hybrid | AC99: EU-CC203 | AD99: FTE | AE99: 63.9
A100: E0096 | B100: Martina Thomas | C100: male | D100: 34 | E100: 33535 | F100: Engineering | G100: Product & Technology | H100: frontend engineer | I100: L4 | K100: Jack Schmidt | L100: REMOTE | M100: Europe | N100: Remote | O100: 44032 | Q100: A | R100: 87000 | S100: 4400 | T100: 3 | U100: 16 | V100: 16 | W100: 4 | X100: 46 | Y100: Not Promoted | Z100: MBA | AA100: Employee Referral | AB100: Hybrid | AC100: EU-CC101 | AD100: Full Time | AE100: 55.1
A101: E0097 | B101: Sem Mulder | C101: Male | D101: 45 | E101: 29396 | F101: Engineering | G101: Product & Technology | H101: Platform Engineer | I101: L3 | J101: M030 | K101: Sem Thomas | L101: Madrid | M101: Spain | N101: community of madrid | O101: 44429 | Q101: Active | R101: 76000 | S101: 10600 | T101: 5 | U101: 27 | V101: 18 | W101: 10 | X101: 83 | Y101: no | Z101: Master's | AA101: Agency | AB101: Remote | AC101: EU-CC101 | AD101: full time | AE101: 85.8
...

Sheet 01_clean_data
A1: Employee ID | B1: Employee Name | C1: Gender | D1: Age | E1: Date of Birth | F1: DOB FLAGS | G1: Department | H1: Business Unit | I1: Designation | J1: Job Level | K1: Manager ID | L1: Manager Name | M1: Location | N1: Country | O1: State | P1: Joining Date | Q1: Exit Date | R1: Employment Status | S1: Salary | T1: Bonus | U1: Performance Rating | V1: Training Hours | W1: Leave Taken | X1: Overtime Hours | Y1: Employee Engagement Score | Z1: Promotion Status | AA1: Education Level | AB1: Recruitment Source | AC1: Work Mode | AD1: Cost Center | AE1: Employee Type | AF1: Productivity Score
A2: ="E"&TEXT(VALUE(SUBSTITUTE(UPPER(TRIM('01_raw_data'!A5)),"E","")),"0000") -> E0001 | B2: =IF('01_raw_data'!B5="", "", PROPER(TRIM('01_raw_data'!B5))) -> Tess Martin | C2: =_xlfn.XLOOKUP(PROPER(TRIM('01_raw_data'!C5)),'03_lookups'!$A$4:$A$9,'03_lookups'!$B$4:$B$9,"Needs Review") -> Male | D2: =VALUE('01_raw_data'!D5) -> 56 | E2: =IF(OR('01_raw_data'!E5="", LOWER(TRIM('01_raw_data'!E5))="not available"), "Missing", '01_raw_data'!E5) -> 25373 | F2: =IF(OR(E2="",LOWER(TRIM(E2))="not available"),"Missing",IF(ISNUMBER(E2),"Valid","Needs Review")) -> Valid | G2: =_xlfn.XLOOKUP(UPPER(TRIM('01_raw_data'!F5)),'04_departments'!A5:A60,'04_departments'!C5:C60,"Needs Review") -> Data & Analytics | H2: =_xlfn.XLOOKUP('01_clean_data'!G2, '04_departments'!$C$5:$C$60,'04_departments'!$D$5:$D$60,"Needs Review") -> Data & AI | I2: =PROPER(TRIM('01_raw_data'!H5)) -> Senior Data Analyst | J2: =IFERROR(UPPER('01_raw_data'!I5), "") -> L6 | K2: =IFERROR(UPPER('01_raw_data'!J5), "") -> M003 | L2: =IFERROR(VLOOKUP(K2,'05_manager_mapping'!$A$5:$B$64,2), "Missing") -> Sarah Lopez | M2: =IFERROR(_xlfn.XLOOKUP('01_raw_data'!L5,'06_location_master'!$B$5:$B$60,'06_location_master'!$C$5:$C$60), "Missing Location") -> Valencia | N2: =IFERROR(_xlfn.XLOOKUP(M2,'06_location_master'!$C$5:$C$60,'06_location_master'!$D$5:$D$60), "Missing Country") -> Spain | O2: =IFERROR(_xlfn.XLOOKUP(M2,'06_location_master'!$C$5:$C$60,'06_location_master'!$E$5:$E$60), "Missing State") -> Valencian Community | P2: =IFERROR(--'01_raw_data'!O5,"Missing Date") -> 44869 | Q2: =IF(TRIM('01_raw_data'!P5)="","", IFERROR('01_raw_data'!P5, "check")) | R2: =IFERROR(IF(OR(UPPER(TRIM('01_raw_data'!Q5))="A",UPPER(TRIM('01_raw_data'!Q5)="ACTVE"),UPPER(TRIM('01_raw_data'!Q5))="ACTIVE"), "Active", IF(OR(UPPER(TRIM('01_raw_data'!Q5)="INACTIVE"),UPPER(TRIM('01_raw_data'!Q5))="INACTVE"),"Inactive",IF(OR(UPPER(TRIM('01_raw_data'!Q5))="EXITED"), "Exited", IF(OR(UPPER(TRIM('01_raw_data'!Q5))="TERMINATED"), "Terminated", IF(OR(UPPER(TRIM('01_raw_data'!Q5))="LEFT"),"Left",IF(OR(UPPER(TRIM('01_raw_data'!Q5))="RESIGNED"),"Resigned")))))),"Check") -> Active | S2: =IFERROR(IF(VALUE('01_raw_data'!R5)>0,VALUE('01_raw_data'!R5),"Check"),"Check") -> 134000 | T2: =IFERROR(IF(VALUE('01_raw_data'!S5)>0, VALUE('01_raw_data'!S5), "Check"), "Check") -> 4000 | U2: =IFERROR(VLOOKUP(UPPER(TRIM('01_raw_data'!T5)),'07_performance_master'!$A$5:$B$14,2,FALSE),"Check") -> 2 | V2: =IFERROR(IF(VALUE('01_raw_data'!U5)>0,VALUE('01_raw_data'!U5),"Check"),"Check") -> 35 | W2: =IFERROR(IF(VALUE('01_raw_data'!V5)>=0, VALUE('01_raw_data'!V5), "Check"), "Check") -> 20 | X2: =IFERROR(IF(VALUE('01_raw_data'!W5)>=0, VALUE('01_raw_data'!W5),"Check"), "Check") -> 10 | Y2: =IFERROR(IF(AND(VALUE('01_raw_data'!X5)>=0, VALUE('01_raw_data'!X5)<=100), VALUE('01_raw_data'!X5), "Check"), "Check") -> 74 | Z2: =IFERROR(IF(OR(UPPER(TRIM('01_raw_data'!Y5))="YES", UPPER(TRIM('01_raw_data'!Y5))="PROMOTED"),"Promoted", IF(OR(UPPER(TRIM('01_raw_data'!Y5))="NO",UPPER(TRIM('01_raw_data'!Y5))="NOT PROMOTED"), "Not Promoted", "Check")),"Check") -> Not Promoted | AA2: =IFERROR(PROPER(TRIM('01_raw_data'!Z5)), "") -> Master'S | AB2: =IFERROR(PROPER(TRIM('01_raw_data'!AA5)),"") -> University Hiring | AC2: =IFERROR(IF(UPPER(TRIM('01_raw_data'!AB5))="HYBRID","Hybrid",IF(OR(UPPER(TRIM('01_raw_data'!AB5))="REMOTE",UPPER(TRIM('01_raw_data'!AB5))="WFH",UPPER(TRIM('01_raw_data'!AB5))="WORK FROM HOME"),"Remote",IF(OR(UPPER(TRIM('01_raw_data'!AB5))="ONSITE",UPPER(TRIM('01_raw_data'!AB5))="ON-SITE",UPPER(TRIM('01_raw_data'!AB5))="OFFICE"),"Office"))),"Check") -> Hybrid | AD2: =IFERROR(VLOOKUP(UPPER(TRIM('01_raw_data'!AC5)),'09_cost_center'!$A$5:$E$19,1,FALSE), "Check") -> EU-CC103 | AE2: =IFERROR(IF(OR(UPPER(TRIM('01_raw_data'!AD5))="CONTRACT", UPPER(TRIM('01_raw_data'!AD5))="CONTRACTOR"), "Contract", IF(OR(PROPER(TRIM('01_raw_data'!AD5))="FTE", UPPER(TRIM('01_raw_data'!AD5))="FULL TIME", UPPER(TRIM('01_raw_data'!AD5))="FULL-TIME"), "Full Time", IF(OR(UPPER(TRIM('01_raw_data'!AD5))="INTERN", UPPER(TRIM('01_raw_data'!AD5))="INTERNSHIP"), "Intern", IF(OR(UPPER(TRIM('01_raw_data'!AD5))="PART TIME", UPPER(TRIM('01_raw_data'!AD5))="PART-TIME"), "Part Time")))), "Check") -> Contract | AF2: =IFERROR(IF(AND(VALUE('01_raw_data'!AE5)>=0,VALUE('01_raw_data'!AE5)<=100), VALUE('01_raw_data'!AE5), "Check"), "Check") -> 57.6
A3: ="E"&TEXT(VALUE(SUBSTITUTE(UPPER(TRIM('01_raw_data'!A6)),"E","")),"0000") -> E0002 | B3: =IF('01_raw_data'!B6="", "", PROPER(TRIM('01_raw_data'!B6))) -> Miguel Gonzalez | C3: =_xlfn.XLOOKUP(PROPER(TRIM('01_raw_data'!C6)),'03_lookups'!$A$4:$A$9,'03_lookups'!$B$4:$B$9,"Needs Review") -> Male | D3: =VALUE('01_raw_data'!D6) -> 25 | E3: =IF(OR('01_raw_data'!E6="", LOWER(TRIM('01_raw_data'!E6))="not available"), "Missing", '01_raw_data'!E6) -> 37009 | F3: =IF(OR(E3="",LOWER(TRIM(E3))="not available"),"Missing",IF(ISNUMBER(E3),"Valid","Needs Review")) -> Valid | G3: =_xlfn.XLOOKUP(UPPER(TRIM('01_raw_data'!F6)),'04_departments'!A6:A61,'04_departments'!C6:C61,"Needs Review") -> Finance | H3: =_xlfn.XLOOKUP('01_clean_data'!G3, '04_departments'!$C$5:$C$60,'04_departments'!$D$5:$D$60,"Needs Review") -> Corporate Services | I3: =PROPER(TRIM('01_raw_data'!H6)) -> Financial Analyst | J3: =IFERROR(UPPER('01_raw_data'!I6), "") -> L4 | K3: =IFERROR(UPPER('01_raw_data'!J6), "") -> M007 | L3: =IFERROR(VLOOKUP(K3,'05_manager_mapping'!$A$5:$B$64,2), "Missing") -> Astrid Bakker | M3: =IFERROR(_xlfn.XLOOKUP('01_raw_data'!L6,'06_location_master'!$B$5:$B$60,'06_location_master'!$C$5:$C$60), "Missing Location") -> Hamburg | N3: =IFERROR(_xlfn.XLOOKUP(M3,'06_location_master'!$C$5:$C$60,'06_location_master'!$D$5:$D$60), "Missing Country") -> Germany | O3: =IFERROR(_xlfn.XLOOKUP(M3,'06_location_master'!$C$5:$C$60,'06_location_master'!$E$5:$E$60), "Missing State") -> Hamburg | P3: =IFERROR(--'01_raw_data'!O6,"Missing Date") -> 43226 | Q3: =IF(TRIM('01_raw_data'!P6)="","", IFERROR('01_raw_data'!P6, "check")) | R3: =IFERROR(IF(OR(UPPER(TRIM('01_raw_data'!Q6))="A",UPPER(TRIM('01_raw_data'!Q6)="ACTVE"),UPPER(TRIM('01_raw_data'!Q6))="ACTIVE"), "Active", IF(OR(UPPER(TRIM('01_raw_data'!Q6)="INACTIVE"),UPPER(TRIM('01_raw_data'!Q6))="INACTVE"),"Inactive",IF(OR(UPPER(TRIM('01_raw_data'!Q6))="EXITED"), "Exited", IF(OR(UPPER(TRIM('01_raw_data'!Q6))="TERMINATED"), "Terminated", IF(OR(UPPER(TRIM('01_raw_data'!Q6))="LEFT"),"Left",IF(OR(UPPER(TRIM('01_raw_data'!Q6))="RESIGNED"),"Resigned")))))),"Check") -> Active | S3: =IFERROR(IF(VALUE('01_raw_data'!R6)>0,VALUE('01_raw_data'!R6),"Check"),"Check") -> 107000 | T3: =IFERROR(IF(VALUE('01_raw_data'!S6)>0, VALUE('01_raw_data'!S6), "Check"), "Check") -> 5400 | U3: =IFERROR(VLOOKUP(UPPER(TRIM('01_raw_data'!T6)),'07_performance_master'!$A$5:$B$14,2,FALSE),"Check") -> 3 | V3: =IFERROR(IF(VALUE('01_raw_data'!U6)>0,VALUE('01_raw_data'!U6),"Check"),"Check") -> 28 | W3: =IFERROR(IF(VALUE('01_raw_data'!V6)>=0, VALUE('01_raw_data'!V6), "Check"), "Check") -> 15 | X3: =IFERROR(IF(VALUE('01_raw_data'!W6)>=0, VALUE('01_raw_data'!W6),"Check"), "Check") -> 26 | Y3: =IFERROR(IF(AND(VALUE('01_raw_data'!X6)>=0, VALUE('01_raw_data'!X6)<=100), VALUE('01_raw_data'!X6), "Check"), "Check") -> 44 | Z3: =IFERROR(IF(OR(UPPER(TRIM('01_raw_data'!Y6))="YES", UPPER(TRIM('01_raw_data'!Y6))="PROMOTED"),"Promoted", IF(OR(UPPER(TRIM('01_raw_data'!Y6))="NO",UPPER(TRIM('01_raw_data'!Y6))="NOT PROMOTED"), "Not Promoted", "Check")),"Check") -> Not Promoted | AA3: =IFERROR(PROPER(TRIM('01_raw_data'!Z6)), "") -> Bachelor'S | AB3: =IFERROR(PROPER(TRIM('01_raw_data'!AA6)),"") -> Agency | AC3: =IFERROR(IF(UPPER(TRIM('01_raw_data'!AB6))="HYBRID","Hybrid",IF(OR(UPPER(TRIM('01_raw_data'!AB6))="REMOTE",UPPER(TRIM('01_raw_data'!AB6))="WFH",UPPER(TRIM('01_raw_data'!AB6))="WORK FROM HOME"),"Remote",IF(OR(UPPER(TRIM('01_raw_data'!AB6))="ONSITE",UPPER(TRIM('01_raw_data'!AB6))="ON-SITE",UPPER(TRIM('01_raw_data'!AB6))="OFFICE"),"Office"))),"Check") -> Hybrid | AD3: =IFERROR(VLOOKUP(UPPER(TRIM('01_raw_data'!AC6)),'09_cost_center'!$A$5:$E$19,1,FALSE), "Check") -> EU-CC301 | AE3: =IFERROR(IF(OR(UPPER(TRIM('01_raw_data'!AD6))="CONTRACT", UPPER(TRIM('01_raw_data'!AD6))="CONTRACTOR"), "Contract", IF(OR(PROPER(TRIM('01_raw_data'!AD6))="FTE", UPPER(TRIM('01_raw_data'!AD6))="FULL TIME", UPPER(TRIM('01_raw_data'!AD6))="FULL-TIME"), "Full Time", IF(OR(UPPER(TRIM('01_raw_data'!AD6))="INTERN", UPPER(TRIM('01_raw_data'!AD6))="INTERNSHIP"), "Intern", IF(OR(UPPER(TRIM('01_raw_data'!AD6))="PART TIME", UPPER(TRIM('01_raw_data'!AD6))="PART-TIME"), "Part Time")))), "Check") -> Full Time | AF3: =IFERROR(IF(AND(VALUE('01_raw_data'!AE6)>=0,VALUE('01_raw_data'!AE6)<=100), VALUE('01_raw_data'!AE6), "Check"), "Check") -> 49.4
A4: ="E"&TEXT(VALUE(SUBSTITUTE(UPPER(TRIM('01_raw_data'!A7)),"E","")),"0000") -> E0003 | B4: =IF('01_raw_data'!B7="", "", PROPER(TRIM('01_raw_data'!B7))) -> Hannah Wilson | C4: =_xlfn.XLOOKUP(PROPER(TRIM('01_raw_data'!C7)),'03_lookups'!$A$4:$A$9,'03_lookups'!$B$4:$B$9,"Needs Review") -> Male | D4: =VALUE('01_raw_data'!D7) -> 24 | E4: =IF(OR('01_raw_data'!E7="", LOWER(TRIM('01_raw_data'!E7))="not available"), "Missing", '01_raw_data'!E7) -> 37238 | F4: =IF(OR(E4="",LOWER(TRIM(E4))="not available"),"Missing",IF(ISNUMBER(E4),"Valid","Needs Review")) -> Valid | G4: =_xlfn.XLOOKUP(UPPER(TRIM('01_raw_data'!F7)),'04_departments'!A7:A62,'04_departments'!C7:C62,"Needs Review") -> Product | H4: =_xlfn.XLOOKUP('01_clean_data'!G4, '04_departments'!$C$5:$C$60,'04_departments'!$D$5:$D$60,"Needs Review") -> Product & Technology | I4: =PROPER(TRIM('01_raw_data'!H7)) -> Product Analyst | J4: =IFERROR(UPPER('01_raw_data'!I7), "") -> L2 | K4: =IFERROR(UPPER('01_raw_data'!J7), "") | L4: =IFERROR(VLOOKUP(K4,'05_manager_mapping'!$A$5:$B$64,2), "Missing") -> Missing | M4: =IFERROR(_xlfn.XLOOKUP('01_raw_data'!L7,'06_location_master'!$B$5:$B$60,'06_location_master'!$C$5:$C$60), "Missing Location") -> Krakow | N4: =IFERROR(_xlfn.XLOOKUP(M4,'06_location_master'!$C$5:$C$60,'06_location_master'!$D$5:$D$60), "Missing Country") -> Poland | O4: =IFERROR(_xlfn.XLOOKUP(M4,'06_location_master'!$C$5:$C$60,'06_location_master'!$E$5:$E$60), "Missing State") -> Lesser Poland | P4: =IFERROR(--'01_raw_data'!O7,"Missing Date") -> 45858 | Q4: =IF(TRIM('01_raw_data'!P7)="","", IFERROR('01_raw_data'!P7, "check")) | R4: =IFERROR(IF(OR(UPPER(TRIM('01_raw_data'!Q7))="A",UPPER(TRIM('01_raw_data'!Q7)="ACTVE"),UPPER(TRIM('01_raw_data'!Q7))="ACTIVE"), "Active", IF(OR(UPPER(TRIM('01_raw_data'!Q7)="INACTIVE"),UPPER(TRIM('01_raw_data'!Q7))="INACTVE"),"Inactive",IF(OR(UPPER(TRIM('01_raw_data'!Q7))="EXITED"), "Exited", IF(OR(UPPER(TRIM('01_raw_data'!Q7))="TERMINATED"), "Terminated", IF(OR(UPPER(TRIM('01_raw_data'!Q7))="LEFT"),"Left",IF(OR(UPPER(TRIM('01_raw_data'!Q7))="RESIGNED"),"Resigned")))))),"Check") -> Active | S4: =IFERROR(IF(VALUE('01_raw_data'!R7)>0,VALUE('01_raw_data'!R7),"Check"),"Check") -> 44000 | T4: =IFERROR(IF(VALUE('01_raw_data'!S7)>0, VALUE('01_raw_data'!S7), "Check"), "Check") -> 2200 | U4: =IFERROR(VLOOKUP(UPPER(TRIM('01_raw_data'!T7)),'07_performance_master'!$A$5:$B$14,2,FALSE),"Check") -> 3 | V4: =IFERROR(IF(VALUE('01_raw_data'!U7)>0,VALUE('01_raw_data'!U7),"Check"),"Check") -> 35 | W4: =IFERROR(IF(VALUE('01_raw_data'!V7)>=0, VALUE('01_raw_data'!V7), "Check"), "Check") -> 25 | X4: =IFERROR(IF(VALUE('01_raw_data'!W7)>=0, VALUE('01_raw_data'!W7),"Check"), "Check") -> 16 | Y4: =IFERROR(IF(AND(VALUE('01_raw_data'!X7)>=0, VALUE('01_raw_data'!X7)<=100), VALUE('01_raw_data'!X7), "Check"), "Check") -> 74 | Z4: =IFERROR(IF(OR(UPPER(TRIM('01_raw_data'!Y7))="YES", UPPER(TRIM('01_raw_data'!Y7))="PROMOTED"),"Promoted", IF(OR(UPPER(TRIM('01_raw_data'!Y7))="NO",UPPER(TRIM('01_raw_data'!Y7))="NOT PROMOTED"), "Not Promoted", "Check")),"Check") -> Not Promoted | AA4: =IFERROR(PROPER(TRIM('01_raw_data'!Z7)), "") -> Bachelor'S | AB4: =IFERROR(PROPER(TRIM('01_raw_data'!AA7)),"") -> Agency | AC4: =IFERROR(IF(UPPER(TRIM('01_raw_data'!AB7))="HYBRID","Hybrid",IF(OR(UPPER(TRIM('01_raw_data'!AB7))="REMOTE",UPPER(TRIM('01_raw_data'!AB7))="WFH",UPPER(TRIM('01_raw_data'!AB7))="WORK FROM HOME"),"Remote",IF(OR(UPPER(TRIM('01_raw_data'!AB7))="ONSITE",UPPER(TRIM('01_raw_data'!AB7))="ON-SITE",UPPER(TRIM('01_raw_data'!AB7))="OFFICE"),"Office"))),"Check") -> Remote | AD4: =IFERROR(VLOOKUP(UPPER(TRIM('01_raw_data'!AC7)),'09_cost_center'!$A$5:$E$19,1,FALSE), "Check") -> EU-CC102 | AE4: =IFERROR(IF(OR(UPPER(TRIM('01_raw_data'!AD7))="CONTRACT", UPPER(TRIM('01_raw_data'!AD7))="CONTRACTOR"), "Contract", IF(OR(PROPER(TRIM('01_raw_data'!AD7))="FTE", UPPER(TRIM('01_raw_data'!AD7))="FULL TIME", UPPER(TRIM('01_raw_data'!AD7))="FULL-TIME"), "Full Time", IF(OR(UPPER(TRIM('01_raw_data'!AD7))="INTERN", UPPER(TRIM('01_raw_data'!AD7))="INTERNSHIP"), "Intern", IF(OR(UPPER(TRIM('01_raw_data'!AD7))="PART TIME", UPPER(TRIM('01_raw_data'!AD7))="PART-TIME"), "Part Time")))), "Check") -> Full Time | AF4: =IFERROR(IF(AND(VALUE('01_raw_data'!AE7)>=0,VALUE('01_raw_data'!AE7)<=100), VALUE('01_raw_data'!AE7), "Check"), "Check") -> 63.6
A5: ="E"&TEXT(VALUE(SUBSTITUTE(UPPER(TRIM('01_raw_data'!A8)),"E","")),"0000") -> E0004 | B5: =IF('01_raw_data'!B8="", "", PROPER(TRIM('01_raw_data'!B8))) -> Bram Visser | C5: =_xlfn.XLOOKUP(PROPER(TRIM('01_raw_data'!C8)),'03_lookups'!$A$4:$A$9,'03_lookups'!$B$4:$B$9,"Needs Review") -> Male | D5: =VALUE('01_raw_data'!D8) -> 28 | E5: =IF(OR('01_raw_data'!E8="", LOWER(TRIM('01_raw_data'!E8))="not available"), "Missing", '01_raw_data'!E8) -> 12-01-1997 | F5: =IF(OR(E5="",LOWER(TRIM(E5))="not available"),"Missing",IF(ISNUMBER(E5),"Valid","Needs Review")) -> Needs Review | G5: =_xlfn.XLOOKUP(UPPER(TRIM('01_raw_data'!F8)),'04_departments'!A8:A63,'04_departments'!C8:C63,"Needs Review") -> Legal | H5: =_xlfn.XLOOKUP('01_clean_data'!G5, '04_departments'!$C$5:$C$60,'04_departments'!$D$5:$D$60,"Needs Review") -> Risk & Compliance | I5: =PROPER(TRIM('01_raw_data'!H8)) -> Contracts Analyst | J5: =IFERROR(UPPER('01_raw_data'!I8), "") -> L5 | K5: =IFERROR(UPPER('01_raw_data'!J8), "") -> M011 | L5: =IFERROR(VLOOKUP(K5,'05_manager_mapping'!$A$5:$B$64,2), "Missing") -> Julia Marino | M5: =IFERROR(_xlfn.XLOOKUP('01_raw_data'!L8,'06_location_master'!$B$5:$B$60,'06_location_master'!$C$5:$C$60), "Missing Location") -> Milan | N5: =IFERROR(_xlfn.XLOOKUP(M5,'06_location_master'!$C$5:$C$60,'06_location_master'!$D$5:$D$60), "Missing Country") -> Italy | O5: =IFERROR(_xlfn.XLOOKUP(M5,'06_location_master'!$C$5:$C$60,'06_location_master'!$E$5:$E$60), "Missing State") -> Lombardy | P5: =IFERROR(--'01_raw_data'!O8,"Missing Date") -> 44343 | Q5: =IF(TRIM('01_raw_data'!P8)="","", IFERROR('01_raw_data'!P8, "check")) | R5: =IFERROR(IF(OR(UPPER(TRIM('01_raw_data'!Q8))="A",UPPER(TRIM('01_raw_data'!Q8)="ACTVE"),UPPER(TRIM('01_raw_data'!Q8))="ACTIVE"), "Active", IF(OR(UPPER(TRIM('01_raw_data'!Q8)="INACTIVE"),UPPER(TRIM('01_raw_data'!Q8))="INACTVE"),"Inactive",IF(OR(UPPER(TRIM('01_raw_data'!Q8))="EXITED"), "Exited", IF(OR(UPPER(TRIM('01_raw_data'!Q8))="TERMINATED"), "Terminated", IF(OR(UPPER(TRIM('01_raw_data'!Q8))="LEFT"),"Left",IF(OR(UPPER(TRIM('01_raw_data'!Q8))="RESIGNED"),"Resigned")))))),"Check") -> Active | S5: =IFERROR(IF(VALUE('01_raw_data'!R8)>0,VALUE('01_raw_data'!R8),"Check"),"Check") -> 118000 | T5: =IFERROR(IF(VALUE('01_raw_data'!S8)>0, VALUE('01_raw_data'!S8), "Check"), "Check") -> 1200 | U5: =IFERROR(VLOOKUP(UPPER(TRIM('01_raw_data'!T8)),'07_performance_master'!$A$5:$B$14,2,FALSE),"Check") -> 1 | V5: =IFERROR(IF(VALUE('01_raw_data'!U8)>0,VALUE('01_raw_data'!U8),"Check"),"Check") -> 27 | W5: =IFERROR(IF(VALUE('01_raw_data'!V8)>=0, VALUE('01_raw_data'!V8), "Check"), "Check") -> 20 | X5: =IFERROR(IF(VALUE('01_raw_data'!W8)>=0, VALUE('01_raw_data'!W8),"Check"), "Check") -> 27 | Y5: =IFERROR(IF(AND(VALUE('01_raw_data'!X8)>=0, VALUE('01_raw_data'!X8)<=100), VALUE('01_raw_data'!X8), "Check"), "Check") -> 26 | Z5: =IFERROR(IF(OR(UPPER(TRIM('01_raw_data'!Y8))="YES", UPPER(TRIM('01_raw_data'!Y8))="PROMOTED"),"Promoted", IF(OR(UPPER(TRIM('01_raw_data'!Y8))="NO",UPPER(TRIM('01_raw_data'!Y8))="NOT PROMOTED"), "Not Promoted", "Check")),"Check") -> Not Promoted | AA5: =IFERROR(PROPER(TRIM('01_raw_data'!Z8)), "") -> Bachelor'S | AB5: =IFERROR(PROPER(TRIM('01_raw_data'!AA8)),"") -> Company Careers Page | AC5: =IFERROR(IF(UPPER(TRIM('01_raw_data'!AB8))="HYBRID","Hybrid",IF(OR(UPPER(TRIM('01_raw_data'!AB8))="REMOTE",UPPER(TRIM('01_raw_data'!AB8))="WFH",UPPER(TRIM('01_raw_data'!AB8))="WORK FROM HOME"),"Remote",IF(OR(UPPER(TRIM('01_raw_data'!AB8))="ONSITE",UPPER(TRIM('01_raw_data'!AB8))="ON-SITE",UPPER(TRIM('01_raw_data'!AB8))="OFFICE"),"Office"))),"Check") -> Hybrid | AD5: =IFERROR(VLOOKUP(UPPER(TRIM('01_raw_data'!AC8)),'09_cost_center'!$A$5:$E$19,1,FALSE), "Check") -> EU-CC501 | AE5: =IFERROR(IF(OR(UPPER(TRIM('01_raw_data'!AD8))="CONTRACT", UPPER(TRIM('01_raw_data'!AD8))="CONTRACTOR"), "Contract", IF(OR(PROPER(TRIM('01_raw_data'!AD8))="FTE", UPPER(TRIM('01_raw_data'!AD8))="FULL TIME", UPPER(TRIM('01_raw_data'!AD8))="FULL-TIME"), "Full Time", IF(OR(UPPER(TRIM('01_raw_data'!AD8))="INTERN", UPPER(TRIM('01_raw_data'!AD8))="INTERNSHIP"), "Intern", IF(OR(UPPER(TRIM('01_raw_data'!AD8))="PART TIME", UPPER(TRIM('01_raw_data'!AD8))="PART-TIME"), "Part Time")))), "Check") -> Contract | AF5: =IFERROR(IF(AND(VALUE('01_raw_data'!AE8)>=0,VALUE('01_raw_data'!AE8)<=100), VALUE('01_raw_data'!AE8), "Check"), "Check") -> 24.9
A6: ="E"&TEXT(VALUE(SUBSTITUTE(UPPER(TRIM('01_raw_data'!A9)),"E","")),"0000") -> E0005 | B6: =IF('01_raw_data'!B9="", "", PROPER(TRIM('01_raw_data'!B9))) -> Kacper Brown | C6: =_xlfn.XLOOKUP(PROPER(TRIM('01_raw_data'!C9)),'03_lookups'!$A$4:$A$9,'03_lookups'!$B$4:$B$9,"Needs Review") -> Male | D6: =VALUE('01_raw_data'!D9) -> 38 | E6: =IF(OR('01_raw_data'!E9="", LOWER(TRIM('01_raw_data'!E9))="not available"), "Missing", '01_raw_data'!E9) -> 32217 | F6: =IF(OR(E6="",LOWER(TRIM(E6))="not available"),"Missing",IF(ISNUMBER(E6),"Valid","Needs Review")) -> Valid | G6: =_xlfn.XLOOKUP(UPPER(TRIM('01_raw_data'!F9)),'04_departments'!A9:A64,'04_departments'!C9:C64,"Needs Review") -> Marketing | H6: =_xlfn.XLOOKUP('01_clean_data'!G6, '04_departments'!$C$5:$C$60,'04_departments'!$D$5:$D$60,"Needs Review") -> Revenue | I6: =PROPER(TRIM('01_raw_data'!H9)) -> Marketing Executive | J6: =IFERROR(UPPER('01_raw_data'!I9), "") -> L6 | K6: =IFERROR(UPPER('01_raw_data'!J9), "") -> M006 | L6: =IFERROR(VLOOKUP(K6,'05_manager_mapping'!$A$5:$B$64,2), "Missing") -> Aleksander Fischer | M6: =IFERROR(_xlfn.XLOOKUP('01_raw_data'!L9,'06_location_master'!$B$5:$B$60,'06_location_master'!$C$5:$C$60), "Missing Location") -> Madrid | N6: =IFERROR(_xlfn.XLOOKUP(M6,'06_location_master'!$C$5:$C$60,'06_location_master'!$D$5:$D$60), "Missing Country") -> Spain | O6: =IFERROR(_xlfn.XLOOKUP(M6,'06_location_master'!$C$5:$C$60,'06_location_master'!$E$5:$E$60), "Missing State") -> Community of Madrid | P6: =IFERROR(--'01_raw_data'!O9,"Missing Date") -> 43996 | Q6: =IF(TRIM('01_raw_data'!P9)="","", IFERROR('01_raw_data'!P9, "check")) | R6: =IFERROR(IF(OR(UPPER(TRIM('01_raw_data'!Q9))="A",UPPER(TRIM('01_raw_data'!Q9)="ACTVE"),UPPER(TRIM('01_raw_data'!Q9))="ACTIVE"), "Active", IF(OR(UPPER(TRIM('01_raw_data'!Q9)="INACTIVE"),UPPER(TRIM('01_raw_data'!Q9))="INACTVE"),"Inactive",IF(OR(UPPER(TRIM('01_raw_data'!Q9))="EXITED"), "Exited", IF(OR(UPPER(TRIM('01_raw_data'!Q9))="TERMINATED"), "Terminated", IF(OR(UPPER(TRIM('01_raw_data'!Q9))="LEFT"),"Left",IF(OR(UPPER(TRIM('01_raw_data'!Q9))="RESIGNED"),"Resigned")))))),"Check") -> Active | S6: =IFERROR(IF(VALUE('01_raw_data'!R9)>0,VALUE('01_raw_data'!R9),"Check"),"Check") -> 157000 | T6: =IFERROR(IF(VALUE('01_raw_data'!S9)>0, VALUE('01_raw_data'!S9), "Check"), "Check") -> 9400 | U6: =IFERROR(VLOOKUP(UPPER(TRIM('01_raw_data'!T9)),'07_performance_master'!$A$5:$B$14,2,FALSE),"Check") -> 3 | V6: =IFERROR(IF(VALUE('01_raw_data'!U9)>0,VALUE('01_raw_data'!U9),"Check"),"Check") -> 15 | W6: =IFERROR(IF(VALUE('01_raw_data'!V9)>=0, VALUE('01_raw_data'!V9), "Check"), "Check") -> 12 | X6: =IFERROR(IF(VALUE('01_raw_data'!W9)>=0, VALUE('01_raw_data'!W9),"Check"), "Check") -> 11 | Y6: =IFERROR(IF(AND(VALUE('01_raw_data'!X9)>=0, VALUE('01_raw_data'!X9)<=100), VALUE('01_raw_data'!X9), "Check"), "Check") -> 63 | Z6: =IFERROR(IF(OR(UPPER(TRIM('01_raw_data'!Y9))="YES", UPPER(TRIM('01_raw_data'!Y9))="PROMOTED"),"Promoted", IF(OR(UPPER(TRIM('01_raw_data'!Y9))="NO",UPPER(TRIM('01_raw_data'!Y9))="NOT PROMOTED"), "Not Promoted", "Check")),"Check") -> Not Promoted | AA6: =IFERROR(PROPER(TRIM('01_raw_data'!Z9)), "") -> Mba | AB6: =IFERROR(PROPER(TRIM('01_raw_data'!AA9)),"") -> University Hiring | AC6: =IFERROR(IF(UPPER(TRIM('01_raw_data'!AB9))="HYBRID","Hybrid",IF(OR(UPPER(TRIM('01_raw_data'!AB9))="REMOTE",UPPER(TRIM('01_raw_data'!AB9))="WFH",UPPER(TRIM('01_raw_data'!AB9))="WORK FROM HOME"),"Remote",IF(OR(UPPER(TRIM('01_raw_data'!AB9))="ONSITE",UPPER(TRIM('01_raw_data'!AB9))="ON-SITE",UPPER(TRIM('01_raw_data'!AB9))="OFFICE"),"Office"))),"Check") -> Hybrid | AD6: =IFERROR(VLOOKUP(UPPER(TRIM('01_raw_data'!AC9)),'09_cost_center'!$A$5:$E$19,1,FALSE), "Check") -> EU-CC203 | AE6: =IFERROR(IF(OR(UPPER(TRIM('01_raw_data'!AD9))="CONTRACT", UPPER(TRIM('01_raw_data'!AD9))="CONTRACTOR"), "Contract", IF(OR(PROPER(TRIM('01_raw_data'!AD9))="FTE", UPPER(TRIM('01_raw_data'!AD9))="FULL TIME", UPPER(TRIM('01_raw_data'!AD9))="FULL-TIME"), "Full Time", IF(OR(UPPER(TRIM('01_raw_data'!AD9))="INTERN", UPPER(TRIM('01_raw_data'!AD9))="INTERNSHIP"), "Intern", IF(OR(UPPER(TRIM('01_raw_data'!AD9))="PART TIME", UPPER(TRIM('01_raw_data'!AD9))="PART-TIME"), "Part Time")))), "Check") -> Full Time | AF6: =IFERROR(IF(AND(VALUE('01_raw_data'!AE9)>=0,VALUE('01_raw_data'!AE9)<=100), VALUE('01_raw_data'!AE9), "Check"), "Check") -> 57.3
A7: ="E"&TEXT(VALUE(SUBSTITUTE(UPPER(TRIM('01_raw_data'!A10)),"E","")),"0000") -> E0006 | B7: =IF('01_raw_data'!B10="", "", PROPER(TRIM('01_raw_data'!B10))) -> Kacper Gustafsson | C7: =_xlfn.XLOOKUP(PROPER(TRIM('01_raw_data'!C10)),'03_lookups'!$A$4:$A$9,'03_lookups'!$B$4:$B$9,"Needs Review") -> Male | D7: =VALUE('01_raw_data'!D10) -> 29 | E7: =IF(OR('01_raw_data'!E10="", LOWER(TRIM('01_raw_data'!E10))="not available"), "Missing", '01_raw_data'!E10) -> Missing | F7: =IF(OR(E7="",LOWER(TRIM(E7))="not available"),"Missing",IF(ISNUMBER(E7),"Valid","Needs Review")) -> Needs Review | G7: =_xlfn.XLOOKUP(UPPER(TRIM('01_raw_data'!F10)),'04_departments'!A10:A65,'04_departments'!C10:C65,"Needs Review") -> Customer Success | H7: =_xlfn.XLOOKUP('01_clean_data'!G7, '04_departments'!$C$5:$C$60,'04_departments'!$D$5:$D$60,"Needs Review") -> Revenue | I7: =PROPER(TRIM('01_raw_data'!H10)) -> Client Success Associate | J7: =IFERROR(UPPER('01_raw_data'!I10), "") -> L3 | K7: =IFERROR(UPPER('01_raw_data'!J10), "") -> M054 | L7: =IFERROR(VLOOKUP(K7,'05_manager_mapping'!$A$5:$B$64,2), "Missing") -> Isla Eriksson | M7: =IFERROR(_xlfn.XLOOKUP('01_raw_data'!L10,'06_location_master'!$B$5:$B$60,'06_location_master'!$C$5:$C$60), "Missing Location") -> Stockholm | N7: =IFERROR(_xlfn.XLOOKUP(M7,'06_location_master'!$C$5:$C$60,'06_location_master'!$D$5:$D$60), "Missing Country") -> Sweden | O7: =IFERROR(_xlfn.XLOOKUP(M7,'06_location_master'!$C$5:$C$60,'06_location_master'!$E$5:$E$60), "Missing State") -> Stockholm County | P7: =IFERROR(--'01_raw_data'!O10,"Missing Date") -> 44665 | Q7: =IF(TRIM('01_raw_data'!P10)="","", IFERROR('01_raw_data'!P10, "check")) | R7: =IFERROR(IF(OR(UPPER(TRIM('01_raw_data'!Q10))="A",UPPER(TRIM('01_raw_data'!Q10)="ACTVE"),UPPER(TRIM('01_raw_data'!Q10))="ACTIVE"), "Active", IF(OR(UPPER(TRIM('01_raw_data'!Q10)="INACTIVE"),UPPER(TRIM('01_raw_data'!Q10))="INACTVE"),"Inactive",IF(OR(UPPER(TRIM('01_raw_data'!Q10))="EXITED"), "Exited", IF(OR(UPPER(TRIM('01_raw_data'!Q10))="TERMINATED"), "Terminated", IF(OR(UPPER(TRIM('01_raw_data'!Q10))="LEFT"),"Left",IF(OR(UPPER(TRIM('01_raw_data'!Q10))="RESIGNED"),"Resigned")))))),"Check") -> Active | S7: =IFERROR(IF(VALUE('01_raw_data'!R10)>0,VALUE('01_raw_data'!R10),"Check"),"Check") -> 79000 | T7: =IFERROR(IF(VALUE('01_raw_data'!S10)>0, VALUE('01_raw_data'!S10), "Check"), "Check") -> 7100 | U7: =IFERROR(VLOOKUP(UPPER(TRIM('01_raw_data'!T10)),'07_performance_master'!$A$5:$B$14,2,FALSE),"Check") -> 4 | V7: =IFERROR(IF(VALUE('01_raw_data'!U10)>0,VALUE('01_raw_data'!U10),"Check"),"Check") -> Check | W7: =IFERROR(IF(VALUE('01_raw_data'!V10)>=0, VALUE('01_raw_data'!V10), "Check"), "Check") -> 23 | X7: =IFERROR(IF(VALUE('01_raw_data'!W10)>=0, VALUE('01_raw_data'!W10),"Check"), "Check") -> 0 | Y7: =IFERROR(IF(AND(VALUE('01_raw_data'!X10)>=0, VALUE('01_raw_data'!X10)<=100), VALUE('01_raw_data'!X10), "Check"), "Check") -> 84 | Z7: =IFERROR(IF(OR(UPPER(TRIM('01_raw_data'!Y10))="YES", UPPER(TRIM('01_raw_data'!Y10))="PROMOTED"),"Promoted", IF(OR(UPPER(TRIM('01_raw_data'!Y10))="NO",UPPER(TRIM('01_raw_data'!Y10))="NOT PROMOTED"), "Not Promoted", "Check")),"Check") -> Not Promoted | AA7: =IFERROR(PROPER(TRIM('01_raw_data'!Z10)), "") -> Bachelor'S | AB7: =IFERROR(PROPER(TRIM('01_raw_data'!AA10)),"") -> Agency | AC7: =IFERROR(IF(UPPER(TRIM('01_raw_data'!AB10))="HYBRID","Hybrid",IF(OR(UPPER(TRIM('01_raw_data'!AB10))="REMOTE",UPPER(TRIM('01_raw_data'!AB10))="WFH",UPPER(TRIM('01_raw_data'!AB10))="WORK FROM HOME"),"Remote",IF(OR(UPPER(TRIM('01_raw_data'!AB10))="ONSITE",UPPER(TRIM('01_raw_data'!AB10))="ON-SITE",UPPER(TRIM('01_raw_data'!AB10))="OFFICE"),"Office"))),"Check") -> Hybrid | AD7: =IFERROR(VLOOKUP(UPPER(TRIM('01_raw_data'!AC10)),'09_cost_center'!$A$5:$E$19,1,FALSE), "Check") -> EU-CC202 | AE7: =IFERROR(IF(OR(UPPER(TRIM('01_raw_data'!AD10))="CONTRACT", UPPER(TRIM('01_raw_data'!AD10))="CONTRACTOR"), "Contract", IF(OR(PROPER(TRIM('01_raw_data'!AD10))="FTE", UPPER(TRIM('01_raw_data'!AD10))="FULL TIME", UPPER(TRIM('01_raw_data'!AD10))="FULL-TIME"), "Full Time", IF(OR(UPPER(TRIM('01_raw_data'!AD10))="INTERN", UPPER(TRIM('01_raw_data'!AD10))="INTERNSHIP"), "Intern", IF(OR(UPPER(TRIM('01_raw_data'!AD10))="PART TIME", UPPER(TRIM('01_raw_data'!AD10))="PART-TIME"), "Part Time")))), "Check") -> Full Time | AF7: =IFERROR(IF(AND(VALUE('01_raw_data'!AE10)>=0,VALUE('01_raw_data'!AE10)<=100), VALUE('01_raw_data'!AE10), "Check"), "Check") -> 83.2
A8: ="E"&TEXT(VALUE(SUBSTITUTE(UPPER(TRIM('01_raw_data'!A11)),"E","")),"0000") -> E0007 | B8: =IF('01_raw_data'!B11="", "", PROPER(TRIM('01_raw_data'!B11))) -> Ines Martinez | C8: =_xlfn.XLOOKUP(PROPER(TRIM('01_raw_data'!C11)),'03_lookups'!$A$4:$A$9,'03_lookups'!$B$4:$B$9,"Needs Review") -> Male | D8: =VALUE('01_raw_data'!D11) -> 32 | E8: =IF(OR('01_raw_data'!E11="", LOWER(TRIM('01_raw_data'!E11))="not available"), "Missing", '01_raw_data'!E11) -> 34162 | F8: =IF(OR(E8="",LOWER(TRIM(E8))="not available"),"Missing",IF(ISNUMBER(E8),"Valid","Needs Review")) -> Valid | G8: =_xlfn.XLOOKUP(UPPER(TRIM('01_raw_data'!F11)),'04_departments'!A11:A66,'04_departments'!C11:C66,"Needs Review") -> Needs Review | H8: =_xlfn.XLOOKUP('01_clean_data'!G8, '04_departments'!$C$5:$C$60,'04_departments'!$D$5:$D$60,"Needs Review") -> Needs Review | I8: =PROPER(TRIM('01_raw_data'!H11)) -> Engineering Lead | J8: =IFERROR(UPPER('01_raw_data'!I11), "") -> L3 | K8: =IFERROR(UPPER('01_raw_data'!J11), "") -> M048 | L8: =IFERROR(VLOOKUP(K8,'05_manager_mapping'!$A$5:$B$64,2), "Missing") -> Jack Schmidt | M8: =IFERROR(_xlfn.XLOOKUP('01_raw_data'!L11,'06_location_master'!$B$5:$B$60,'06_location_master'!$C$5:$C$60), "Missing Location") -> Hamburg | N8: =IFERROR(_xlfn.XLOOKUP(M8,'06_location_master'!$C$5:$C$60,'06_location_master'!$D$5:$D$60), "Missing Country") -> Germany | O8: =IFERROR(_xlfn.XLOOKUP(M8,'06_location_master'!$C$5:$C$60,'06_location_master'!$E$5:$E$60), "Missing State") -> Hamburg | P8: =IFERROR(--'01_raw_data'!O11,"Missing Date") -> 45404 | Q8: =IF(TRIM('01_raw_data'!P11)="","", IFERROR('01_raw_data'!P11, "check")) | R8: =IFERROR(IF(OR(UPPER(TRIM('01_raw_data'!Q11))="A",UPPER(TRIM('01_raw_data'!Q11)="ACTVE"),UPPER(TRIM('01_raw_data'!Q11))="ACTIVE"), "Active", IF(OR(UPPER(TRIM('01_raw_data'!Q11)="INACTIVE"),UPPER(TRIM('01_raw_data'!Q11))="INACTVE"),"Inactive",IF(OR(UPPER(TRIM('01_raw_data'!Q11))="EXITED"), "Exited", IF(OR(UPPER(TRIM('01_raw_data'!Q11))="TERMINATED"), "Terminated", IF(OR(UPPER(TRIM('01_raw_data'!Q11))="LEFT"),"Left",IF(OR(UPPER(TRIM('01_raw_data'!Q11))="RESIGNED"),"Resigned")))))),"Check") -> Active | S8: =IFERROR(IF(VALUE('01_raw_data'!R11)>0,VALUE('01_raw_data'!R11),"Check"),"Check") -> 85000 | T8: =IFERROR(IF(VALUE('01_raw_data'!S11)>0, VALUE('01_raw_data'!S11), "Check"), "Check") -> 1700 | U8: =IFERROR(VLOOKUP(UPPER(TRIM('01_raw_data'!T11)),'07_performance_master'!$A$5:$B$14,2,FALSE),"Check") -> 2 | V8: =IFERROR(IF(VALUE('01_raw_data'!U11)>0,VALUE('01_raw_data'!U11),"Check"),"Check") -> 57 | W8: =IFERROR(IF(VALUE('01_raw_data'!V11)>=0, VALUE('01_raw_data'!V11), "Check"), "Check") -> 20 | X8: =IFERROR(IF(VALUE('01_raw_data'!W11)>=0, VALUE('01_raw_data'!W11),"Check"), "Check") -> 0 | Y8: =IFERROR(IF(AND(VALUE('01_raw_data'!X11)>=0, VALUE('01_raw_data'!X11)<=100), VALUE('01_raw_data'!X11), "Check"), "Check") -> 46 | Z8: =IFERROR(IF(OR(UPPER(TRIM('01_raw_data'!Y11))="YES", UPPER(TRIM('01_raw_data'!Y11))="PROMOTED"),"Promoted", IF(OR(UPPER(TRIM('01_raw_data'!Y11))="NO",UPPER(TRIM('01_raw_data'!Y11))="NOT PROMOTED"), "Not Promoted", "Check")),"Check") -> Not Promoted | AA8: =IFERROR(PROPER(TRIM('01_raw_data'!Z11)), "") -> Bachelor'S | AB8: =IFERROR(PROPER(TRIM('01_raw_data'!AA11)),"") -> University Hiring | AC8: =IFERROR(IF(UPPER(TRIM('01_raw_data'!AB11))="HYBRID","Hybrid",IF(OR(UPPER(TRIM('01_raw_data'!AB11))="REMOTE",UPPER(TRIM('01_raw_data'!AB11))="WFH",UPPER(TRIM('01_raw_data'!AB11))="WORK FROM HOME"),"Remote",IF(OR(UPPER(TRIM('01_raw_data'!AB11))="ONSITE",UPPER(TRIM('01_raw_data'!AB11))="ON-SITE",UPPER(TRIM('01_raw_data'!AB11))="OFFICE"),"Office"))),"Check") -> Hybrid | AD8: =IFERROR(VLOOKUP(UPPER(TRIM('01_raw_data'!AC11)),'09_cost_center'!$A$5:$E$19,1,FALSE), "Check") -> EU-CC101 | AE8: =IFERROR(IF(OR(UPPER(TRIM('01_raw_data'!AD11))="CONTRACT", UPPER(TRIM('01_raw_data'!AD11))="CONTRACTOR"), "Contract", IF(OR(PROPER(TRIM('01_raw_data'!AD11))="FTE", UPPER(TRIM('01_raw_data'!AD11))="FULL TIME", UPPER(TRIM('01_raw_data'!AD11))="FULL-TIME"), "Full Time", IF(OR(UPPER(TRIM('01_raw_data'!AD11))="INTERN", UPPER(TRIM('01_raw_data'!AD11))="INTERNSHIP"), "Intern", IF(OR(UPPER(TRIM('01_raw_data'!AD11))="PART TIME", UPPER(TRIM('01_raw_data'!AD11))="PART-TIME"), "Part Time")))), "Check") -> Full Time | AF8: =IFERROR(IF(AND(VALUE('01_raw_data'!AE11)>=0,VALUE('01_raw_data'!AE11)<=100), VALUE('01_raw_data'!AE11), "Check"), "Check") -> 54.1
A9: ="E"&TEXT(VALUE(SUBSTITUTE(UPPER(TRIM('01_raw_data'!A12)),"E","")),"0000") -> E0008 | B9: =IF('01_raw_data'!B12="", "", PROPER(TRIM('01_raw_data'!B12))) -> Alessandro Jansen | C9: =_xlfn.XLOOKUP(PROPER(TRIM('01_raw_data'!C12)),'03_lookups'!$A$4:$A$9,'03_lookups'!$B$4:$B$9,"Needs Review") -> Male | D9: =VALUE('01_raw_data'!D12) -> 22 | E9: =IF(OR('01_raw_data'!E12="", LOWER(TRIM('01_raw_data'!E12))="not available"), "Missing", '01_raw_data'!E12) -> 38098 | F9: =IF(OR(E9="",LOWER(TRIM(E9))="not available"),"Missing",IF(ISNUMBER(E9),"Valid","Needs Review")) -> Valid | G9: =_xlfn.XLOOKUP(UPPER(TRIM('01_raw_data'!F12)),'04_departments'!A12:A67,'04_departments'!C12:C67,"Needs Review") -> Operations | H9: =_xlfn.XLOOKUP('01_clean_data'!G9, '04_departments'!$C$5:$C$60,'04_departments'!$D$5:$D$60,"Needs Review") -> Operations | I9: =PROPER(TRIM('01_raw_data'!H12)) -> Workforce Planner | J9: =IFERROR(UPPER('01_raw_data'!I12), "") -> L2 | K9: =IFERROR(UPPER('01_raw_data'!J12), "") -> M010 | L9: =IFERROR(VLOOKUP(K9,'05_manager_mapping'!$A$5:$B$64,2), "Missing") -> Lotte Muller | M9: =IFERROR(_xlfn.XLOOKUP('01_raw_data'!L12,'06_location_master'!$B$5:$B$60,'06_location_master'!$C$5:$C$60), "Missing Location") -> Eindhoven | N9: =IFERROR(_xlfn.XLOOKUP(M9,'06_location_master'!$C$5:$C$60,'06_location_master'!$D$5:$D$60), "Missing Country") -> Netherlands | O9: =IFERROR(_xlfn.XLOOKUP(M9,'06_location_master'!$C$5:$C$60,'06_location_master'!$E$5:$E$60), "Missing State") -> North Brabant | P9: =IFERROR(--'01_raw_data'!O12,"Missing Date") -> 45703 | Q9: =IF(TRIM('01_raw_data'!P12)="","", IFERROR('01_raw_data'!P12, "check")) -> 01-08-2026 | R9: =IFERROR(IF(OR(UPPER(TRIM('01_raw_data'!Q12))="A",UPPER(TRIM('01_raw_data'!Q12)="ACTVE"),UPPER(TRIM('01_raw_data'!Q12))="ACTIVE"), "Active", IF(OR(UPPER(TRIM('01_raw_data'!Q12)="INACTIVE"),UPPER(TRIM('01_raw_data'!Q12))="INACTVE"),"Inactive",IF(OR(UPPER(TRIM('01_raw_data'!Q12))="EXITED"), "Exited", IF(OR(UPPER(TRIM('01_raw_data'!Q12))="TERMINATED"), "Terminated", IF(OR(UPPER(TRIM('01_raw_data'!Q12))="LEFT"),"Left",IF(OR(UPPER(TRIM('01_raw_data'!Q12))="RESIGNED"),"Resigned")))))),"Check") -> Exited | S9: =IFERROR(IF(VALUE('01_raw_data'!R12)>0,VALUE('01_raw_data'!R12),"Check"),"Check") -> 56000 | T9: =IFERROR(IF(VALUE('01_raw_data'!S12)>0, VALUE('01_raw_data'!S12), "Check"), "Check") -> 7800 | U9: =IFERROR(VLOOKUP(UPPER(TRIM('01_raw_data'!T12)),'07_performance_master'!$A$5:$B$14,2,FALSE),"Check") -> 5 | V9: =IFERROR(IF(VALUE('01_raw_data'!U12)>0,VALUE('01_raw_data'!U12),"Check"),"Check") -> 48 | W9: =IFERROR(IF(VALUE('01_raw_data'!V12)>=0, VALUE('01_raw_data'!V12), "Check"), "Check") -> 10 | X9: =IFERROR(IF(VALUE('01_raw_data'!W12)>=0, VALUE('01_raw_data'!W12),"Check"), "Check") -> 1 | Y9: =IFERROR(IF(AND(VALUE('01_raw_data'!X12)>=0, VALUE('01_raw_data'!X12)<=100), VALUE('01_raw_data'!X12), "Check"), "Check") -> 57 | Z9: =IFERROR(IF(OR(UPPER(TRIM('01_raw_data'!Y12))="YES", UPPER(TRIM('01_raw_data'!Y12))="PROMOTED"),"Promoted", IF(OR(UPPER(TRIM('01_raw_data'!Y12))="NO",UPPER(TRIM('01_raw_data'!Y12))="NOT PROMOTED"), "Not Promoted", "Check")),"Check") -> Not Promoted | AA9: =IFERROR(PROPER(TRIM('01_raw_data'!Z12)), "") -> Bachelor'S | AB9: =IFERROR(PROPER(TRIM('01_raw_data'!AA12)),"") -> European Job Board | AC9: =IFERROR(IF(UPPER(TRIM('01_raw_data'!AB12))="HYBRID","Hybrid",IF(OR(UPPER(TRIM('01_raw_data'!AB12))="REMOTE",UPPER(TRIM('01_raw_data'!AB12))="WFH",UPPER(TRIM('01_raw_data'!AB12))="WORK FROM HOME"),"Remote",IF(OR(UPPER(TRIM('01_raw_data'!AB12))="ONSITE",UPPER(TRIM('01_raw_data'!AB12))="ON-SITE",UPPER(TRIM('01_raw_data'!AB12))="OFFICE"),"Office"))),"Check") -> Remote | AD9: =IFERROR(VLOOKUP(UPPER(TRIM('01_raw_data'!AC12)),'09_cost_center'!$A$5:$E$19,1,FALSE), "Check") -> EU-CC401 | AE9: =IFERROR(IF(OR(UPPER(TRIM('01_raw_data'!AD12))="CONTRACT", UPPER(TRIM('01_raw_data'!AD12))="CONTRACTOR"), "Contract", IF(OR(PROPER(TRIM('01_raw_data'!AD12))="FTE", UPPER(TRIM('01_raw_data'!AD12))="FULL TIME", UPPER(TRIM('01_raw_data'!AD12))="FULL-TIME"), "Full Time", IF(OR(UPPER(TRIM('01_raw_data'!AD12))="INTERN", UPPER(TRIM('01_raw_data'!AD12))="INTERNSHIP"), "Intern", IF(OR(UPPER(TRIM('01_raw_data'!AD12))="PART TIME", UPPER(TRIM('01_raw_data'!AD12))="PART-TIME"), "Part Time")))), "Check") -> Full Time | AF9: =IFERROR(IF(AND(VALUE('01_raw_data'!AE12)>=0,VALUE('01_raw_data'!AE12)<=100), VALUE('01_raw_data'!AE12), "Check"), "Check") -> 84.5
A10: ="E"&TEXT(VALUE(SUBSTITUTE(UPPER(TRIM('01_raw_data'!A13)),"E","")),"0000") -> E0009 | B10: =IF('01_raw_data'!B13="", "", PROPER(TRIM('01_raw_data'!B13))) -> Javier Ricci | C10: =_xlfn.XLOOKUP(PROPER(TRIM('01_raw_data'!C13)),'03_lookups'!$A$4:$A$9,'03_lookups'!$B$4:$B$9,"Needs Review") -> Male | D10: =VALUE('01_raw_data'!D13) -> 37 | E10: =IF(OR('01_raw_data'!E13="", LOWER(TRIM('01_raw_data'!E13))="not available"), "Missing", '01_raw_data'!E13) -> 32347 | F10: =IF(OR(E10="",LOWER(TRIM(E10))="not available"),"Missing",IF(ISNUMBER(E10),"Valid","Needs Review")) -> Valid | G10: =_xlfn.XLOOKUP(UPPER(TRIM('01_raw_data'!F13)),'04_departments'!A13:A68,'04_departments'!C13:C68,"Needs Review") -> Data & Analytics | H10: =_xlfn.XLOOKUP('01_clean_data'!G10, '04_departments'!$C$5:$C$60,'04_departments'!$D$5:$D$60,"Needs Review") -> Data & AI | I10: =PROPER(TRIM('01_raw_data'!H13)) -> Data Scientist | J10: =IFERROR(UPPER('01_raw_data'!I13), "") -> L4 | K10: =IFERROR(UPPER('01_raw_data'!J13), "") -> M020 | L10: =IFERROR(VLOOKUP(K10,'05_manager_mapping'!$A$5:$B$64,2), "Missing") -> Alessandro Lewandowski | M10: =IFERROR(_xlfn.XLOOKUP('01_raw_data'!L13,'06_location_master'!$B$5:$B$60,'06_location_master'!$C$5:$C$60), "Missing Location") -> Munich | N10: =IFERROR(_xlfn.XLOOKUP(M10,'06_location_master'!$C$5:$C$60,'06_location_master'!$D$5:$D$60), "Missing Country") -> Germany | O10: =IFERROR(_xlfn.XLOOKUP(M10,'06_location_master'!$C$5:$C$60,'06_location_master'!$E$5:$E$60), "Missing State") -> Bavaria | P10: =IFERROR(--'01_raw_data'!O13,"Missing Date") -> 42863 | Q10: =IF(TRIM('01_raw_data'!P13)="","", IFERROR('01_raw_data'!P13, "check")) | R10: =IFERROR(IF(OR(UPPER(TRIM('01_raw_data'!Q13))="A",UPPER(TRIM('01_raw_data'!Q13)="ACTVE"),UPPER(TRIM('01_raw_data'!Q13))="ACTIVE"), "Active", IF(OR(UPPER(TRIM('01_raw_data'!Q13)="INACTIVE"),UPPER(TRIM('01_raw_data'!Q13))="INACTVE"),"Inactive",IF(OR(UPPER(TRIM('01_raw_data'!Q13))="EXITED"), "Exited", IF(OR(UPPER(TRIM('01_raw_data'!Q13))="TERMINATED"), "Terminated", IF(OR(UPPER(TRIM('01_raw_data'!Q13))="LEFT"),"Left",IF(OR(UPPER(TRIM('01_raw_data'!Q13))="RESIGNED"),"Resigned")))))),"Check") -> Active | S10: =IFERROR(IF(VALUE('01_raw_data'!R13)>0,VALUE('01_raw_data'!R13),"Check"),"Check") -> 109000 | T10: =IFERROR(IF(VALUE('01_raw_data'!S13)>0, VALUE('01_raw_data'!S13), "Check"), "Check") -> 5400 | U10: =IFERROR(VLOOKUP(UPPER(TRIM('01_raw_data'!T13)),'07_performance_master'!$A$5:$B$14,2,FALSE),"Check") -> 3 | V10: =IFERROR(IF(VALUE('01_raw_data'!U13)>0,VALUE('01_raw_data'!U13),"Check"),"Check") -> 29 | W10: =IFERROR(IF(VALUE('01_raw_data'!V13)>=0, VALUE('01_raw_data'!V13), "Check"), "Check") -> 18 | X10: =IFERROR(IF(VALUE('01_raw_data'!W13)>=0, VALUE('01_raw_data'!W13),"Check"), "Check") -> 7 | Y10: =IFERROR(IF(AND(VALUE('01_raw_data'!X13)>=0, VALUE('01_raw_data'!X13)<=100), VALUE('01_raw_data'!X13), "Check"), "Check") -> 47 | Z10: =IFERROR(IF(OR(UPPER(TRIM('01_raw_data'!Y13))="YES", UPPER(TRIM('01_raw_data'!Y13))="PROMOTED"),"Promoted", IF(OR(UPPER(TRIM('01_raw_data'!Y13))="NO",UPPER(TRIM('01_raw_data'!Y13))="NOT PROMOTED"), "Not Promoted", "Check")),"Check") -> Not Promoted | AA10: =IFERROR(PROPER(TRIM('01_raw_data'!Z13)), "") -> Diploma | AB10: =IFERROR(PROPER(TRIM('01_raw_data'!AA13)),"") -> Company Careers Page | AC10: =IFERROR(IF(UPPER(TRIM('01_raw_data'!AB13))="HYBRID","Hybrid",IF(OR(UPPER(TRIM('01_raw_data'!AB13))="REMOTE",UPPER(TRIM('01_raw_data'!AB13))="WFH",UPPER(TRIM('01_raw_data'!AB13))="WORK FROM HOME"),"Remote",IF(OR(UPPER(TRIM('01_raw_data'!AB13))="ONSITE",UPPER(TRIM('01_raw_data'!AB13))="ON-SITE",UPPER(TRIM('01_raw_data'!AB13))="OFFICE"),"Office"))),"Check") -> Hybrid | AD10: =IFERROR(VLOOKUP(UPPER(TRIM('01_raw_data'!AC13)),'09_cost_center'!$A$5:$E$19,1,FALSE), "Check") -> EU-CC103 | AE10: =IFERROR(IF(OR(UPPER(TRIM('01_raw_data'!AD13))="CONTRACT", UPPER(TRIM('01_raw_data'!AD13))="CONTRACTOR"), "Contract", IF(OR(PROPER(TRIM('01_raw_data'!AD13))="FTE", UPPER(TRIM('01_raw_data'!AD13))="FULL TIME", UPPER(TRIM('01_raw_data'!AD13))="FULL-TIME"), "Full Time", IF(OR(UPPER(TRIM('01_raw_data'!AD13))="INTERN", UPPER(TRIM('01_raw_data'!AD13))="INTERNSHIP"), "Intern", IF(OR(UPPER(TRIM('01_raw_data'!AD13))="PART TIME", UPPER(TRIM('01_raw_data'!AD13))="PART-TIME"), "Part Time")))), "Check") -> Full Time | AF10: =IFERROR(IF(AND(VALUE('01_raw_data'!AE13)>=0,VALUE('01_raw_data'!AE13)<=100), VALUE('01_raw_data'!AE13), "Check"), "Check") -> 57.2
A11: ="E"&TEXT(VALUE(SUBSTITUTE(UPPER(TRIM('01_raw_data'!A14)),"E","")),"0000") -> E0010 | B11: =IF('01_raw_data'!B14="", "", PROPER(TRIM('01_raw_data'!B14))) -> Sophia Petit | C11: =_xlfn.XLOOKUP(PROPER(TRIM('01_raw_data'!C14)),'03_lookups'!$A$4:$A$9,'03_lookups'!$B$4:$B$9,"Needs Review") -> Female | D11: =VALUE('01_raw_data'!D14) -> 46 | E11: =IF(OR('01_raw_data'!E14="", LOWER(TRIM('01_raw_data'!E14))="not available"), "Missing", '01_raw_data'!E14) -> 29087 | F11: =IF(OR(E11="",LOWER(TRIM(E11))="not available"),"Missing",IF(ISNUMBER(E11),"Valid","Needs Review")) -> Valid | G11: =_xlfn.XLOOKUP(UPPER(TRIM('01_raw_data'!F14)),'04_departments'!A14:A69,'04_departments'!C14:C69,"Needs Review") -> Security | H11: =_xlfn.XLOOKUP('01_clean_data'!G11, '04_departments'!$C$5:$C$60,'04_departments'!$D$5:$D$60,"Needs Review") -> Risk & Compliance | I11: =PROPER(TRIM('01_raw_data'!H14)) -> Security Lead | J11: =IFERROR(UPPER('01_raw_data'!I14), "") -> L1 | K11: =IFERROR(UPPER('01_raw_data'!J14), "") -> M056 | L11: =IFERROR(VLOOKUP(K11,'05_manager_mapping'!$A$5:$B$64,2), "Missing") -> Emily Olsson | M11: =IFERROR(_xlfn.XLOOKUP('01_raw_data'!L14,'06_location_master'!$B$5:$B$60,'06_location_master'!$C$5:$C$60), "Missing Location") -> London | N11: =IFERROR(_xlfn.XLOOKUP(M11,'06_location_master'!$C$5:$C$60,'06_location_master'!$D$5:$D$60), "Missing Country") -> United Kingdom | O11: =IFERROR(_xlfn.XLOOKUP(M11,'06_location_master'!$C$5:$C$60,'06_location_master'!$E$5:$E$60), "Missing State") -> England | P11: =IFERROR(--'01_raw_data'!O14,"Missing Date") -> Missing Date | Q11: =IF(TRIM('01_raw_data'!P14)="","", IFERROR('01_raw_data'!P14, "check")) | R11: =IFERROR(IF(OR(UPPER(TRIM('01_raw_data'!Q14))="A",UPPER(TRIM('01_raw_data'!Q14)="ACTVE"),UPPER(TRIM('01_raw_data'!Q14))="ACTIVE"), "Active", IF(OR(UPPER(TRIM('01_raw_data'!Q14)="INACTIVE"),UPPER(TRIM('01_raw_data'!Q14))="INACTVE"),"Inactive",IF(OR(UPPER(TRIM('01_raw_data'!Q14))="EXITED"), "Exited", IF(OR(UPPER(TRIM('01_raw_data'!Q14))="TERMINATED"), "Terminated", IF(OR(UPPER(TRIM('01_raw_data'!Q14))="LEFT"),"Left",IF(OR(UPPER(TRIM('01_raw_data'!Q14))="RESIGNED"),"Resigned")))))),"Check") -> Active | S11: =IFERROR(IF(VALUE('01_raw_data'!R14)>0,VALUE('01_raw_data'!R14),"Check"),"Check") -> 49000 | T11: =IFERROR(IF(VALUE('01_raw_data'!S14)>0, VALUE('01_raw_data'!S14), "Check"), "Check") -> 2400 | U11: =IFERROR(VLOOKUP(UPPER(TRIM('01_raw_data'!T14)),'07_performance_master'!$A$5:$B$14,2,FALSE),"Check") -> 3 | V11: =IFERROR(IF(VALUE('01_raw_data'!U14)>0,VALUE('01_raw_data'!U14),"Check"),"Check") -> 21 | W11: =IFERROR(IF(VALUE('01_raw_data'!V14)>=0, VALUE('01_raw_data'!V14), "Check"), "Check") -> 2 | X11: =IFERROR(IF(VALUE('01_raw_data'!W14)>=0, VALUE('01_raw_data'!W14),"Check"), "Check") -> 20 | Y11: =IFERROR(IF(AND(VALUE('01_raw_data'!X14)>=0, VALUE('01_raw_data'!X14)<=100), VALUE('01_raw_data'!X14), "Check"), "Check") -> 54 | Z11: =IFERROR(IF(OR(UPPER(TRIM('01_raw_data'!Y14))="YES", UPPER(TRIM('01_raw_data'!Y14))="PROMOTED"),"Promoted", IF(OR(UPPER(TRIM('01_raw_data'!Y14))="NO",UPPER(TRIM('01_raw_data'!Y14))="NOT PROMOTED"), "Not Promoted", "Check")),"Check") -> Not Promoted | AA11: =IFERROR(PROPER(TRIM('01_raw_data'!Z14)), "") -> Bachelor'S | AB11: =IFERROR(PROPER(TRIM('01_raw_data'!AA14)),"") -> European Job Board | AC11: =IFERROR(IF(UPPER(TRIM('01_raw_data'!AB14))="HYBRID","Hybrid",IF(OR(UPPER(TRIM('01_raw_data'!AB14))="REMOTE",UPPER(TRIM('01_raw_data'!AB14))="WFH",UPPER(TRIM('01_raw_data'!AB14))="WORK FROM HOME"),"Remote",IF(OR(UPPER(TRIM('01_raw_data'!AB14))="ONSITE",UPPER(TRIM('01_raw_data'!AB14))="ON-SITE",UPPER(TRIM('01_raw_data'!AB14))="OFFICE"),"Office"))),"Check") -> Office | AD11: =IFERROR(VLOOKUP(UPPER(TRIM('01_raw_data'!AC14)),'09_cost_center'!$A$5:$E$19,1,FALSE), "Check") -> EU-CC503 | AE11: =IFERROR(IF(OR(UPPER(TRIM('01_raw_data'!AD14))="CONTRACT", UPPER(TRIM('01_raw_data'!AD14))="CONTRACTOR"), "Contract", IF(OR(PROPER(TRIM('01_raw_data'!AD14))="FTE", UPPER(TRIM('01_raw_data'!AD14))="FULL TIME", UPPER(TRIM('01_raw_data'!AD14))="FULL-TIME"), "Full Time", IF(OR(UPPER(TRIM('01_raw_data'!AD14))="INTERN", UPPER(TRIM('01_raw_data'!AD14))="INTERNSHIP"), "Intern", IF(OR(UPPER(TRIM('01_raw_data'!AD14))="PART TIME", UPPER(TRIM('01_raw_data'!AD14))="PART-TIME"), "Part Time")))), "Check") -> Full Time | AF11: =IFERROR(IF(AND(VALUE('01_raw_data'!AE14)>=0,VALUE('01_raw_data'!AE14)<=100), VALUE('01_raw_data'!AE14), "Check"), "Check") -> 51.1
A12: ="E"&TEXT(VALUE(SUBSTITUTE(UPPER(TRIM('01_raw_data'!A15)),"E","")),"0000") -> E0011 | B12: =IF('01_raw_data'!B15="", "", PROPER(TRIM('01_raw_data'!B15))) -> Francesco Ferreira | C12: =_xlfn.XLOOKUP(PROPER(TRIM('01_raw_data'!C15)),'03_lookups'!$A$4:$A$9,'03_lookups'!$B$4:$B$9,"Needs Review") -> Male | D12: =VALUE('01_raw_data'!D15) -> 51 | E12: =IF(OR('01_raw_data'!E15="", LOWER(TRIM('01_raw_data'!E15))="not available"), "Missing", '01_raw_data'!E15) -> 27494 | F12: =IF(OR(E12="",LOWER(TRIM(E12))="not available"),"Missing",IF(ISNUMBER(E12),"Valid","Needs Review")) -> Valid | G12: =_xlfn.XLOOKUP(UPPER(TRIM('01_raw_data'!F15)),'04_departments'!A15:A70,'04_departments'!C15:C70,"Needs Review") -> Needs Review | H12: =_xlfn.XLOOKUP('01_clean_data'!G12, '04_departments'!$C$5:$C$60,'04_departments'!$D$5:$D$60,"Needs Review") -> Needs Review | I12: =PROPER(TRIM('01_raw_data'!H15)) -> Transformation Lead | J12: =IFERROR(UPPER('01_raw_data'!I15), "") -> L3 | K12: =IFERROR(UPPER('01_raw_data'!J15), "") -> M015 | L12: =IFERROR(VLOOKUP(K12,'05_manager_mapping'!$A$5:$B$64,2), "Missing") -> Lea Ryan | M12: =IFERROR(_xlfn.XLOOKUP('01_raw_data'!L15,'06_location_master'!$B$5:$B$60,'06_location_master'!$C$5:$C$60), "Missing Location") -> Manchester | N12: =IFERROR(_xlfn.XLOOKUP(M12,'06_location_master'!$C$5:$C$60,'06_location_master'!$D$5:$D$60), "Missing Country") -> United Kingdom | O12: =IFERROR(_xlfn.XLOOKUP(M12,'06_location_master'!$C$5:$C$60,'06_location_master'!$E$5:$E$60), "Missing State") -> England | P12: =IFERROR(--'01_raw_data'!O15,"Missing Date") -> 44414 | Q12: =IF(TRIM('01_raw_data'!P15)="","", IFERROR('01_raw_data'!P15, "check")) -> 45280 | R12: =IFERROR(IF(OR(UPPER(TRIM('01_raw_data'!Q15))="A",UPPER(TRIM('01_raw_data'!Q15)="ACTVE"),UPPER(TRIM('01_raw_data'!Q15))="ACTIVE"), "Active", IF(OR(UPPER(TRIM('01_raw_data'!Q15)="INACTIVE"),UPPER(TRIM('01_raw_data'!Q15))="INACTVE"),"Inactive",IF(OR(UPPER(TRIM('01_raw_data'!Q15))="EXITED"), "Exited", IF(OR(UPPER(TRIM('01_raw_data'!Q15))="TERMINATED"), "Terminated", IF(OR(UPPER(TRIM('01_raw_data'!Q15))="LEFT"),"Left",IF(OR(UPPER(TRIM('01_raw_data'!Q15))="RESIGNED"),"Resigned")))))),"Check") -> Exited | S12: =IFERROR(IF(VALUE('01_raw_data'!R15)>0,VALUE('01_raw_data'!R15),"Check"),"Check") -> 71000 | T12: =IFERROR(IF(VALUE('01_raw_data'!S15)>0, VALUE('01_raw_data'!S15), "Check"), "Check") -> 3600 | U12: =IFERROR(VLOOKUP(UPPER(TRIM('01_raw_data'!T15)),'07_performance_master'!$A$5:$B$14,2,FALSE),"Check") -> 3 | V12: =IFERROR(IF(VALUE('01_raw_data'!U15)>0,VALUE('01_raw_data'!U15),"Check"),"Check") -> 18 | W12: =IFERROR(IF(VALUE('01_raw_data'!V15)>=0, VALUE('01_raw_data'!V15), "Check"), "Check") -> 31 | X12: =IFERROR(IF(VALUE('01_raw_data'!W15)>=0, VALUE('01_raw_data'!W15),"Check"), "Check") -> 0 | Y12: =IFERROR(IF(AND(VALUE('01_raw_data'!X15)>=0, VALUE('01_raw_data'!X15)<=100), VALUE('01_raw_data'!X15), "Check"), "Check") -> 68 | Z12: =IFERROR(IF(OR(UPPER(TRIM('01_raw_data'!Y15))="YES", UPPER(TRIM('01_raw_data'!Y15))="PROMOTED"),"Promoted", IF(OR(UPPER(TRIM('01_raw_data'!Y15))="NO",UPPER(TRIM('01_raw_data'!Y15))="NOT PROMOTED"), "Not Promoted", "Check")),"Check") -> Not Promoted | AA12: =IFERROR(PROPER(TRIM('01_raw_data'!Z15)), "") -> Bachelor'S | AB12: =IFERROR(PROPER(TRIM('01_raw_data'!AA15)),"") -> Linkedin | AC12: =IFERROR(IF(UPPER(TRIM('01_raw_data'!AB15))="HYBRID","Hybrid",IF(OR(UPPER(TRIM('01_raw_data'!AB15))="REMOTE",UPPER(TRIM('01_raw_data'!AB15))="WFH",UPPER(TRIM('01_raw_data'!AB15))="WORK FROM HOME"),"Remote",IF(OR(UPPER(TRIM('01_raw_data'!AB15))="ONSITE",UPPER(TRIM('01_raw_data'!AB15))="ON-SITE",UPPER(TRIM('01_raw_data'!AB15))="OFFICE"),"Office"))),"Check") -> Remote | AD12: =IFERROR(VLOOKUP(UPPER(TRIM('01_raw_data'!AC15)),'09_cost_center'!$A$5:$E$19,1,FALSE), "Check") -> EU-CC303 | AE12: =IFERROR(IF(OR(UPPER(TRIM('01_raw_data'!AD15))="CONTRACT", UPPER(TRIM('01_raw_data'!AD15))="CONTRACTOR"), "Contract", IF(OR(PROPER(TRIM('01_raw_data'!AD15))="FTE", UPPER(TRIM('01_raw_data'!AD15))="FULL TIME", UPPER(TRIM('01_raw_data'!AD15))="FULL-TIME"), "Full Time", IF(OR(UPPER(TRIM('01_raw_data'!AD15))="INTERN", UPPER(TRIM('01_raw_data'!AD15))="INTERNSHIP"), "Intern", IF(OR(UPPER(TRIM('01_raw_data'!AD15))="PART TIME", UPPER(TRIM('01_raw_data'!AD15))="PART-TIME"), "Part Time")))), "Check") -> Full Time | AF12: =IFERROR(IF(AND(VALUE('01_raw_data'!AE15)>=0,VALUE('01_raw_data'!AE15)<=100), VALUE('01_raw_data'!AE15), "Check"), "Check") -> 65.3
A13: ="E"&TEXT(VALUE(SUBSTITUTE(UPPER(TRIM('01_raw_data'!A16)),"E","")),"0000") -> E0012 | B13: =IF('01_raw_data'!B16="", "", PROPER(TRIM('01_raw_data'!B16))) -> Emily Fernandes | C13: =_xlfn.XLOOKUP(PROPER(TRIM('01_raw_data'!C16)),'03_lookups'!$A$4:$A$9,'03_lookups'!$B$4:$B$9,"Needs Review") -> Female | D13: =VALUE('01_raw_data'!D16) -> 24 | E13: =IF(OR('01_raw_data'!E16="", LOWER(TRIM('01_raw_data'!E16))="not available"), "Missing", '01_raw_data'!E16) -> 37406 | F13: =IF(OR(E13="",LOWER(TRIM(E13))="not available"),"Missing",IF(ISNUMBER(E13),"Valid","Needs Review")) -> Valid | G13: =_xlfn.XLOOKUP(UPPER(TRIM('01_raw_data'!F16)),'04_departments'!A16:A71,'04_departments'!C16:C71,"Needs Review") -> Needs Review | H13: =_xlfn.XLOOKUP('01_clean_data'!G13, '04_departments'!$C$5:$C$60,'04_departments'!$D$5:$D$60,"Needs Review") -> Needs Review | I13: =PROPER(TRIM('01_raw_data'!H16)) -> Security Analyst | J13: =IFERROR(UPPER('01_raw_data'!I16), "") -> L2 | K13: =IFERROR(UPPER('01_raw_data'!J16), "") -> M014 | L13: =IFERROR(VLOOKUP(K13,'05_manager_mapping'!$A$5:$B$64,2,), "Missing") -> Elena Szymanski | M13: =IFERROR(_xlfn.XLOOKUP('01_raw_data'!L16,'06_location_master'!$B$5:$B$60,'06_location_master'!$C$5:$C$60), "Missing Location") -> Berlin | N13: =IFERROR(_xlfn.XLOOKUP(M13,'06_location_master'!$C$5:$C$60,'06_location_master'!$D$5:$D$60), "Missing Country") -> Germany | O13: =IFERROR(_xlfn.XLOOKUP(M13,'06_location_master'!$C$5:$C$60,'06_location_master'!$E$5:$E$60), "Missing State") -> Berlin | P13: =IFERROR(--'01_raw_data'!O16,"Missing Date") -> 44246 | Q13: =IF(TRIM('01_raw_data'!P16)="","", IFERROR('01_raw_data'!P16, "check")) | R13: =IFERROR(IF(OR(UPPER(TRIM('01_raw_data'!Q16))="A",UPPER(TRIM('01_raw_data'!Q16)="ACTVE"),UPPER(TRIM('01_raw_data'!Q16))="ACTIVE"), "Active", IF(OR(UPPER(TRIM('01_raw_data'!Q16)="INACTIVE"),UPPER(TRIM('01_raw_data'!Q16))="INACTVE"),"Inactive",IF(OR(UPPER(TRIM('01_raw_data'!Q16))="EXITED"), "Exited", IF(OR(UPPER(TRIM('01_raw_data'!Q16))="TERMINATED"), "Terminated", IF(OR(UPPER(TRIM('01_raw_data'!Q16))="LEFT"),"Left",IF(OR(UPPER(TRIM('01_raw_data'!Q16))="RESIGNED"),"Resigned")))))),"Check") -> Active | S13: =IFERROR(IF(VALUE('01_raw_data'!R16)>0,VALUE('01_raw_data'!R16),"Check"),"Check") -> 57000 | T13: =IFERROR(IF(VALUE('01_raw_data'!S16)>0, VALUE('01_raw_data'!S16), "Check"), "Check") -> 2800 | U13: =IFERROR(VLOOKUP(UPPER(TRIM('01_raw_data'!T16)),'07_performance_master'!$A$5:$B$14,2,FALSE),"Check") -> 3 | V13: =IFERROR(IF(VALUE('01_raw_data'!U16)>0,VALUE('01_raw_data'!U16),"Check"),"Check") -> 12 | W13: =IFERROR(IF(VALUE('01_raw_data'!V16)>=0, VALUE('01_raw_data'!V16), "Check"), "Check") -> 22 | X13: =IFERROR(IF(VALUE('01_raw_data'!W16)>=0, VALUE('01_raw_data'!W16),"Check"), "Check") -> 25 | Y13: =IFERROR(IF(AND(VALUE('01_raw_data'!X16)>=0, VALUE('01_raw_data'!X16)<=100), VALUE('01_raw_data'!X16), "Check"), "Check") -> 57 | Z13: =IFERROR(IF(OR(UPPER(TRIM('01_raw_data'!Y16))="YES", UPPER(TRIM('01_raw_data'!Y16))="PROMOTED"),"Promoted", IF(OR(UPPER(TRIM('01_raw_data'!Y16))="NO",UPPER(TRIM('01_raw_data'!Y16))="NOT PROMOTED"), "Not Promoted", "Check")),"Check") -> Not Promoted | AA13: =IFERROR(PROPER(TRIM('01_raw_data'!Z16)), "") -> Master'S | AB13: =IFERROR(PROPER(TRIM('01_raw_data'!AA16)),"") -> Indeed | AC13: =IFERROR(IF(UPPER(TRIM('01_raw_data'!AB16))="HYBRID","Hybrid",IF(OR(UPPER(TRIM('01_raw_data'!AB16))="REMOTE",UPPER(TRIM('01_raw_data'!AB16))="WFH",UPPER(TRIM('01_raw_data'!AB16))="WORK FROM HOME"),"Remote",IF(OR(UPPER(TRIM('01_raw_data'!AB16))="ONSITE",UPPER(TRIM('01_raw_data'!AB16))="ON-SITE",UPPER(TRIM('01_raw_data'!AB16))="OFFICE"),"Office"))),"Check") -> Remote | AD13: =IFERROR(VLOOKUP(UPPER(TRIM('01_raw_data'!AC16)),'09_cost_center'!$A$5:$E$19,1,FALSE), "Check") -> EU-CC503 | AE13: =IFERROR(IF(OR(UPPER(TRIM('01_raw_data'!AD16))="CONTRACT", UPPER(TRIM('01_raw_data'!AD16))="CONTRACTOR"), "Contract", IF(OR(PROPER(TRIM('01_raw_data'!AD16))="FTE", UPPER(TRIM('01_raw_data'!AD16))="FULL TIME", UPPER(TRIM('01_raw_data'!AD16))="FULL-TIME"), "Full Time", IF(OR(UPPER(TRIM('01_raw_data'!AD16))="INTERN", UPPER(TRIM('01_raw_data'!AD16))="INTERNSHIP"), "Intern", IF(OR(UPPER(TRIM('01_raw_data'!AD16))="PART TIME", UPPER(TRIM('01_raw_data'!AD16))="PART-TIME"), "Part Time")))), "Check") -> Full Time | AF13: =IFERROR(IF(AND(VALUE('01_raw_data'!AE16)>=0,VALUE('01_raw_data'!AE16)<=100), VALUE('01_raw_data'!AE16), "Check"), "Check") -> 50
A14: ="E"&TEXT(VALUE(SUBSTITUTE(UPPER(TRIM('01_raw_data'!A17)),"E","")),"0000") -> E0013 | B14: =IF('01_raw_data'!B17="", "", PROPER(TRIM('01_raw_data'!B17))) -> Arthur Mulder | C14: =_xlfn.XLOOKUP(PROPER(TRIM('01_raw_data'!C17)),'03_lookups'!$A$4:$A$9,'03_lookups'!$B$4:$B$9,"Needs Review") -> Female | D14: =VALUE('01_raw_data'!D17) -> 46 | E14: =IF(OR('01_raw_data'!E17="", LOWER(TRIM('01_raw_data'!E17))="not available"), "Missing", '01_raw_data'!E17) -> 29183 | F14: =IF(OR(E14="",LOWER(TRIM(E14))="not available"),"Missing",IF(ISNUMBER(E14),"Valid","Needs Review")) -> Valid | G14: =_xlfn.XLOOKUP(UPPER(TRIM('01_raw_data'!F17)),'04_departments'!A17:A72,'04_departments'!C17:C72,"Needs Review") -> Procurement | H14: =_xlfn.XLOOKUP('01_clean_data'!G14, '04_departments'!$C$5:$C$60,'04_departments'!$D$5:$D$60,"Needs Review") -> Operations | I14: =PROPER(TRIM('01_raw_data'!H17)) -> Vendor Manager | J14: =IFERROR(UPPER('01_raw_data'!I17), "") -> L2 | K14: =IFERROR(UPPER('01_raw_data'!J17), "") -> M013 | L14: =IFERROR(VLOOKUP(K14,'05_manager_mapping'!$A$5:$B$64,2), "Missing") -> Ebba Kelly | M14: =IFERROR(_xlfn.XLOOKUP('01_raw_data'!L17,'06_location_master'!$B$5:$B$60,'06_location_master'!$C$5:$C$60), "Missing Location") -> Stockholm | N14: =IFERROR(_xlfn.XLOOKUP(M14,'06_location_master'!$C$5:$C$60,'06_location_master'!$D$5:$D$60), "Missing Country") -> Sweden | O14: =IFERROR(_xlfn.XLOOKUP(M14,'06_location_master'!$C$5:$C$60,'06_location_master'!$E$5:$E$60), "Missing State") -> Stockholm County | P14: =IFERROR(--'01_raw_data'!O17,"Missing Date") -> 44155 | Q14: =IF(TRIM('01_raw_data'!P17)="","", IFERROR('01_raw_data'!P17, "check")) | R14: =IFERROR(IF(OR(UPPER(TRIM('01_raw_data'!Q17))="A",UPPER(TRIM('01_raw_data'!Q17)="ACTVE"),UPPER(TRIM('01_raw_data'!Q17))="ACTIVE"), "Active", IF(OR(UPPER(TRIM('01_raw_data'!Q17)="INACTIVE"),UPPER(TRIM('01_raw_data'!Q17))="INACTVE"),"Inactive",IF(OR(UPPER(TRIM('01_raw_data'!Q17))="EXITED"), "Exited", IF(OR(UPPER(TRIM('01_raw_data'!Q17))="TERMINATED"), "Terminated", IF(OR(UPPER(TRIM('01_raw_data'!Q17))="LEFT"),"Left",IF(OR(UPPER(TRIM('01_raw_data'!Q17))="RESIGNED"),"Resigned")))))),"Check") -> Active | S14: =IFERROR(IF(VALUE('01_raw_data'!R17)>0,VALUE('01_raw_data'!R17),"Check"),"Check") -> 66000 | T14: =IFERROR(IF(VALUE('01_raw_data'!S17)>0, VALUE('01_raw_data'!S17), "Check"), "Check") -> 3300 | U14: =IFERROR(VLOOKUP(UPPER(TRIM('01_raw_data'!T17)),'07_performance_master'!$A$5:$B$14,2,FALSE),"Check") -> Check | V14: =IFERROR(IF(VALUE('01_raw_data'!U17)>0,VALUE('01_raw_data'!U17),"Check"),"Check") -> 38 | W14: =IFERROR(IF(VALUE('01_raw_data'!V17)>=0, VALUE('01_raw_data'!V17), "Check"), "Check") -> 17 | X14: =IFERROR(IF(VALUE('01_raw_data'!W17)>=0, VALUE('01_raw_data'!W17),"Check"), "Check") -> 10 | Y14: =IFERROR(IF(AND(VALUE('01_raw_data'!X17)>=0, VALUE('01_raw_data'!X17)<=100), VALUE('01_raw_data'!X17), "Check"), "Check") -> 60 | Z14: =IFERROR(IF(OR(UPPER(TRIM('01_raw_data'!Y17))="YES", UPPER(TRIM('01_raw_data'!Y17))="PROMOTED"),"Promoted", IF(OR(UPPER(TRIM('01_raw_data'!Y17))="NO",UPPER(TRIM('01_raw_data'!Y17))="NOT PROMOTED"), "Not Promoted", "Check")),"Check") -> Not Promoted | AA14: =IFERROR(PROPER(TRIM('01_raw_data'!Z17)), "") -> Master'S | AB14: =IFERROR(PROPER(TRIM('01_raw_data'!AA17)),"") -> Linkedin | AC14: =IFERROR(IF(UPPER(TRIM('01_raw_data'!AB17))="HYBRID","Hybrid",IF(OR(UPPER(TRIM('01_raw_data'!AB17))="REMOTE",UPPER(TRIM('01_raw_data'!AB17))="WFH",UPPER(TRIM('01_raw_data'!AB17))="WORK FROM HOME"),"Remote",IF(OR(UPPER(TRIM('01_raw_data'!AB17))="ONSITE",UPPER(TRIM('01_raw_data'!AB17))="ON-SITE",UPPER(TRIM('01_raw_data'!AB17))="OFFICE"),"Office"))),"Check") -> Remote | AD14: =IFERROR(VLOOKUP(UPPER(TRIM('01_raw_data'!AC17)),'09_cost_center'!$A$5:$E$19,1,FALSE), "Check") -> EU-CC402 | AE14: =IFERROR(IF(OR(UPPER(TRIM('01_raw_data'!AD17))="CONTRACT", UPPER(TRIM('01_raw_data'!AD17))="CONTRACTOR"), "Contract", IF(OR(PROPER(TRIM('01_raw_data'!AD17))="FTE", UPPER(TRIM('01_raw_data'!AD17))="FULL TIME", UPPER(TRIM('01_raw_data'!AD17))="FULL-TIME"), "Full Time", IF(OR(UPPER(TRIM('01_raw_data'!AD17))="INTERN", UPPER(TRIM('01_raw_data'!AD17))="INTERNSHIP"), "Intern", IF(OR(UPPER(TRIM('01_raw_data'!AD17))="PART TIME", UPPER(TRIM('01_raw_data'!AD17))="PART-TIME"), "Part Time")))), "Check") -> Contract | AF14: =IFERROR(IF(AND(VALUE('01_raw_data'!AE17)>=0,VALUE('01_raw_data'!AE17)<=100), VALUE('01_raw_data'!AE17), "Check"), "Check") -> 62.5
A15: ="E"&TEXT(VALUE(SUBSTITUTE(UPPER(TRIM('01_raw_data'!A18)),"E","")),"0000") -> E0014 | B15: =IF('01_raw_data'!B18="", "", PROPER(TRIM('01_raw_data'!B18))) -> Maximilian Romano | C15: =_xlfn.XLOOKUP(PROPER(TRIM('01_raw_data'!C18)),'03_lookups'!$A$4:$A$9,'03_lookups'!$B$4:$B$9,"Needs Review") -> Female | D15: =VALUE('01_raw_data'!D18) -> 51 | E15: =IF(OR('01_raw_data'!E18="", LOWER(TRIM('01_raw_data'!E18))="not available"), "Missing", '01_raw_data'!E18) -> 27197 | F15: =IF(OR(E15="",LOWER(TRIM(E15))="not available"),"Missing",IF(ISNUMBER(E15),"Valid","Needs Review")) -> Valid | G15: =_xlfn.XLOOKUP(UPPER(TRIM('01_raw_data'!F18)),'04_departments'!A18:A73,'04_departments'!C18:C73,"Needs Review") -> Needs Review | H15: =_xlfn.XLOOKUP('01_clean_data'!G15, '04_departments'!$C$5:$C$60,'04_departments'!$D$5:$D$60,"Needs Review") -> Needs Review | I15: =PROPER(TRIM('01_raw_data'!H18)) -> Platform Engineer | J15: =IFERROR(UPPER('01_raw_data'!I18), "") -> L2 | K15: =IFERROR(UPPER('01_raw_data'!J18), "") -> M051 | L15: =IFERROR(VLOOKUP(K15,'05_manager_mapping'!$A$5:$B$64,2), "Missing") -> Eva Bianchi | M15: =IFERROR(_xlfn.XLOOKUP('01_raw_data'!L18,'06_location_master'!$B$5:$B$60,'06_location_master'!$C$5:$C$60), "Missing Location") -> Munich | N15: =IFERROR(_xlfn.XLOOKUP(M15,'06_location_master'!$C$5:$C$60,'06_location_master'!$D$5:$D$60), "Missing Country") -> Germany | O15: =IFERROR(_xlfn.XLOOKUP(M15,'06_location_master'!$C$5:$C$60,'06_location_master'!$E$5:$E$60), "Missing State") -> Bavaria | P15: =IFERROR(--'01_raw_data'!O18,"Missing Date") -> 45560 | Q15: =IF(TRIM('01_raw_data'!P18)="","", IFERROR('01_raw_data'!P18, "check")) | R15: =IFERROR(IF(OR(UPPER(TRIM('01_raw_data'!Q18))="A",UPPER(TRIM('01_raw_data'!Q18)="ACTVE"),UPPER(TRIM('01_raw_data'!Q18))="ACTIVE"), "Active", IF(OR(UPPER(TRIM('01_raw_data'!Q18)="INACTIVE"),UPPER(TRIM('01_raw_data'!Q18))="INACTVE"),"Inactive",IF(OR(UPPER(TRIM('01_raw_data'!Q18))="EXITED"), "Exited", IF(OR(UPPER(TRIM('01_raw_data'!Q18))="TERMINATED"), "Terminated", IF(OR(UPPER(TRIM('01_raw_data'!Q18))="LEFT"),"Left",IF(OR(UPPER(TRIM('01_raw_data'!Q18))="RESIGNED"),"Resigned")))))),"Check") -> Active | S15: =IFERROR(IF(VALUE('01_raw_data'!R18)>0,VALUE('01_raw_data'!R18),"Check"),"Check") -> 60000 | T15: =IFERROR(IF(VALUE('01_raw_data'!S18)>0, VALUE('01_raw_data'!S18), "Check"), "Check") -> 5400 | U15: =IFERROR(VLOOKUP(UPPER(TRIM('01_raw_data'!T18)),'07_performance_master'!$A$5:$B$14,2,FALSE),"Check") -> 4 | V15: =IFERROR(IF(VALUE('01_raw_data'!U18)>0,VALUE('01_raw_data'!U18),"Check"),"Check") -> 21 | W15: =IFERROR(IF(VALUE('01_raw_data'!V18)>=0, VALUE('01_raw_data'!V18), "Check"), "Check") -> 28 | X15: =IFERROR(IF(VALUE('01_raw_data'!W18)>=0, VALUE('01_raw_data'!W18),"Check"), "Check") -> 13 | Y15: =IFERROR(IF(AND(VALUE('01_raw_data'!X18)>=0, VALUE('01_raw_data'!X18)<=100), VALUE('01_raw_data'!X18), "Check"), "Check") -> 65 | Z15: =IFERROR(IF(OR(UPPER(TRIM('01_raw_data'!Y18))="YES", UPPER(TRIM('01_raw_data'!Y18))="PROMOTED"),"Promoted", IF(OR(UPPER(TRIM('01_raw_data'!Y18))="NO",UPPER(TRIM('01_raw_data'!Y18))="NOT PROMOTED"), "Not Promoted", "Check")),"Check") -> Not Promoted | AA15: =IFERROR(PROPER(TRIM('01_raw_data'!Z18)), "") -> Bachelor'S | AB15: =IFERROR(PROPER(TRIM('01_raw_data'!AA18)),"") -> European Job Board | AC15: =IFERROR(IF(UPPER(TRIM('01_raw_data'!AB18))="HYBRID","Hybrid",IF(OR(UPPER(TRIM('01_raw_data'!AB18))="REMOTE",UPPER(TRIM('01_raw_data'!AB18))="WFH",UPPER(TRIM('01_raw_data'!AB18))="WORK FROM HOME"),"Remote",IF(OR(UPPER(TRIM('01_raw_data'!AB18))="ONSITE",UPPER(TRIM('01_raw_data'!AB18))="ON-SITE",UPPER(TRIM('01_raw_data'!AB18))="OFFICE"),"Office"))),"Check") -> Hybrid | AD15: =IFERROR(VLOOKUP(UPPER(TRIM('01_raw_data'!AC18)),'09_cost_center'!$A$5:$E$19,1,FALSE), "Check") -> EU-CC101 | AE15: =IFERROR(IF(OR(UPPER(TRIM('01_raw_data'!AD18))="CONTRACT", UPPER(TRIM('01_raw_data'!AD18))="CONTRACTOR"), "Contract", IF(OR(PROPER(TRIM('01_raw_data'!AD18))="FTE", UPPER(TRIM('01_raw_data'!AD18))="FULL TIME", UPPER(TRIM('01_raw_data'!AD18))="FULL-TIME"), "Full Time", IF(OR(UPPER(TRIM('01_raw_data'!AD18))="INTERN", UPPER(TRIM('01_raw_data'!AD18))="INTERNSHIP"), "Intern", IF(OR(UPPER(TRIM('01_raw_data'!AD18))="PART TIME", UPPER(TRIM('01_raw_data'!AD18))="PART-TIME"), "Part Time")))), "Check") -> Full Time | AF15: =IFERROR(IF(AND(VALUE('01_raw_data'!AE18)>=0,VALUE('01_raw_data'!AE18)<=100), VALUE('01_raw_data'!AE18), "Check"), "Check") -> 67.5
A16: ="E"&TEXT(VALUE(SUBSTITUTE(UPPER(TRIM('01_raw_data'!A19)),"E","")),"0000") -> E0015 | B16: =IF('01_raw_data'!B19="", "", PROPER(TRIM('01_raw_data'!B19))) -> Aleksander Brown | C16: =_xlfn.XLOOKUP(PROPER(TRIM('01_raw_data'!C19)),'03_lookups'!$A$4:$A$9,'03_lookups'!$B$4:$B$9,"Needs Review") -> Female | D16: =VALUE('01_raw_data'!D19) -> 42 | E16: =IF(OR('01_raw_data'!E19="", LOWER(TRIM('01_raw_data'!E19))="not available"), "Missing", '01_raw_data'!E19) -> 30754 | F16: =IF(OR(E16="",LOWER(TRIM(E16))="not available"),"Missing",IF(ISNUMBER(E16),"Valid","Needs Review")) -> Valid | G16: =_xlfn.XLOOKUP(UPPER(TRIM('01_raw_data'!F19)),'04_departments'!A19:A74,'04_departments'!C19:C74,"Needs Review") -> Customer Success | H16: =_xlfn.XLOOKUP('01_clean_data'!G16, '04_departments'!$C$5:$C$60,'04_departments'!$D$5:$D$60,"Needs Review") -> Revenue | I16: =PROPER(TRIM('01_raw_data'!H19)) -> Client Success Associate | J16: =IFERROR(UPPER('01_raw_data'!I19), "") -> L2 | K16: =IFERROR(UPPER('01_raw_data'!J19), "") -> M050 | L16: =IFERROR(VLOOKUP(K16,'05_manager_mapping'!$A$5:$B$64,2), "Missing") -> Louis Szymanski | M16: =IFERROR(_xlfn.XLOOKUP('01_raw_data'!L19,'06_location_master'!$B$5:$B$60,'06_location_master'!$C$5:$C$60), "Missing Location") -> Munich | N16: =IFERROR(_xlfn.XLOOKUP(M16,'06_location_master'!$C$5:$C$60,'06_location_master'!$D$5:$D$60), "Missing Country") -> Germany | O16: =IFERROR(_xlfn.XLOOKUP(M16,'06_location_master'!$C$5:$C$60,'06_location_master'!$E$5:$E$60), "Missing State") -> Bavaria | P16: =IFERROR(--'01_raw_data'!O19,"Missing Date") -> 44699 | Q16: =IF(TRIM('01_raw_data'!P19)="","", IFERROR('01_raw_data'!P19, "check")) -> 45180 | R16: =IFERROR(IF(OR(UPPER(TRIM('01_raw_data'!Q19))="A",UPPER(TRIM('01_raw_data'!Q19)="ACTVE"),UPPER(TRIM('01_raw_data'!Q19))="ACTIVE"), "Active", IF(OR(UPPER(TRIM('01_raw_data'!Q19)="INACTIVE"),UPPER(TRIM('01_raw_data'!Q19))="INACTVE"),"Inactive",IF(OR(UPPER(TRIM('01_raw_data'!Q19))="EXITED"), "Exited", IF(OR(UPPER(TRIM('01_raw_data'!Q19))="TERMINATED"), "Terminated", IF(OR(UPPER(TRIM('01_raw_data'!Q19))="LEFT"),"Left",IF(OR(UPPER(TRIM('01_raw_data'!Q19))="RESIGNED"),"Resigned")))))),"Check") -> Inactive | S16: =IFERROR(IF(VALUE('01_raw_data'!R19)>0,VALUE('01_raw_data'!R19),"Check"),"Check") -> 53000 | T16: =IFERROR(IF(VALUE('01_raw_data'!S19)>0, VALUE('01_raw_data'!S19), "Check"), "Check") -> 4800 | U16: =IFERROR(VLOOKUP(UPPER(TRIM('01_raw_data'!T19)),'07_performance_master'!$A$5:$B$14,2,FALSE),"Check") -> 4 | V16: =IFERROR(IF(VALUE('01_raw_data'!U19)>0,VALUE('01_raw_data'!U19),"Check"),"Check") -> 24 | W16: =IFERROR(IF(VALUE('01_raw_data'!V19)>=0, VALUE('01_raw_data'!V19), "Check"), "Check") -> 4 | X16: =IFERROR(IF(VALUE('01_raw_data'!W19)>=0, VALUE('01_raw_data'!W19),"Check"), "Check") -> 5 | Y16: =IFERROR(IF(AND(VALUE('01_raw_data'!X19)>=0, VALUE('01_raw_data'!X19)<=100), VALUE('01_raw_data'!X19), "Check"), "Check") -> 52 | Z16: =IFERROR(IF(OR(UPPER(TRIM('01_raw_data'!Y19))="YES", UPPER(TRIM('01_raw_data'!Y19))="PROMOTED"),"Promoted", IF(OR(UPPER(TRIM('01_raw_data'!Y19))="NO",UPPER(TRIM('01_raw_data'!Y19))="NOT PROMOTED"), "Not Promoted", "Check")),"Check") -> Not Promoted | AA16: =IFERROR(PROPER(TRIM('01_raw_data'!Z19)), "") -> Master'S | AB16: =IFERROR(PROPER(TRIM('01_raw_data'!AA19)),"") -> Employee Referral | AC16: =IFERROR(IF(UPPER(TRIM('01_raw_data'!AB19))="HYBRID","Hybrid",IF(OR(UPPER(TRIM('01_raw_data'!AB19))="REMOTE",UPPER(TRIM('01_raw_data'!AB19))="WFH",UPPER(TRIM('01_raw_data'!AB19))="WORK FROM HOME"),"Remote",IF(OR(UPPER(TRIM('01_raw_data'!AB19))="ONSITE",UPPER(TRIM('01_raw_data'!AB19))="ON-SITE",UPPER(TRIM('01_raw_data'!AB19))="OFFICE"),"Office"))),"Check") -> Hybrid | AD16: =IFERROR(VLOOKUP(UPPER(TRIM('01_raw_data'!AC19)),'09_cost_center'!$A$5:$E$19,1,FALSE), "Check") -> EU-CC202 | AE16: =IFERROR(IF(OR(UPPER(TRIM('01_raw_data'!AD19))="CONTRACT", UPPER(TRIM('01_raw_data'!AD19))="CONTRACTOR"), "Contract", IF(OR(PROPER(TRIM('01_raw_data'!AD19))="FTE", UPPER(TRIM('01_raw_data'!AD19))="FULL TIME", UPPER(TRIM('01_raw_data'!AD19))="FULL-TIME"), "Full Time", IF(OR(UPPER(TRIM('01_raw_data'!AD19))="INTERN", UPPER(TRIM('01_raw_data'!AD19))="INTERNSHIP"), "Intern", IF(OR(UPPER(TRIM('01_raw_data'!AD19))="PART TIME", UPPER(TRIM('01_raw_data'!AD19))="PART-TIME"), "Part Time")))), "Check") -> Full Time | AF16: =IFERROR(IF(AND(VALUE('01_raw_data'!AE19)>=0,VALUE('01_raw_data'!AE19)<=100), VALUE('01_raw_data'!AE19), "Check"), "Check") -> 67.7
A17: ="E"&TEXT(VALUE(SUBSTITUTE(UPPER(TRIM('01_raw_data'!A20)),"E","")),"0000") -> E0016 | B17: =IF('01_raw_data'!B20="", "", PROPER(TRIM('01_raw_data'!B20))) -> Milan Mulder | C17: =_xlfn.XLOOKUP(PROPER(TRIM('01_raw_data'!C20)),'03_lookups'!$A$4:$A$9,'03_lookups'!$B$4:$B$9,"Needs Review") -> Female | D17: =VALUE('01_raw_data'!D20) -> 45 | E17: =IF(OR('01_raw_data'!E20="", LOWER(TRIM('01_raw_data'!E20))="not available"), "Missing", '01_raw_data'!E20) -> 29509 | F17: =IF(OR(E17="",LOWER(TRIM(E17))="not available"),"Missing",IF(ISNUMBER(E17),"Valid","Needs Review")) -> Valid | G17: =_xlfn.XLOOKUP(UPPER(TRIM('01_raw_data'!F20)),'04_departments'!A20:A75,'04_departments'!C20:C75,"Needs Review") -> Marketing | H17: =_xlfn.XLOOKUP('01_clean_data'!G17, '04_departments'!$C$5:$C$60,'04_departments'!$D$5:$D$60,"Needs Review") -> Revenue | I17: =PROPER(TRIM('01_raw_data'!H20)) -> Seo Specialist | J17: =IFERROR(UPPER('01_raw_data'!I20), "") -> L2 | K17: =IFERROR(UPPER('01_raw_data'!J20), "") -> M006 | L17: =IFERROR(VLOOKUP(K17,'05_manager_mapping'!$A$5:$B$64,2), "Missing") -> Aleksander Fischer | M17: =IFERROR(_xlfn.XLOOKUP('01_raw_data'!L20,'06_location_master'!$B$5:$B$60,'06_location_master'!$C$5:$C$60), "Missing Location") -> Frankfurt | N17: =IFERROR(_xlfn.XLOOKUP(M17,'06_location_master'!$C$5:$C$60,'06_location_master'!$D$5:$D$60), "Missing Country") -> Germany | O17: =IFERROR(_xlfn.XLOOKUP(M17,'06_location_master'!$C$5:$C$60,'06_location_master'!$E$5:$E$60), "Missing State") -> Hesse | P17: =IFERROR(--'01_raw_data'!O20,"Missing Date") -> 44325 | Q17: =IF(TRIM('01_raw_data'!P20)="","", IFERROR('01_raw_data'!P20, "check")) | R17: =IFERROR(IF(OR(UPPER(TRIM('01_raw_data'!Q20))="A",UPPER(TRIM('01_raw_data'!Q20)="ACTVE"),UPPER(TRIM('01_raw_data'!Q20))="ACTIVE"), "Active", IF(OR(UPPER(TRIM('01_raw_data'!Q20)="INACTIVE"),UPPER(TRIM('01_raw_data'!Q20))="INACTVE"),"Inactive",IF(OR(UPPER(TRIM('01_raw_data'!Q20))="EXITED"), "Exited", IF(OR(UPPER(TRIM('01_raw_data'!Q20))="TERMINATED"), "Terminated", IF(OR(UPPER(TRIM('01_raw_data'!Q20))="LEFT"),"Left",IF(OR(UPPER(TRIM('01_raw_data'!Q20))="RESIGNED"),"Resigned")))))),"Check") -> Active | S17: =IFERROR(IF(VALUE('01_raw_data'!R20)>0,VALUE('01_raw_data'!R20),"Check"),"Check") -> 63000 | T17: =IFERROR(IF(VALUE('01_raw_data'!S20)>0, VALUE('01_raw_data'!S20), "Check"), "Check") -> 3200 | U17: =IFERROR(VLOOKUP(UPPER(TRIM('01_raw_data'!T20)),'07_performance_master'!$A$5:$B$14,2,FALSE),"Check") -> 3 | V17: =IFERROR(IF(VALUE('01_raw_data'!U20)>0,VALUE('01_raw_data'!U20),"Check"),"Check") -> 22 | W17: =IFERROR(IF(VALUE('01_raw_data'!V20)>=0, VALUE('01_raw_data'!V20), "Check"), "Check") -> 0 | X17: =IFERROR(IF(VALUE('01_raw_data'!W20)>=0, VALUE('01_raw_data'!W20),"Check"), "Check") -> 9 | Y17: =IFERROR(IF(AND(VALUE('01_raw_data'!X20)>=0, VALUE('01_raw_data'!X20)<=100), VALUE('01_raw_data'!X20), "Check"), "Check") -> 57 | Z17: =IFERROR(IF(OR(UPPER(TRIM('01_raw_data'!Y20))="YES", UPPER(TRIM('01_raw_data'!Y20))="PROMOTED"),"Promoted", IF(OR(UPPER(TRIM('01_raw_data'!Y20))="NO",UPPER(TRIM('01_raw_data'!Y20))="NOT PROMOTED"), "Not Promoted", "Check")),"Check") -> Not Promoted | AA17: =IFERROR(PROPER(TRIM('01_raw_data'!Z20)), "") -> Master'S | AB17: =IFERROR(PROPER(TRIM('01_raw_data'!AA20)),"") -> Internal Transfer | AC17: =IFERROR(IF(UPPER(TRIM('01_raw_data'!AB20))="HYBRID","Hybrid",IF(OR(UPPER(TRIM('01_raw_data'!AB20))="REMOTE",UPPER(TRIM('01_raw_data'!AB20))="WFH",UPPER(TRIM('01_raw_data'!AB20))="WORK FROM HOME"),"Remote",IF(OR(UPPER(TRIM('01_raw_data'!AB20))="ONSITE",UPPER(TRIM('01_raw_data'!AB20))="ON-SITE",UPPER(TRIM('01_raw_data'!AB20))="OFFICE"),"Office"))),"Check") -> Hybrid | AD17: =IFERROR(VLOOKUP(UPPER(TRIM('01_raw_data'!AC20)),'09_cost_center'!$A$5:$E$19,1,FALSE), "Check") -> EU-CC203 | AE17: =IFERROR(IF(OR(UPPER(TRIM('01_raw_data'!AD20))="CONTRACT", UPPER(TRIM('01_raw_data'!AD20))="CONTRACTOR"), "Contract", IF(OR(PROPER(TRIM('01_raw_data'!AD20))="FTE", UPPER(TRIM('01_raw_data'!AD20))="FULL TIME", UPPER(TRIM('01_raw_data'!AD20))="FULL-TIME"), "Full Time", IF(OR(UPPER(TRIM('01_raw_data'!AD20))="INTERN", UPPER(TRIM('01_raw_data'!AD20))="INTERNSHIP"), "Intern", IF(OR(UPPER(TRIM('01_raw_data'!AD20))="PART TIME", UPPER(TRIM('01_raw_data'!AD20))="PART-TIME"), "Part Time")))), "Check") -> Part Time | AF17: =IFERROR(IF(AND(VALUE('01_raw_data'!AE20)>=0,VALUE('01_raw_data'!AE20)<=100), VALUE('01_raw_data'!AE20), "Check"), "Check") -> 58
A18: ="E"&TEXT(VALUE(SUBSTITUTE(UPPER(TRIM('01_raw_data'!A21)),"E","")),"0000") -> E0017 | B18: =IF('01_raw_data'!B21="", "", PROPER(TRIM('01_raw_data'!B21))) -> Valeria Olsson | C18: =_xlfn.XLOOKUP(PROPER(TRIM('01_raw_data'!C21)),'03_lookups'!$A$4:$A$9,'03_lookups'!$B$4:$B$9,"Needs Review") -> Male | D18: =VALUE('01_raw_data'!D21) -> 28 | E18: =IF(OR('01_raw_data'!E21="", LOWER(TRIM('01_raw_data'!E21))="not available"), "Missing", '01_raw_data'!E21) -> 35861 | F18: =IF(OR(E18="",LOWER(TRIM(E18))="not available"),"Missing",IF(ISNUMBER(E18),"Valid","Needs Review")) -> Valid | G18: =_xlfn.XLOOKUP(UPPER(TRIM('01_raw_data'!F21)),'04_departments'!A21:A76,'04_departments'!C21:C76,"Needs Review") -> Needs Review | H18: =_xlfn.XLOOKUP('01_clean_data'!G18, '04_departments'!$C$5:$C$60,'04_departments'!$D$5:$D$60,"Needs Review") -> Needs Review | I18: =PROPER(TRIM('01_raw_data'!H21)) -> Analytics Engineer | J18: =IFERROR(UPPER('01_raw_data'!I21), "") -> L2 | K18: =IFERROR(UPPER('01_raw_data'!J21), "") -> M003 | L18: =IFERROR(VLOOKUP(K18,'05_manager_mapping'!$A$5:$B$64,2), "Missing") -> Sarah Lopez | M18: =IFERROR(_xlfn.XLOOKUP('01_raw_data'!L21,'06_location_master'!$B$5:$B$60,'06_location_master'!$C$5:$C$60), "Missing Location") -> Stockholm | N18: =IFERROR(_xlfn.XLOOKUP(M18,'06_location_master'!$C$5:$C$60,'06_location_master'!$D$5:$D$60), "Missing Country") -> Sweden | O18: =IFERROR(_xlfn.XLOOKUP(M18,'06_location_master'!$C$5:$C$60,'06_location_master'!$E$5:$E$60), "Missing State") -> Stockholm County | P18: =IFERROR(--'01_raw_data'!O21,"Missing Date") -> 42737 | Q18: =IF(TRIM('01_raw_data'!P21)="","", IFERROR('01_raw_data'!P21, "check")) | R18: =IFERROR(IF(OR(UPPER(TRIM('01_raw_data'!Q21))="A",UPPER(TRIM('01_raw_data'!Q21)="ACTVE"),UPPER(TRIM('01_raw_data'!Q21))="ACTIVE"), "Active", IF(OR(UPPER(TRIM('01_raw_data'!Q21)="INACTIVE"),UPPER(TRIM('01_raw_data'!Q21))="INACTVE"),"Inactive",IF(OR(UPPER(TRIM('01_raw_data'!Q21))="EXITED"), "Exited", IF(OR(UPPER(TRIM('01_raw_data'!Q21))="TERMINATED"), "Terminated", IF(OR(UPPER(TRIM('01_raw_data'!Q21))="LEFT"),"Left",IF(OR(UPPER(TRIM('01_raw_data'!Q21))="RESIGNED"),"Resigned")))))),"Check") -> Active | S18: =IFERROR(IF(VALUE('01_raw_data'!R21)>0,VALUE('01_raw_data'!R21),"Check"),"Check") -> 64000 | T18: =IFERROR(IF(VALUE('01_raw_data'!S21)>0, VALUE('01_raw_data'!S21), "Check"), "Check") -> 1300 | U18: =IFERROR(VLOOKUP(UPPER(TRIM('01_raw_data'!T21)),'07_performance_master'!$A$5:$B$14,2,FALSE),"Check") -> 2 | V18: =IFERROR(IF(VALUE('01_raw_data'!U21)>0,VALUE('01_raw_data'!U21),"Check"),"Check") -> 33 | W18: =IFERROR(IF(VALUE('01_raw_data'!V21)>=0, VALUE('01_raw_data'!V21), "Check"), "Check") -> 9 | X18: =IFERROR(IF(VALUE('01_raw_data'!W21)>=0, VALUE('01_raw_data'!W21),"Check"), "Check") -> 20 | Y18: =IFERROR(IF(AND(VALUE('01_raw_data'!X21)>=0, VALUE('01_raw_data'!X21)<=100), VALUE('01_raw_data'!X21), "Check"), "Check") -> 45 | Z18: =IFERROR(IF(OR(UPPER(TRIM('01_raw_data'!Y21))="YES", UPPER(TRIM('01_raw_data'!Y21))="PROMOTED"),"Promoted", IF(OR(UPPER(TRIM('01_raw_data'!Y21))="NO",UPPER(TRIM('01_raw_data'!Y21))="NOT PROMOTED"), "Not Promoted", "Check")),"Check") -> Not Promoted | AA18: =IFERROR(PROPER(TRIM('01_raw_data'!Z21)), "") -> Bachelor'S | AB18: =IFERROR(PROPER(TRIM('01_raw_data'!AA21)),"") -> European Job Board | AC18: =IFERROR(IF(UPPER(TRIM('01_raw_data'!AB21))="HYBRID","Hybrid",IF(OR(UPPER(TRIM('01_raw_data'!AB21))="REMOTE",UPPER(TRIM('01_raw_data'!AB21))="WFH",UPPER(TRIM('01_raw_data'!AB21))="WORK FROM HOME"),"Remote",IF(OR(UPPER(TRIM('01_raw_data'!AB21))="ONSITE",UPPER(TRIM('01_raw_data'!AB21))="ON-SITE",UPPER(TRIM('01_raw_data'!AB21))="OFFICE"),"Office"))),"Check") -> Hybrid | AD18: =IFERROR(VLOOKUP(UPPER(TRIM('01_raw_data'!AC21)),'09_cost_center'!$A$5:$E$19,1,FALSE), "Check") -> EU-CC103 | AE18: =IFERROR(IF(OR(UPPER(TRIM('01_raw_data'!AD21))="CONTRACT", UPPER(TRIM('01_raw_data'!AD21))="CONTRACTOR"), "Contract", IF(OR(PROPER(TRIM('01_raw_data'!AD21))="FTE", UPPER(TRIM('01_raw_data'!AD21))="FULL TIME", UPPER(TRIM('01_raw_data'!AD21))="FULL-TIME"), "Full Time", IF(OR(UPPER(TRIM('01_raw_data'!AD21))="INTERN", UPPER(TRIM('01_raw_data'!AD21))="INTERNSHIP"), "Intern", IF(OR(UPPER(TRIM('01_raw_data'!AD21))="PART TIME", UPPER(TRIM('01_raw_data'!AD21))="PART-TIME"), "Part Time")))), "Check") -> Part Time | AF18: =IFERROR(IF(AND(VALUE('01_raw_data'!AE21)>=0,VALUE('01_raw_data'!AE21)<=100), VALUE('01_raw_data'!AE21), "Check"), "Check") -> 42
A19: ="E"&TEXT(VALUE(SUBSTITUTE(UPPER(TRIM('01_raw_data'!A22)),"E","")),"0000") -> E0018 | B19: =IF('01_raw_data'!B22="", "", PROPER(TRIM('01_raw_data'!B22))) -> Luuk Rodriguez | C19: =_xlfn.XLOOKUP(PROPER(TRIM('01_raw_data'!C22)),'03_lookups'!$A$4:$A$9,'03_lookups'!$B$4:$B$9,"Needs Review") -> Male | D19: =VALUE('01_raw_data'!D22) -> 26 | E19: =IF(OR('01_raw_data'!E22="", LOWER(TRIM('01_raw_data'!E22))="not available"), "Missing", '01_raw_data'!E22) -> 36486 | F19: =IF(OR(E19="",LOWER(TRIM(E19))="not available"),"Missing",IF(ISNUMBER(E19),"Valid","Needs Review")) -> Valid | G19: =_xlfn.XLOOKUP(UPPER(TRIM('01_raw_data'!F22)),'04_departments'!A22:A77,'04_departments'!C22:C77,"Needs Review") -> Customer Success | H19: =_xlfn.XLOOKUP('01_clean_data'!G19, '04_departments'!$C$5:$C$60,'04_departments'!$D$5:$D$60,"Needs Review") -> Revenue | I19: =PROPER(TRIM('01_raw_data'!H22)) -> Customer Success Manager | J19: =IFERROR(UPPER('01_raw_data'!I22), "") -> L3 | K19: =IFERROR(UPPER('01_raw_data'!J22), "") -> M024 | L19: =IFERROR(VLOOKUP(K19,'05_manager_mapping'!$A$5:$B$64,2), "Missing") -> Noah Ryan | M19: =IFERROR(_xlfn.XLOOKUP('01_raw_data'!L22,'06_location_master'!$B$5:$B$60,'06_location_master'!$C$5:$C$60), "Missing Location") -> Missing Location | N19: =IFERROR(_xlfn.XLOOKUP(M19,'06_location_master'!$C$5:$C$60,'06_location_master'!$D$5:$D$60), "Missing Country") -> Missing Country | O19: =IFERROR(_xlfn.XLOOKUP(M19,'06_location_master'!$C$5:$C$60,'06_location_master'!$E$5:$E$60), "Missing State") -> Missing State | P19: =IFERROR(--'01_raw_data'!O22,"Missing Date") -> 44684 | Q19: =IF(TRIM('01_raw_data'!P22)="","", IFERROR('01_raw_data'!P22, "check")) | R19: =IFERROR(IF(OR(UPPER(TRIM('01_raw_data'!Q22))="A",UPPER(TRIM('01_raw_data'!Q22)="ACTVE"),UPPER(TRIM('01_raw_data'!Q22))="ACTIVE"), "Active", IF(OR(UPPER(TRIM('01_raw_data'!Q22)="INACTIVE"),UPPER(TRIM('01_raw_data'!Q22))="INACTVE"),"Inactive",IF(OR(UPPER(TRIM('01_raw_data'!Q22))="EXITED"), "Exited", IF(OR(UPPER(TRIM('01_raw_data'!Q22))="TERMINATED"), "Terminated", IF(OR(UPPER(TRIM('01_raw_data'!Q22))="LEFT"),"Left",IF(OR(UPPER(TRIM('01_raw_data'!Q22))="RESIGNED"),"Resigned")))))),"Check") -> Active | S19: =IFERROR(IF(VALUE('01_raw_data'!R22)>0,VALUE('01_raw_data'!R22),"Check"),"Check") -> 72000 | T19: =IFERROR(IF(VALUE('01_raw_data'!S22)>0, VALUE('01_raw_data'!S22), "Check"), "Check") -> 6500 | U19: =IFERROR(VLOOKUP(UPPER(TRIM('01_raw_data'!T22)),'07_performance_master'!$A$5:$B$14,2,FALSE),"Check") -> 4 | V19: =IFERROR(IF(VALUE('01_raw_data'!U22)>0,VALUE('01_raw_data'!U22),"Check"),"Check") -> 7 | W19: =IFERROR(IF(VALUE('01_raw_data'!V22)>=0, VALUE('01_raw_data'!V22), "Check"), "Check") -> 7 | X19: =IFERROR(IF(VALUE('01_raw_data'!W22)>=0, VALUE('01_raw_data'!W22),"Check"), "Check") -> 13 | Y19: =IFERROR(IF(AND(VALUE('01_raw_data'!X22)>=0, VALUE('01_raw_data'!X22)<=100), VALUE('01_raw_data'!X22), "Check"), "Check") -> Check | Z19: =IFERROR(IF(OR(UPPER(TRIM('01_raw_data'!Y22))="YES", UPPER(TRIM('01_raw_data'!Y22))="PROMOTED"),"Promoted", IF(OR(UPPER(TRIM('01_raw_data'!Y22))="NO",UPPER(TRIM('01_raw_data'!Y22))="NOT PROMOTED"), "Not Promoted", "Check")),"Check") -> Not Promoted | AA19: =IFERROR(PROPER(TRIM('01_raw_data'!Z22)), "") -> Bachelor'S | AB19: =IFERROR(PROPER(TRIM('01_raw_data'!AA22)),"") -> Company Careers Page | AC19: =IFERROR(IF(UPPER(TRIM('01_raw_data'!AB22))="HYBRID","Hybrid",IF(OR(UPPER(TRIM('01_raw_data'!AB22))="REMOTE",UPPER(TRIM('01_raw_data'!AB22))="WFH",UPPER(TRIM('01_raw_data'!AB22))="WORK FROM HOME"),"Remote",IF(OR(UPPER(TRIM('01_raw_data'!AB22))="ONSITE",UPPER(TRIM('01_raw_data'!AB22))="ON-SITE",UPPER(TRIM('01_raw_data'!AB22))="OFFICE"),"Office"))),"Check") -> Hybrid | AD19: =IFERROR(VLOOKUP(UPPER(TRIM('01_raw_data'!AC22)),'09_cost_center'!$A$5:$E$19,1,FALSE), "Check") -> EU-CC202 | AE19: =IFERROR(IF(OR(UPPER(TRIM('01_raw_data'!AD22))="CONTRACT", UPPER(TRIM('01_raw_data'!AD22))="CONTRACTOR"), "Contract", IF(OR(PROPER(TRIM('01_raw_data'!AD22))="FTE", UPPER(TRIM('01_raw_data'!AD22))="FULL TIME", UPPER(TRIM('01_raw_data'!AD22))="FULL-TIME"), "Full Time", IF(OR(UPPER(TRIM('01_raw_data'!AD22))="INTERN", UPPER(TRIM('01_raw_data'!AD22))="INTERNSHIP"), "Intern", IF(OR(UPPER(TRIM('01_raw_data'!AD22))="PART TIME", UPPER(TRIM('01_raw_data'!AD22))="PART-TIME"), "Part Time")))), "Check") -> Full Time | AF19: =IFERROR(IF(AND(VALUE('01_raw_data'!AE22)>=0,VALUE('01_raw_data'!AE22)<=100), VALUE('01_raw_data'!AE22), "Check"), "Check") -> 70.7
A20: ="E"&TEXT(VALUE(SUBSTITUTE(UPPER(TRIM('01_raw_data'!A23)),"E","")),"0000") -> E0019 | B20: =IF('01_raw_data'!B23="", "", PROPER(TRIM('01_raw_data'!B23))) -> Linnea Costa | C20: =_xlfn.XLOOKUP(PROPER(TRIM('01_raw_data'!C23)),'03_lookups'!$A$4:$A$9,'03_lookups'!$B$4:$B$9,"Needs Review") -> Male | D20: =VALUE('01_raw_data'!D23) -> 35 | E20: =IF(OR('01_raw_data'!E23="", LOWER(TRIM('01_raw_data'!E23))="not available"), "Missing", '01_raw_data'!E23) -> 07-29-1990 | F20: =IF(OR(E20="",LOWER(TRIM(E20))="not available"),"Missing",IF(ISNUMBER(E20),"Valid","Needs Review")) -> Needs Review | G20: =_xlfn.XLOOKUP(UPPER(TRIM('01_raw_data'!F23)),'04_departments'!A23:A78,'04_departments'!C23:C78,"Needs Review") -> Needs Review | H20: =_xlfn.XLOOKUP('01_clean_data'!G20, '04_departments'!$C$5:$C$60,'04_departments'!$D$5:$D$60,"Needs Review") -> Needs Review | I20: =PROPER(TRIM('01_raw_data'!H23)) -> Product Manager | J20: =IFERROR(UPPER('01_raw_data'!I23), "") -> L3 | K20: =IFERROR(UPPER('01_raw_data'!J23), "") -> M028 | L20: =IFERROR(VLOOKUP(K20,'05_manager_mapping'!$A$5:$B$64,2), "Missing") -> Sara Fernandes | M20: =IFERROR(_xlfn.XLOOKUP('01_raw_data'!L23,'06_location_master'!$B$5:$B$60,'06_location_master'!$C$5:$C$60), "Missing Location") -> Dublin | N20: =IFERROR(_xlfn.XLOOKUP(M20,'06_location_master'!$C$5:$C$60,'06_location_master'!$D$5:$D$60), "Missing Country") -> Ireland | O20: =IFERROR(_xlfn.XLOOKUP(M20,'06_location_master'!$C$5:$C$60,'06_location_master'!$E$5:$E$60), "Missing State") -> Leinster | P20: =IFERROR(--'01_raw_data'!O23,"Missing Date") -> 42749 | Q20: =IF(TRIM('01_raw_data'!P23)="","", IFERROR('01_raw_data'!P23, "check")) | R20: =IFERROR(IF(OR(UPPER(TRIM('01_raw_data'!Q23))="A",UPPER(TRIM('01_raw_data'!Q23)="ACTVE"),UPPER(TRIM('01_raw_data'!Q23))="ACTIVE"), "Active", IF(OR(UPPER(TRIM('01_raw_data'!Q23)="INACTIVE"),UPPER(TRIM('01_raw_data'!Q23))="INACTVE"),"Inactive",IF(OR(UPPER(TRIM('01_raw_data'!Q23))="EXITED"), "Exited", IF(OR(UPPER(TRIM('01_raw_data'!Q23))="TERMINATED"), "Terminated", IF(OR(UPPER(TRIM('01_raw_data'!Q23))="LEFT"),"Left",IF(OR(UPPER(TRIM('01_raw_data'!Q23))="RESIGNED"),"Resigned")))))),"Check") -> Active | S20: =IFERROR(IF(VALUE('01_raw_data'!R23)>0,VALUE('01_raw_data'!R23),"Check"),"Check") -> 85000 | T20: =IFERROR(IF(VALUE('01_raw_data'!S23)>0, VALUE('01_raw_data'!S23), "Check"), "Check") -> 4200 | U20: =IFERROR(VLOOKUP(UPPER(TRIM('01_raw_data'!T23)),'07_performance_master'!$A$5:$B$14,2,FALSE),"Check") -> 3 | V20: =IFERROR(IF(VALUE('01_raw_data'!U23)>0,VALUE('01_raw_data'!U23),"Check"),"Check") -> 26 | W20: =IFERROR(IF(VALUE('01_raw_data'!V23)>=0, VALUE('01_raw_data'!V23), "Check"), "Check") -> 25 | X20: =IFERROR(IF(VALUE('01_raw_data'!W23)>=0, VALUE('01_raw_data'!W23),"Check"), "Check") -> 9 | Y20: =IFERROR(IF(AND(VALUE('01_raw_data'!X23)>=0, VALUE('01_raw_data'!X23)<=100), VALUE('01_raw_data'!X23), "Check"), "Check") -> 52 | Z20: =IFERROR(IF(OR(UPPER(TRIM('01_raw_data'!Y23))="YES", UPPER(TRIM('01_raw_data'!Y23))="PROMOTED"),"Promoted", IF(OR(UPPER(TRIM('01_raw_data'!Y23))="NO",UPPER(TRIM('01_raw_data'!Y23))="NOT PROMOTED"), "Not Promoted", "Check")),"Check") -> Not Promoted | AA20: =IFERROR(PROPER(TRIM('01_raw_data'!Z23)), "") -> Master'S | AB20: =IFERROR(PROPER(TRIM('01_raw_data'!AA23)),"") -> Internal Transfer | AC20: =IFERROR(IF(UPPER(TRIM('01_raw_data'!AB23))="HYBRID","Hybrid",IF(OR(UPPER(TRIM('01_raw_data'!AB23))="REMOTE",UPPER(TRIM('01_raw_data'!AB23))="WFH",UPPER(TRIM('01_raw_data'!AB23))="WORK FROM HOME"),"Remote",IF(OR(UPPER(TRIM('01_raw_data'!AB23))="ONSITE",UPPER(TRIM('01_raw_data'!AB23))="ON-SITE",UPPER(TRIM('01_raw_data'!AB23))="OFFICE"),"Office"))),"Check") -> Remote | AD20: =IFERROR(VLOOKUP(UPPER(TRIM('01_raw_data'!AC23)),'09_cost_center'!$A$5:$E$19,1,FALSE), "Check") -> EU-CC102 | AE20: =IFERROR(IF(OR(UPPER(TRIM('01_raw_data'!AD23))="CONTRACT", UPPER(TRIM('01_raw_data'!AD23))="CONTRACTOR"), "Contract", IF(OR(PROPER(TRIM('01_raw_data'!AD23))="FTE", UPPER(TRIM('01_raw_data'!AD23))="FULL TIME", UPPER(TRIM('01_raw_data'!AD23))="FULL-TIME"), "Full Time", IF(OR(UPPER(TRIM('01_raw_data'!AD23))="INTERN", UPPER(TRIM('01_raw_data'!AD23))="INTERNSHIP"), "Intern", IF(OR(UPPER(TRIM('01_raw_data'!AD23))="PART TIME", UPPER(TRIM('01_raw_data'!AD23))="PART-TIME"), "Part Time")))), "Check") -> Full Time | AF20: =IFERROR(IF(AND(VALUE('01_raw_data'!AE23)>=0,VALUE('01_raw_data'!AE23)<=100), VALUE('01_raw_data'!AE23), "Check"), "Check") -> 57.2
A21: ="E"&TEXT(VALUE(SUBSTITUTE(UPPER(TRIM('01_raw_data'!A24)),"E","")),"0000") -> E0020 | B21: =IF('01_raw_data'!B24="", "", PROPER(TRIM('01_raw_data'!B24))) -> Camille Bianchi | C21: =_xlfn.XLOOKUP(PROPER(TRIM('01_raw_data'!C24)),'03_lookups'!$A$4:$A$9,'03_lookups'!$B$4:$B$9,"Needs Review") -> Male | D21: =VALUE('01_raw_data'!D24) -> 36 | E21: =IF(OR('01_raw_data'!E24="", LOWER(TRIM('01_raw_data'!E24))="not available"), "Missing", '01_raw_data'!E24) -> 32707 | F21: =IF(OR(E21="",LOWER(TRIM(E21))="not available"),"Missing",IF(ISNUMBER(E21),"Valid","Needs Review")) -> Valid | G21: =_xlfn.XLOOKUP(UPPER(TRIM('01_raw_data'!F24)),'04_departments'!A24:A79,'04_departments'!C24:C79,"Needs Review") -> Needs Review | H21: =_xlfn.XLOOKUP('01_clean_data'!G21, '04_departments'!$C$5:$C$60,'04_departments'!$D$5:$D$60,"Needs Review") -> Needs Review | I21: =PROPER(TRIM('01_raw_data'!H24)) -> Senior Software Engineer | J21: =IFERROR(UPPER('01_raw_data'!I24), "") -> L2 | K21: =IFERROR(UPPER('01_raw_data'!J24), "") -> M001 | L21: =IFERROR(VLOOKUP(K21,'05_manager_mapping'!$A$5:$B$64,2), "Missing") -> Milan Leroy | M21: =IFERROR(_xlfn.XLOOKUP('01_raw_data'!L24,'06_location_master'!$B$5:$B$60,'06_location_master'!$C$5:$C$60), "Missing Location") -> London | N21: =IFERROR(_xlfn.XLOOKUP(M21,'06_location_master'!$C$5:$C$60,'06_location_master'!$D$5:$D$60), "Missing Country") -> United Kingdom | O21: =IFERROR(_xlfn.XLOOKUP(M21,'06_location_master'!$C$5:$C$60,'06_location_master'!$E$5:$E$60), "Missing State") -> England | P21: =IFERROR(--'01_raw_data'!O24,"Missing Date") -> 45589 | Q21: =IF(TRIM('01_raw_data'!P24)="","", IFERROR('01_raw_data'!P24, "check")) | R21: =IFERROR(IF(OR(UPPER(TRIM('01_raw_data'!Q24))="A",UPPER(TRIM('01_raw_data'!Q24)="ACTVE"),UPPER(TRIM('01_raw_data'!Q24))="ACTIVE"), "Active", IF(OR(UPPER(TRIM('01_raw_data'!Q24)="INACTIVE"),UPPER(TRIM('01_raw_data'!Q24))="INACTVE"),"Inactive",IF(OR(UPPER(TRIM('01_raw_data'!Q24))="EXITED"), "Exited", IF(OR(UPPER(TRIM('01_raw_data'!Q24))="TERMINATED"), "Terminated", IF(OR(UPPER(TRIM('01_raw_data'!Q24))="LEFT"),"Left",IF(OR(UPPER(TRIM('01_raw_data'!Q24))="RESIGNED"),"Resigned")))))),"Check") -> Active | S21: =IFERROR(IF(VALUE('01_raw_data'!R24)>0,VALUE('01_raw_data'!R24),"Check"),"Check") -> 70000 | T21: =IFERROR(IF(VALUE('01_raw_data'!S24)>0, VALUE('01_raw_data'!S24), "Check"), "Check") -> 3500 | U21: =IFERROR(VLOOKUP(UPPER(TRIM('01_raw_data'!T24)),'07_performance_master'!$A$5:$B$14,2,FALSE),"Check") -> 3 | V21: =IFERROR(IF(VALUE('01_raw_data'!U24)>0,VALUE('01_raw_data'!U24),"Check"),"Check") -> 13 | W21: =IFERROR(IF(VALUE('01_raw_data'!V24)>=0, VALUE('01_raw_data'!V24), "Check"), "Check") -> 16 | X21: =IFERROR(IF(VALUE('01_raw_data'!W24)>=0, VALUE('01_raw_data'!W24),"Check"), "Check") -> 6 | Y21: =IFERROR(IF(AND(VALUE('01_raw_data'!X24)>=0, VALUE('01_raw_data'!X24)<=100), VALUE('01_raw_data'!X24), "Check"), "Check") -> 70 | Z21: =IFERROR(IF(OR(UPPER(TRIM('01_raw_data'!Y24))="YES", UPPER(TRIM('01_raw_data'!Y24))="PROMOTED"),"Promoted", IF(OR(UPPER(TRIM('01_raw_data'!Y24))="NO",UPPER(TRIM('01_raw_data'!Y24))="NOT PROMOTED"), "Not Promoted", "Check")),"Check") -> Not Promoted | AA21: =IFERROR(PROPER(TRIM('01_raw_data'!Z24)), "") -> Bachelor'S | AB21: =IFERROR(PROPER(TRIM('01_raw_data'!AA24)),"") -> European Job Board | AC21: =IFERROR(IF(UPPER(TRIM('01_raw_data'!AB24))="HYBRID","Hybrid",IF(OR(UPPER(TRIM('01_raw_data'!AB24))="REMOTE",UPPER(TRIM('01_raw_data'!AB24))="WFH",UPPER(TRIM('01_raw_data'!AB24))="WORK FROM HOME"),"Remote",IF(OR(UPPER(TRIM('01_raw_data'!AB24))="ONSITE",UPPER(TRIM('01_raw_data'!AB24))="ON-SITE",UPPER(TRIM('01_raw_data'!AB24))="OFFICE"),"Office"))),"Check") -> Office | AD21: =IFERROR(VLOOKUP(UPPER(TRIM('01_raw_data'!AC24)),'09_cost_center'!$A$5:$E$19,1,FALSE), "Check") -> EU-CC101 | AE21: =IFERROR(IF(OR(UPPER(TRIM('01_raw_data'!AD24))="CONTRACT", UPPER(TRIM('01_raw_data'!AD24))="CONTRACTOR"), "Contract", IF(OR(PROPER(TRIM('01_raw_data'!AD24))="FTE", UPPER(TRIM('01_raw_data'!AD24))="FULL TIME", UPPER(TRIM('01_raw_data'!AD24))="FULL-TIME"), "Full Time", IF(OR(UPPER(TRIM('01_raw_data'!AD24))="INTERN", UPPER(TRIM('01_raw_data'!AD24))="INTERNSHIP"), "Intern", IF(OR(UPPER(TRIM('01_raw_data'!AD24))="PART TIME", UPPER(TRIM('01_raw_data'!AD24))="PART-TIME"), "Part Time")))), "Check") -> Full Time | AF21: =IFERROR(IF(AND(VALUE('01_raw_data'!AE24)>=0,VALUE('01_raw_data'!AE24)<=100), VALUE('01_raw_data'!AE24), "Check"), "Check") -> 61.8
A22: ="E"&TEXT(VALUE(SUBSTITUTE(UPPER(TRIM('01_raw_data'!A25)),"E","")),"0000") -> E0021 | B22: =IF('01_raw_data'!B25="", "", PROPER(TRIM('01_raw_data'!B25))) -> Sofia Costa | C22: =_xlfn.XLOOKUP(PROPER(TRIM('01_raw_data'!C25)),'03_lookups'!$A$4:$A$9,'03_lookups'!$B$4:$B$9,"Needs Review") -> Male | D22: =VALUE('01_raw_data'!D25) -> 38 | E22: =IF(OR('01_raw_data'!E25="", LOWER(TRIM('01_raw_data'!E25))="not available"), "Missing", '01_raw_data'!E25) -> 32295 | F22: =IF(OR(E22="",LOWER(TRIM(E22))="not available"),"Missing",IF(ISNUMBER(E22),"Valid","Needs Review")) -> Valid | G22: =_xlfn.XLOOKUP(UPPER(TRIM('01_raw_data'!F25)),'04_departments'!A25:A80,'04_departments'!C25:C80,"Needs Review") -> Needs Review | H22: =_xlfn.XLOOKUP('01_clean_data'!G22, '04_departments'!$C$5:$C$60,'04_departments'!$D$5:$D$60,"Needs Review") -> Needs Review | I22: =PROPER(TRIM('01_raw_data'!H25)) -> Platform Engineer | J22: =IFERROR(UPPER('01_raw_data'!I25), "") -> L6 | K22: =IFERROR(UPPER('01_raw_data'!J25), "") -> M048 | L22: =IFERROR(VLOOKUP(K22,'05_manager_mapping'!$A$5:$B$64,2), "Missing") -> Jack Schmidt | M22: =IFERROR(_xlfn.XLOOKUP('01_raw_data'!L25,'06_location_master'!$B$5:$B$60,'06_location_master'!$C$5:$C$60), "Missing Location") -> Missing Location | N22: =IFERROR(_xlfn.XLOOKUP(M22,'06_location_master'!$C$5:$C$60,'06_location_master'!$D$5:$D$60), "Missing Country") -> Missing Country | O22: =IFERROR(_xlfn.XLOOKUP(M22,'06_location_master'!$C$5:$C$60,'06_location_master'!$E$5:$E$60), "Missing State") -> Missing State | P22: =IFERROR(--'01_raw_data'!O25,"Missing Date") -> 45988 | Q22: =IF(TRIM('01_raw_data'!P25)="","", IFERROR('01_raw_data'!P25, "check")) | R22: =IFERROR(IF(OR(UPPER(TRIM('01_raw_data'!Q25))="A",UPPER(TRIM('01_raw_data'!Q25)="ACTVE"),UPPER(TRIM('01_raw_data'!Q25))="ACTIVE"), "Active", IF(OR(UPPER(TRIM('01_raw_data'!Q25)="INACTIVE"),UPPER(TRIM('01_raw_data'!Q25))="INACTVE"),"Inactive",IF(OR(UPPER(TRIM('01_raw_data'!Q25))="EXITED"), "Exited", IF(OR(UPPER(TRIM('01_raw_data'!Q25))="TERMINATED"), "Terminated", IF(OR(UPPER(TRIM('01_raw_data'!Q25))="LEFT"),"Left",IF(OR(UPPER(TRIM('01_raw_data'!Q25))="RESIGNED"),"Resigned")))))),"Check") -> Active | S22: =IFERROR(IF(VALUE('01_raw_data'!R25)>0,VALUE('01_raw_data'!R25),"Check"),"Check") -> 149000 | T22: =IFERROR(IF(VALUE('01_raw_data'!S25)>0, VALUE('01_raw_data'!S25), "Check"), "Check") -> 14900 | U22: =IFERROR(VLOOKUP(UPPER(TRIM('01_raw_data'!T25)),'07_performance_master'!$A$5:$B$14,2,FALSE),"Check") -> 4 | V22: =IFERROR(IF(VALUE('01_raw_data'!U25)>0,VALUE('01_raw_data'!U25),"Check"),"Check") -> 6 | W22: =IFERROR(IF(VALUE('01_raw_data'!V25)>=0, VALUE('01_raw_data'!V25), "Check"), "Check") -> 16 | X22: =IFERROR(IF(VALUE('01_raw_data'!W25)>=0, VALUE('01_raw_data'!W25),"Check"), "Check") -> 16 | Y22: =IFERROR(IF(AND(VALUE('01_raw_data'!X25)>=0, VALUE('01_raw_data'!X25)<=100), VALUE('01_raw_data'!X25), "Check"), "Check") -> 65 | Z22: =IFERROR(IF(OR(UPPER(TRIM('01_raw_data'!Y25))="YES", UPPER(TRIM('01_raw_data'!Y25))="PROMOTED"),"Promoted", IF(OR(UPPER(TRIM('01_raw_data'!Y25))="NO",UPPER(TRIM('01_raw_data'!Y25))="NOT PROMOTED"), "Not Promoted", "Check")),"Check") -> Not Promoted | AA22: =IFERROR(PROPER(TRIM('01_raw_data'!Z25)), "") -> Master'S | AB22: =IFERROR(PROPER(TRIM('01_raw_data'!AA25)),"") -> European Job Board | AC22: =IFERROR(IF(UPPER(TRIM('01_raw_data'!AB25))="HYBRID","Hybrid",IF(OR(UPPER(TRIM('01_raw_data'!AB25))="REMOTE",UPPER(TRIM('01_raw_data'!AB25))="WFH",UPPER(TRIM('01_raw_data'!AB25))="WORK FROM HOME"),"Remote",IF(OR(UPPER(TRIM('01_raw_data'!AB25))="ONSITE",UPPER(TRIM('01_raw_data'!AB25))="ON-SITE",UPPER(TRIM('01_raw_data'!AB25))="OFFICE"),"Office"))),"Check") -> Remote | AD22: =IFERROR(VLOOKUP(UPPER(TRIM('01_raw_data'!AC25)),'09_cost_center'!$A$5:$E$19,1,FALSE), "Check") -> EU-CC101 | AE22: =IFERROR(IF(OR(UPPER(TRIM('01_raw_data'!AD25))="CONTRACT", UPPER(TRIM('01_raw_data'!AD25))="CONTRACTOR"), "Contract", IF(OR(PROPER(TRIM('01_raw_data'!AD25))="FTE", UPPER(TRIM('01_raw_data'!AD25))="FULL TIME", UPPER(TRIM('01_raw_data'!AD25))="FULL-TIME"), "Full Time", IF(OR(UPPER(TRIM('01_raw_data'!AD25))="INTERN", UPPER(TRIM('01_raw_data'!AD25))="INTERNSHIP"), "Intern", IF(OR(UPPER(TRIM('01_raw_data'!AD25))="PART TIME", UPPER(TRIM('01_raw_data'!AD25))="PART-TIME"), "Part Time")))), "Check") -> Full Time | AF22: =IFERROR(IF(AND(VALUE('01_raw_data'!AE25)>=0,VALUE('01_raw_data'!AE25)<=100), VALUE('01_raw_data'!AE25), "Check"), "Check") -> 62.2
A23: ="E"&TEXT(VALUE(SUBSTITUTE(UPPER(TRIM('01_raw_data'!A26)),"E","")),"0000") -> E0022 | B23: =IF('01_raw_data'!B26="", "", PROPER(TRIM('01_raw_data'!B26))) -> Marco Wisniewski | C23: =_xlfn.XLOOKUP(PROPER(TRIM('01_raw_data'!C26)),'03_lookups'!$A$4:$A$9,'03_lookups'!$B$4:$B$9,"Needs Review") -> Male | D23: =VALUE('01_raw_data'!D26) -> 28 | E23: =IF(OR('01_raw_data'!E26="", LOWER(TRIM('01_raw_data'!E26))="not available"), "Missing", '01_raw_data'!E26) -> 1998/03/24 | F23: =IF(OR(E23="",LOWER(TRIM(E23))="not available"),"Missing",IF(ISNUMBER(E23),"Valid","Needs Review")) -> Needs Review | G23: =_xlfn.XLOOKUP(UPPER(TRIM('01_raw_data'!F26)),'04_departments'!A26:A81,'04_departments'!C26:C81,"Needs Review") -> Needs Review | H23: =_xlfn.XLOOKUP('01_clean_data'!G23, '04_departments'!$C$5:$C$60,'04_departments'!$D$5:$D$60,"Needs Review") -> Needs Review | I23: =PROPER(TRIM('01_raw_data'!H26)) -> Enterprise Account Manager | J23: =IFERROR(UPPER('01_raw_data'!I26), "") -> L4 | K23: =IFERROR(UPPER('01_raw_data'!J26), "") -> M026 | L23: =IFERROR(VLOOKUP(K23,'05_manager_mapping'!$A$5:$B$64,2), "Missing") -> Sergio Rodrigues | M23: =IFERROR(_xlfn.XLOOKUP('01_raw_data'!L26,'06_location_master'!$B$5:$B$60,'06_location_master'!$C$5:$C$60), "Missing Location") -> Wroclaw | N23: =IFERROR(_xlfn.XLOOKUP(M23,'06_location_master'!$C$5:$C$60,'06_location_master'!$D$5:$D$60), "Missing Country") -> Poland | O23: =IFERROR(_xlfn.XLOOKUP(M23,'06_location_master'!$C$5:$C$60,'06_location_master'!$E$5:$E$60), "Missing State") -> Lower Silesian | P23: =IFERROR(--'01_raw_data'!O26,"Missing Date") -> 44776 | Q23: =IF(TRIM('01_raw_data'!P26)="","", IFERROR('01_raw_data'!P26, "check")) | R23: =IFERROR(IF(OR(UPPER(TRIM('01_raw_data'!Q26))="A",UPPER(TRIM('01_raw_data'!Q26)="ACTVE"),UPPER(TRIM('01_raw_data'!Q26))="ACTIVE"), "Active", IF(OR(UPPER(TRIM('01_raw_data'!Q26)="INACTIVE"),UPPER(TRIM('01_raw_data'!Q26))="INACTVE"),"Inactive",IF(OR(UPPER(TRIM('01_raw_data'!Q26))="EXITED"), "Exited", IF(OR(UPPER(TRIM('01_raw_data'!Q26))="TERMINATED"), "Terminated", IF(OR(UPPER(TRIM('01_raw_data'!Q26))="LEFT"),"Left",IF(OR(UPPER(TRIM('01_raw_data'!Q26))="RESIGNED"),"Resigned")))))),"Check") -> Active | S23: =IFERROR(IF(VALUE('01_raw_data'!R26)>0,VALUE('01_raw_data'!R26),"Check"),"Check") -> 68000 | T23: =IFERROR(IF(VALUE('01_raw_data'!S26)>0, VALUE('01_raw_data'!S26), "Check"), "Check") -> 9500 | U23: =IFERROR(VLOOKUP(UPPER(TRIM('01_raw_data'!T26)),'07_performance_master'!$A$5:$B$14,2,FALSE),"Check") -> 5 | V23: =IFERROR(IF(VALUE('01_raw_data'!U26)>0,VALUE('01_raw_data'!U26),"Check"),"Check") -> 12 | W23: =IFERROR(IF(VALUE('01_raw_data'!V26)>=0, VALUE('01_raw_data'!V26), "Check"), "Check") -> 19 | X23: =IFERROR(IF(VALUE('01_raw_data'!W26)>=0, VALUE('01_raw_data'!W26),"Check"), "Check") -> 25 | Y23: =IFERROR(IF(AND(VALUE('01_raw_data'!X26)>=0, VALUE('01_raw_data'!X26)<=100), VALUE('01_raw_data'!X26), "Check"), "Check") -> 72 | Z23: =IFERROR(IF(OR(UPPER(TRIM('01_raw_data'!Y26))="YES", UPPER(TRIM('01_raw_data'!Y26))="PROMOTED"),"Promoted", IF(OR(UPPER(TRIM('01_raw_data'!Y26))="NO",UPPER(TRIM('01_raw_data'!Y26))="NOT PROMOTED"), "Not Promoted", "Check")),"Check") -> Not Promoted | AA23: =IFERROR(PROPER(TRIM('01_raw_data'!Z26)), "") -> Bachelor'S | AB23: =IFERROR(PROPER(TRIM('01_raw_data'!AA26)),"") -> University Hiring | AC23: =IFERROR(IF(UPPER(TRIM('01_raw_data'!AB26))="HYBRID","Hybrid",IF(OR(UPPER(TRIM('01_raw_data'!AB26))="REMOTE",UPPER(TRIM('01_raw_data'!AB26))="WFH",UPPER(TRIM('01_raw_data'!AB26))="WORK FROM HOME"),"Remote",IF(OR(UPPER(TRIM('01_raw_data'!AB26))="ONSITE",UPPER(TRIM('01_raw_data'!AB26))="ON-SITE",UPPER(TRIM('01_raw_data'!AB26))="OFFICE"),"Office"))),"Check") -> Hybrid | AD23: =IFERROR(VLOOKUP(UPPER(TRIM('01_raw_data'!AC26)),'09_cost_center'!$A$5:$E$19,1,FALSE), "Check") -> EU-CC201 | AE23: =IFERROR(IF(OR(UPPER(TRIM('01_raw_data'!AD26))="CONTRACT", UPPER(TRIM('01_raw_data'!AD26))="CONTRACTOR"), "Contract", IF(OR(PROPER(TRIM('01_raw_data'!AD26))="FTE", UPPER(TRIM('01_raw_data'!AD26))="FULL TIME", UPPER(TRIM('01_raw_data'!AD26))="FULL-TIME"), "Full Time", IF(OR(UPPER(TRIM('01_raw_data'!AD26))="INTERN", UPPER(TRIM('01_raw_data'!AD26))="INTERNSHIP"), "Intern", IF(OR(UPPER(TRIM('01_raw_data'!AD26))="PART TIME", UPPER(TRIM('01_raw_data'!AD26))="PART-TIME"), "Part Time")))), "Check") -> Full Time | AF23: =IFERROR(IF(AND(VALUE('01_raw_data'!AE26)>=0,VALUE('01_raw_data'!AE26)<=100), VALUE('01_raw_data'!AE26), "Check"), "Check") -> 73.2
A24: ="E"&TEXT(VALUE(SUBSTITUTE(UPPER(TRIM('01_raw_data'!A27)),"E","")),"0000") -> E0023 | B24: =IF('01_raw_data'!B27="", "", PROPER(TRIM('01_raw_data'!B27))) -> Manuel Murphy | C24: =_xlfn.XLOOKUP(PROPER(TRIM('01_raw_data'!C27)),'03_lookups'!$A$4:$A$9,'03_lookups'!$B$4:$B$9,"Needs Review") -> Male | D24: =VALUE('01_raw_data'!D27) -> 25 | E24: =IF(OR('01_raw_data'!E27="", LOWER(TRIM('01_raw_data'!E27))="not available"), "Missing", '01_raw_data'!E27) -> 36952 | F24: =IF(OR(E24="",LOWER(TRIM(E24))="not available"),"Missing",IF(ISNUMBER(E24),"Valid","Needs Review")) -> Valid | G24: =_xlfn.XLOOKUP(UPPER(TRIM('01_raw_data'!F27)),'04_departments'!A27:A82,'04_departments'!C27:C82,"Needs Review") -> Needs Review | H24: =_xlfn.XLOOKUP('01_clean_data'!G24, '04_departments'!$C$5:$C$60,'04_departments'!$D$5:$D$60,"Needs Review") -> Needs Review | I24: =PROPER(TRIM('01_raw_data'!H27)) -> Analytics Engineer | J24: =IFERROR(UPPER('01_raw_data'!I27), "") -> L2 | K24: =IFERROR(UPPER('01_raw_data'!J27), "") -> M058 | L24: =IFERROR(VLOOKUP(K24,'05_manager_mapping'!$A$5:$B$64,2), "Missing") -> Lukas Esposito | M24: =IFERROR(_xlfn.XLOOKUP('01_raw_data'!L27,'06_location_master'!$B$5:$B$60,'06_location_master'!$C$5:$C$60), "Missing Location") -> Missing Location | N24: =IFERROR(_xlfn.XLOOKUP(M24,'06_location_master'!$C$5:$C$60,'06_location_master'!$D$5:$D$60), "Missing Country") -> Missing Country | O24: =IFERROR(_xlfn.XLOOKUP(M24,'06_location_master'!$C$5:$C$60,'06_location_master'!$E$5:$E$60), "Missing State") -> Missing State | P24: =IFERROR(--'01_raw_data'!O27,"Missing Date") -> 44582 | Q24: =IF(TRIM('01_raw_data'!P27)="","", IFERROR('01_raw_data'!P27, "check")) | R24: =IFERROR(IF(OR(UPPER(TRIM('01_raw_data'!Q27))="A",UPPER(TRIM('01_raw_data'!Q27)="ACTVE"),UPPER(TRIM('01_raw_data'!Q27))="ACTIVE"), "Active", IF(OR(UPPER(TRIM('01_raw_data'!Q27)="INACTIVE"),UPPER(TRIM('01_raw_data'!Q27))="INACTVE"),"Inactive",IF(OR(UPPER(TRIM('01_raw_data'!Q27))="EXITED"), "Exited", IF(OR(UPPER(TRIM('01_raw_data'!Q27))="TERMINATED"), "Terminated", IF(OR(UPPER(TRIM('01_raw_data'!Q27))="LEFT"),"Left",IF(OR(UPPER(TRIM('01_raw_data'!Q27))="RESIGNED"),"Resigned")))))),"Check") -> Active | S24: =IFERROR(IF(VALUE('01_raw_data'!R27)>0,VALUE('01_raw_data'!R27),"Check"),"Check") -> 52000 | T24: =IFERROR(IF(VALUE('01_raw_data'!S27)>0, VALUE('01_raw_data'!S27), "Check"), "Check") -> Check | U24: =IFERROR(VLOOKUP(UPPER(TRIM('01_raw_data'!T27)),'07_performance_master'!$A$5:$B$14,2,FALSE),"Check") -> 2 | V24: =IFERROR(IF(VALUE('01_raw_data'!U27)>0,VALUE('01_raw_data'!U27),"Check"),"Check") -> 9 | W24: =IFERROR(IF(VALUE('01_raw_data'!V27)>=0, VALUE('01_raw_data'!V27), "Check"), "Check") -> 12 | X24: =IFERROR(IF(VALUE('01_raw_data'!W27)>=0, VALUE('01_raw_data'!W27),"Check"), "Check") -> 35 | Y24: =IFERROR(IF(AND(VALUE('01_raw_data'!X27)>=0, VALUE('01_raw_data'!X27)<=100), VALUE('01_raw_data'!X27), "Check"), "Check") -> 75 | Z24: =IFERROR(IF(OR(UPPER(TRIM('01_raw_data'!Y27))="YES", UPPER(TRIM('01_raw_data'!Y27))="PROMOTED"),"Promoted", IF(OR(UPPER(TRIM('01_raw_data'!Y27))="NO",UPPER(TRIM('01_raw_data'!Y27))="NOT PROMOTED"), "Not Promoted", "Check")),"Check") -> Not Promoted | AA24: =IFERROR(PROPER(TRIM('01_raw_data'!Z27)), "") -> Mba | AB24: =IFERROR(PROPER(TRIM('01_raw_data'!AA27)),"") -> European Job Board | AC24: =IFERROR(IF(UPPER(TRIM('01_raw_data'!AB27))="HYBRID","Hybrid",IF(OR(UPPER(TRIM('01_raw_data'!AB27))="REMOTE",UPPER(TRIM('01_raw_data'!AB27))="WFH",UPPER(TRIM('01_raw_data'!AB27))="WORK FROM HOME"),"Remote",IF(OR(UPPER(TRIM('01_raw_data'!AB27))="ONSITE",UPPER(TRIM('01_raw_data'!AB27))="ON-SITE",UPPER(TRIM('01_raw_data'!AB27))="OFFICE"),"Office"))),"Check") -> Remote | AD24: =IFERROR(VLOOKUP(UPPER(TRIM('01_raw_data'!AC27)),'09_cost_center'!$A$5:$E$19,1,FALSE), "Check") -> EU-CC103 | AE24: =IFERROR(IF(OR(UPPER(TRIM('01_raw_data'!AD27))="CONTRACT", UPPER(TRIM('01_raw_data'!AD27))="CONTRACTOR"), "Contract", IF(OR(PROPER(TRIM('01_raw_data'!AD27))="FTE", UPPER(TRIM('01_raw_data'!AD27))="FULL TIME", UPPER(TRIM('01_raw_data'!AD27))="FULL-TIME"), "Full Time", IF(OR(UPPER(TRIM('01_raw_data'!AD27))="INTERN", UPPER(TRIM('01_raw_data'!AD27))="INTERNSHIP"), "Intern", IF(OR(UPPER(TRIM('01_raw_data'!AD27))="PART TIME", UPPER(TRIM('01_raw_data'!AD27))="PART-TIME"), "Part Time")))), "Check") -> Full Time | AF24: =IFERROR(IF(AND(VALUE('01_raw_data'!AE27)>=0,VALUE('01_raw_data'!AE27)<=100), VALUE('01_raw_data'!AE27), "Check"), "Check") -> 46.5
A25: ="E"&TEXT(VALUE(SUBSTITUTE(UPPER(TRIM('01_raw_data'!A28)),"E","")),"0000") -> E0024 | B25: =IF('01_raw_data'!B28="", "", PROPER(TRIM('01_raw_data'!B28))) -> Laura Fernandez | C25: =_xlfn.XLOOKUP(PROPER(TRIM('01_raw_data'!C28)),'03_lookups'!$A$4:$A$9,'03_lookups'!$B$4:$B$9,"Needs Review") -> Female | D25: =VALUE('01_raw_data'!D28) -> 40 | E25: =IF(OR('01_raw_data'!E28="", LOWER(TRIM('01_raw_data'!E28))="not available"), "Missing", '01_raw_data'!E28) -> 31317 | F25: =IF(OR(E25="",LOWER(TRIM(E25))="not available"),"Missing",IF(ISNUMBER(E25),"Valid","Needs Review")) -> Valid | G25: =_xlfn.XLOOKUP(UPPER(TRIM('01_raw_data'!F28)),'04_departments'!A28:A83,'04_departments'!C28:C83,"Needs Review") -> Human Resources | H25: =_xlfn.XLOOKUP('01_clean_data'!G25, '04_departments'!$C$5:$C$60,'04_departments'!$D$5:$D$60,"Needs Review") -> Corporate Services | I25: =PROPER(TRIM('01_raw_data'!H28)) -> People Operations Analyst | J25: =IFERROR(UPPER('01_raw_data'!I28), "") -> L3 | K25: =IFERROR(UPPER('01_raw_data'!J28), "") -> M060 | L25: =IFERROR(VLOOKUP(K25,'05_manager_mapping'!$A$5:$B$64,2), "Missing") -> Matteo Wagner | M25: =IFERROR(_xlfn.XLOOKUP('01_raw_data'!L28,'06_location_master'!$B$5:$B$60,'06_location_master'!$C$5:$C$60), "Missing Location") -> Missing Location | N25: =IFERROR(_xlfn.XLOOKUP(M25,'06_location_master'!$C$5:$C$60,'06_location_master'!$D$5:$D$60), "Missing Country") -> Missing Country | O25: =IFERROR(_xlfn.XLOOKUP(M25,'06_location_master'!$C$5:$C$60,'06_location_master'!$E$5:$E$60), "Missing State") -> Missing State | P25: =IFERROR(--'01_raw_data'!O28,"Missing Date") -> 44749 | Q25: =IF(TRIM('01_raw_data'!P28)="","", IFERROR('01_raw_data'!P28, "check")) | R25: =IFERROR(IF(OR(UPPER(TRIM('01_raw_data'!Q28))="A",UPPER(TRIM('01_raw_data'!Q28)="ACTVE"),UPPER(TRIM('01_raw_data'!Q28))="ACTIVE"), "Active", IF(OR(UPPER(TRIM('01_raw_data'!Q28)="INACTIVE"),UPPER(TRIM('01_raw_data'!Q28))="INACTVE"),"Inactive",IF(OR(UPPER(TRIM('01_raw_data'!Q28))="EXITED"), "Exited", IF(OR(UPPER(TRIM('01_raw_data'!Q28))="TERMINATED"), "Terminated", IF(OR(UPPER(TRIM('01_raw_data'!Q28))="LEFT"),"Left",IF(OR(UPPER(TRIM('01_raw_data'!Q28))="RESIGNED"),"Resigned")))))),"Check") -> Active | S25: =IFERROR(IF(VALUE('01_raw_data'!R28)>0,VALUE('01_raw_data'!R28),"Check"),"Check") -> 80000 | T25: =IFERROR(IF(VALUE('01_raw_data'!S28)>0, VALUE('01_raw_data'!S28), "Check"), "Check") -> 7200 | U25: =IFERROR(VLOOKUP(UPPER(TRIM('01_raw_data'!T28)),'07_performance_master'!$A$5:$B$14,2,FALSE),"Check") -> 4 | V25: =IFERROR(IF(VALUE('01_raw_data'!U28)>0,VALUE('01_raw_data'!U28),"Check"),"Check") -> 30 | W25: =IFERROR(IF(VALUE('01_raw_data'!V28)>=0, VALUE('01_raw_data'!V28), "Check"), "Check") -> 10 | X25: =IFERROR(IF(VALUE('01_raw_data'!W28)>=0, VALUE('01_raw_data'!W28),"Check"), "Check") -> 14 | Y25: =IFERROR(IF(AND(VALUE('01_raw_data'!X28)>=0, VALUE('01_raw_data'!X28)<=100), VALUE('01_raw_data'!X28), "Check"), "Check") -> 57 | Z25: =IFERROR(IF(OR(UPPER(TRIM('01_raw_data'!Y28))="YES", UPPER(TRIM('01_raw_data'!Y28))="PROMOTED"),"Promoted", IF(OR(UPPER(TRIM('01_raw_data'!Y28))="NO",UPPER(TRIM('01_raw_data'!Y28))="NOT PROMOTED"), "Not Promoted", "Check")),"Check") -> Not Promoted | AA25: =IFERROR(PROPER(TRIM('01_raw_data'!Z28)), "") -> Bachelor'S | AB25: =IFERROR(PROPER(TRIM('01_raw_data'!AA28)),"") -> Linkedin | AC25: =IFERROR(IF(UPPER(TRIM('01_raw_data'!AB28))="HYBRID","Hybrid",IF(OR(UPPER(TRIM('01_raw_data'!AB28))="REMOTE",UPPER(TRIM('01_raw_data'!AB28))="WFH",UPPER(TRIM('01_raw_data'!AB28))="WORK FROM HOME"),"Remote",IF(OR(UPPER(TRIM('01_raw_data'!AB28))="ONSITE",UPPER(TRIM('01_raw_data'!AB28))="ON-SITE",UPPER(TRIM('01_raw_data'!AB28))="OFFICE"),"Office"))),"Check") -> Hybrid | AD25: =IFERROR(VLOOKUP(UPPER(TRIM('01_raw_data'!AC28)),'09_cost_center'!$A$5:$E$19,1,FALSE), "Check") -> EU-CC302 | AE25: =IFERROR(IF(OR(UPPER(TRIM('01_raw_data'!AD28))="CONTRACT", UPPER(TRIM('01_raw_data'!AD28))="CONTRACTOR"), "Contract", IF(OR(PROPER(TRIM('01_raw_data'!AD28))="FTE", UPPER(TRIM('01_raw_data'!AD28))="FULL TIME", UPPER(TRIM('01_raw_data'!AD28))="FULL-TIME"), "Full Time", IF(OR(UPPER(TRIM('01_raw_data'!AD28))="INTERN", UPPER(TRIM('01_raw_data'!AD28))="INTERNSHIP"), "Intern", IF(OR(UPPER(TRIM('01_raw_data'!AD28))="PART TIME", UPPER(TRIM('01_raw_data'!AD28))="PART-TIME"), "Part Time")))), "Check") -> Full Time | AF25: =IFERROR(IF(AND(VALUE('01_raw_data'!AE28)>=0,VALUE('01_raw_data'!AE28)<=100), VALUE('01_raw_data'!AE28), "Check"), "Check") -> 66.5
... A1001: ="E"&TEXT(VALUE(SUBSTITUTE(UPPER(TRIM('01_raw_data'!A1004)),"E","")),"0000") -> E1000 | B1001: =IF('01_raw_data'!B1004="", "", PROPER(TRIM('01_raw_data'!B1004))) -> Anna Thomas | C1001: =_xlfn.XLOOKUP(PROPER(TRIM('01_raw_data'!C1004)),'03_lookups'!$A$4:$A$9,'03_lookups'!$B$4:$B$9,"Needs Review") -> Male | D1001: =VALUE('01_raw_data'!D1004) -> 31 | E1001: =IF(OR('01_raw_data'!E1004="", LOWER(TRIM('01_raw_data'!E1004))="not available"), "Missing", '01_raw_data'!E1004) -> 34719 | F1001: =IF(OR(E1001="",LOWER(TRIM(E1001))="not available"),"Missing",IF(ISNUMBER(E1001),"Valid","Needs Review")) -> Valid | G1001: =_xlfn.XLOOKUP(UPPER(TRIM('01_raw_data'!F1004)),'04_departments'!A1004:A1059,'04_departments'!C1004:C1059,"Needs Review") -> Needs Review | H1001: =_xlfn.XLOOKUP('01_clean_data'!G1001, '04_departments'!$C$5:$C$60,'04_departments'!$D$5:$D$60,"Needs Review") -> Needs Review | I1001: =PROPER(TRIM('01_raw_data'!H1004)) -> Backend Engineer | J1001: =IFERROR(UPPER('01_raw_data'!I1004), "") -> L2 | K1001: =IFERROR(UPPER('01_raw_data'!J1004), "") -> M057 | L1001: =IFERROR(VLOOKUP(K1001,'05_manager_mapping'!$A$5:$B$64,2), "Missing") -> Emma Karlsson | M1001: =IFERROR(_xlfn.XLOOKUP('01_raw_data'!L1004,'06_location_master'!$B$5:$B$60,'06_location_master'!$C$5:$C$60), "Missing Location") -> Dublin | N1001: =IFERROR(_xlfn.XLOOKUP(M1001,'06_location_master'!$C$5:$C$60,'06_location_master'!$D$5:$D$60), "Missing Country") -> Ireland | O1001: =IFERROR(_xlfn.XLOOKUP(M1001,'06_location_master'!$C$5:$C$60,'06_location_master'!$E$5:$E$60), "Missing State") -> Leinster | P1001: =IFERROR(--'01_raw_data'!O1004,"Missing Date") -> 43392 | Q1001: =IF(TRIM('01_raw_data'!P1004)="","", IFERROR('01_raw_data'!P1004, "check")) | R1001: =IFERROR(IF(OR(UPPER(TRIM('01_raw_data'!Q1004))="A",UPPER(TRIM('01_raw_data'!Q1004)="ACTVE"),UPPER(TRIM('01_raw_data'!Q1004))="ACTIVE"), "Active", IF(OR(UPPER(TRIM('01_raw_data'!Q1004)="INACTIVE"),UPPER(TRIM('01_raw_data'!Q1004))="INACTVE"),"Inactive",IF(OR(UPPER(TRIM('01_raw_data'!Q1004))="EXITED"), "Exited", IF(OR(UPPER(TRIM('01_raw_data'!Q1004))="TERMINATED"), "Terminated", IF(OR(UPPER(TRIM('01_raw_data'!Q1004))="LEFT"),"Left",IF(OR(UPPER(TRIM('01_raw_data'!Q1004))="RESIGNED"),"Resigned")))))),"Check") -> Active | S1001: =IFERROR(IF(VALUE('01_raw_data'!R1004)>0,VALUE('01_raw_data'!R1004),"Check"),"Check") -> 51000 | T1001: =IFERROR(IF(VALUE('01_raw_data'!S1004)>0, VALUE('01_raw_data'!S1004), "Check"), "Check") -> 2600 | U1001: =IFERROR(VLOOKUP(UPPER(TRIM('01_raw_data'!T1004)),'07_performance_master'!$A$5:$B$14,2,FALSE),"Check") -> 3 | V1001: =IFERROR(IF(VALUE('01_raw_data'!U1004)>0,VALUE('01_raw_data'!U1004),"Check"),"Check") -> Check | W1001: =IFERROR(IF(VALUE('01_raw_data'!V1004)>=0, VALUE('01_raw_data'!V1004), "Check"), "Check") -> 17 | X1001: =IFERROR(IF(VALUE('01_raw_data'!W1004)>=0, VALUE('01_raw_data'!W1004),"Check"), "Check") -> 10 | Y1001: =IFERROR(IF(AND(VALUE('01_raw_data'!X1004)>=0, VALUE('01_raw_data'!X1004)<=100), VALUE('01_raw_data'!X1004), "Check"), "Check") -> 80 | Z1001: =IFERROR(IF(OR(UPPER(TRIM('01_raw_data'!Y1004))="YES", UPPER(TRIM('01_raw_data'!Y1004))="PROMOTED"),"Promoted", IF(OR(UPPER(TRIM('01_raw_data'!Y1004))="NO",UPPER(TRIM('01_raw_data'!Y1004))="NOT PROMOTED"), "Not Promoted", "Check")),"Check") -> Not Promoted | AA1001: =IFERROR(PROPER(TRIM('01_raw_data'!Z1004)), "") -> Diploma | AB1001: =IFERROR(PROPER(TRIM('01_raw_data'!AA1004)),"") -> Agency | AC1001: =IFERROR(IF(UPPER(TRIM('01_raw_data'!AB1004))="HYBRID","Hybrid",IF(OR(UPPER(TRIM('01_raw_data'!AB1004))="REMOTE",UPPER(TRIM('01_raw_data'!AB1004))="WFH",UPPER(TRIM('01_raw_data'!AB1004))="WORK FROM HOME"),"Remote",IF(OR(UPPER(TRIM('01_raw_data'!AB1004))="ONSITE",UPPER(TRIM('01_raw_data'!AB1004))="ON-SITE",UPPER(TRIM('01_raw_data'!AB1004))="OFFICE"),"Office"))),"Check") -> Remote | AD1001: =IFERROR(VLOOKUP(UPPER(TRIM('01_raw_data'!AC1004)),'09_cost_center'!$A$5:$E$19,1,FALSE), "Check") -> EU-CC101 | AE1001: =IFERROR(IF(OR(UPPER(TRIM('01_raw_data'!AD1004))="CONTRACT", UPPER(TRIM('01_raw_data'!AD1004))="CONTRACTOR"), "Contract", IF(OR(PROPER(TRIM('01_raw_data'!AD1004))="FTE", UPPER(TRIM('01_raw_data'!AD1004))="FULL TIME", UPPER(TRIM('01_raw_data'!AD1004))="FULL-TIME"), "Full Time", IF(OR(UPPER(TRIM('01_raw_data'!AD1004))="INTERN", UPPER(TRIM('01_raw_data'!AD1004))="INTERNSHIP"), "Intern", IF(OR(UPPER(TRIM('01_raw_data'!AD1004))="PART TIME", UPPER(TRIM('01_raw_data'!AD1004))="PART-TIME"), "Part Time")))), "Check") -> Full Time | AF1001: =IFERROR(IF(AND(VALUE('01_raw_data'!AE1004)>=0,VALUE('01_raw_data'!AE1004)<=100), VALUE('01_raw_data'!AE1004), "Check"), "Check") -> 70

Sheet 03_lookups
A3: Raw Gender | B3: Standard Gender
A4: M | B4: Male
A5: Male | B5: Male
A6: F | B6: Female
A7: Female | B7: Female
A8: NB | B8: Non-Binary
A9: Non-Binary | B9: Non-Binary

Sheet 04_departments
A1: 03 - Department Master
A2: Standardizes European department names and maps EMEA business units
A4: Department Key | B4: Raw/Dirty Department Value | C4: Standard Department | D4: Business Unit | E4: Department Head | F4: Active Flag
A5: ENGINEERING | B5: ENGINEERING | C5: Engineering | D5: Product & Technology | E5: Elena Rossi | F5: Y
A6: ENGG | B6: ENGG | C6: Engineering | D6: Product & Technology | E6: Elena Rossi | F6: Y
A7: ENGINERING | B7: ENGINERING | C7: Engineering | D7: Product & Technology | E7: Elena Rossi | F7: Y
A8: TECH | B8: TECH | C8: Engineering | D8: Product & Technology | E8: Elena Rossi | F8: Y
A9: SOFTWARE ENGG | B9: Software Engg | C9: Engineering | D9: Product & Technology | E9: Elena Rossi | F9: Y
A10: PRODUCT | B10: PRODUCT | C10: Product | D10: Product & Technology | E10: Thomas Muller | F10: Y
A11: PROD | B11: Prod | C11: Product | D11: Product & Technology | E11: Thomas Muller | F11: Y
A12: PRODUCT MGMT | B12: Product Mgmt | C12: Product | D12: Product & Technology | E12: Thomas Muller | F12: Y
A13: PMO PRODUCT | B13: PMO Product | C13: Product | D13: Product & Technology | E13: Thomas Muller | F13: Y
A14: DATA & ANALYTICS | B14: DATA & ANALYTICS | C14: Data & Analytics | D14: Data & AI | E14: Sofia Garcia | F14: Y
A15: DATA ANALYTICS | B15: Data Analytics | C15: Data & Analytics | D15: Data & AI | E15: Sofia Garcia | F15: Y
... A60: SECOPS | B60: SecOps | C60: Security | D60: Risk & Compliance | E60: Felix Schneider | F60: Y

Sheet 05_manager_mapping
A1: 08 - Manager Mapping Table
A2: Maps European Manager ID to manager name, department, level and location
A4: Manager ID | B4: Manager Name | C4: Department | D4: Job Level | E4: Location | F4: Status
A5: M001 | B5: Milan Leroy | C5: Engineering | D5: L6 | E5: London | F5: Active
A6: M002 | B6: Finn Larsson | C6: Product | D6: L6 | E6: Manchester | F6: Active
A7: M003 | B7: Sarah Lopez | C7: Data & Analytics | D7: L6 | E7: London | F7: Active
A8: M004 | B8: Giovanni Leroy | C8: Sales | D8: L5 | E8: Eindhoven | F8: Active
A9: M005 | B9: Lucas Doyle | C9: Customer Success | D9: L5 | E9: Munich | F9: Active
A10: M006 | B10: Aleksander Fischer | C10: Marketing | D10: L6 | E10: Munich | F10: Active
A11: M007 | B11: Astrid Bakker | C11: Finance | D11: L5 | E11: Manchester | F11: Active
A12: M008 | B12: Mia Szymanski | C12: Human Resources | D12: L5 | E12: Gothenburg | F12: Active
A13: M009 | B13: Maja Nilsson | C13: IT | D13: L5 | E13: Munich | F13: Active
A14: M010 | B14: Lotte Muller | C14: Operations | D14: L6 | E14: London | F14: Active
A15: M011 | B15: Julia Marino | C15: Legal | D15: L5 | E15: Rome | F15: Active
... A64: M060 | B64: Matteo Wagner | C64: Human Resources | D64: L6 | E64: Hamburg | F64: Active

Sheet 06_location_master
A1: 04 - Location Master
A2: Standardizes European office locations and derives country/region
A4: Location Key | B4: Raw/Dirty Location Value | C4: Standard Location | D4: Country | E4: State | F4: Region
A5: LONDON | B5: LONDON | C5: London | D5: United Kingdom | E5: England | F5: Northern Europe
A6: LONDN | B6: Londn | C6: London | D6: United Kingdom | E6: England | F6: Northern Europe
A7: MANCHESTER | B7: MANCHESTER | C7: Manchester | D7: United Kingdom | E7: England | F7: Northern Europe
A8: MANCHSTR | B8: Manchstr | C8: Manchester | D8: United Kingdom | E8: England | F8: Northern Europe
A9: EDINBURGH | B9: EDINBURGH | C9: Edinburgh | D9: United Kingdom | E9: Scotland | F9: Northern Europe
A10: EDINBURG | B10: Edinburg | C10: Edinburgh | D10: United Kingdom | E10: Scotland | F10: Northern Europe
A11: DUBLIN | B11: DUBLIN | C11: Dublin | D11: Ireland | E11: Leinster | F11: Northern Europe
A12: DUBLN | B12: Dubln | C12: Dublin | D12: Ireland | E12: Leinster | F12: Northern Europe
A13: CORK | B13: CORK | C13: Cork | D13: Ireland | E13: Munster | F13: Northern Europe
A14: CORK | B14: Cork | C14: Cork | D14: Ireland | E14: Munster | F14: Northern Europe
A15: BERLIN | B15: BERLIN | C15: Berlin | D15: Germany | E15: Berlin | F15: Central Europe
... A60: LISBOA | B60: Lisboa | C60: Lisbon | D60: Portugal | E60: Lisbon District | F60: Southern Europe

Sheet 07_performance_master
A1: 06 - Performance Rating Master
A2: Normalizes rating values and explains performance categories
A4: Rating Key | B4: Standard Rating | C4: Rating Label | D4: Performance Category | E4: Business Meaning
A5: 1 | B5: 1 | C5: Unsatisfactory | D5: Low Performer | E5: Immediate performance intervention required
A6: 2 | B6: 2 | C6: Needs Improvement | D6: Low Performer | E6: Coaching plan required
A7: 3 | B7: 3 | C7: Meets Expectations | D7: Core Performer | E7: Reliable contributor
A8: 4 | B8: 4 | C8: Exceeds Expectations | D8: High Performer | E8: Strong performer and promotion candidate
A9: 5 | B9: 5 | C9: Outstanding | D9: High Performer | E9: Critical talent / leadership pipeline
A10: ONE | B10: 1 | C10: Unsatisfactory | D10: Low Performer | E10: Text value mapping
A11: TWO | B11: 2 | C11: Needs Improvement | D11: Low Performer | E11: Text value mapping
A12: THREE | B12: 3 | C12: Meets Expectations | D12: Core Performer | E12: Text value mapping
A13: FOUR | B13: 4 | C13: Exceeds Expectations | D13: High Performer | E13: Text value mapping
A14: FIVE | B14: 5 | C14: Outstanding | D14: High Performer | E14: Text value mapping

Sheet 09_cost_center
A1: 09 - Cost Center Table
A2: Maps European departments to EMEA cost centers and budget owners
A4: Cost Center | B4: Department | C4: Business Unit | D4: Budget Owner | E4: Annual People Budget
A5: EU-CC101 | B5: Engineering | C5: Product & Technology | D5: Elena Rossi | E5: 17100000
A6: EU-CC102 | B6: Product | C6: Product & Technology | D6: Thomas Muller | E6: 7200000
A7: EU-CC103 | B7: Data & Analytics | C7: Data & AI | D7: Sofia Garcia | E7: 6300000
A8: EU-CC201 | B8: Sales | C8: Revenue | D8: Oliver Smith | E8: 13050000
A9: EU-CC202 | B9: Customer Success | C9: Revenue | D9: Camille Dubois | E9: 10800000
A10: EU-CC203 | B10: Marketing | C10: Revenue | D10: Eva Jansen | E10: 6300000
A11: EU-CC301 | B11: Finance | C11: Corporate Services | D11: Luca Bianchi | E11: 5400000
A12: EU-CC302 | B12: Human Resources | C12: Corporate Services | D12: Amelia Wilson | E12: 4950000
A13: EU-CC104 | B13: IT | C13: Product & Technology | D13: Jakub Kowalski | E13: 6300000
A14: EU-CC401 | B14: Operations | C14: Operations | D14: Erik Andersson | E14: 8550000
A15: EU-CC501 | B15: Legal | C15: Risk & Compliance | D15: Claire Martin | E15: 2250000
A16: EU-CC502 | B16: Compliance | C16: Risk & Compliance | D16: Niels De Vries | E16: 3150000
... A19: EU-CC303 | B19: Corporate Strategy | C19: Corporate Services | D19: Alice Murphy | E19: 2700000

Sheet 10_pivot_source
A1: 14 - Pivot Source
A2: Clean, analysis-ready European HR dataset for PivotTables and Pivot Charts
A4: Employee ID | B4: Employee Name | C4: Gender | D4: Age | E4: Date of Birth | F4: Department | G4: Business Unit | H4: Designation | I4: Job Level | J4: Manager ID | K4: Manager Name | L4: Location | M4: Country | N4: State | O4: Joining Date | P4: Exit Date | Q4: Employment Status | R4: Salary | S4: Bonus | T4: Performance Rating | U4: Training Hours | V4: Leave Taken | W4: Overtime Hours | X4: Employee Engagement Score | Y4: Promotion Status | Z4: Education Level | AA4: Recruitment Source | AB4: Work Mode | AC4: Cost Center | AD4: Employee Type | AE4: Productivity Score | AF4: Employee Tenure | AG4: Age Band | AH4: Salary Band | AI4: Performance Category | AJ4: Attrition Flag | AK4: Training Category | AL4: Promotion Eligibility | AM4: Department Productivity Score | AN4: Data Quality Flag
A5: E0001 | B5: Tess Martin | C5: Male | D5: 56 | E5: 25373 | F5: Data & Analytics | G5: Data & AI | H5: Senior Data Analyst | I5: L6 | J5: M003 | K5: Sarah Lopez | L5: Valencia | M5: Spain | N5: Valencian Community | O5: 44869 | Q5: Active | R5: 134000 | S5: 4000 | T5: 2 | U5: 35 | V5: 20 | W5: 10 | X5: 74 | Y5: Not Promoted | Z5: Master's | AA5: University Hiring | AB5: Hybrid | AC5: EU-CC103 | AD5: Contract | AE5: 57.6 | AF5: 3.6 | AG5: 55+ | AH5: €120k-€170k | AI5: Low Performer | AJ5: 0 | AK5: High Training | AL5: Not Eligible | AM5: 57.6
A6: E0002 | B6: Miguel Gonzalez | C6: Male | D6: 25 | E6: 37009 | F6: Finance | G6: Corporate Services | H6: Financial Analyst | I6: L4 | J6: M007 | K6: Astrid Bakker | L6: Hamburg | M6: Germany | N6: Hamburg | O6: 43226 | Q6: Active | R6: 107000 | S6: 5400 | T6: 3 | U6: 28 | V6: 15 | W6: 26 | X6: 44 | Y6: Not Promoted | Z6: Bachelor's | AA6: Agency | AB6: Hybrid | AC6: EU-CC301 | AD6: Full Time | AE6: 49.4 | AF6: 8.1 | AG6: 25-34 | AH6: €85k-€120k | AI6: Core Performer | AJ6: 0 | AK6: Moderate Training | AL6: Not Eligible | AM6: 49.4
A7: E0003 | B7: Hannah Wilson | C7: Male | D7: 24 | E7: 37238 | F7: Product | G7: Product & Technology | H7: Product Analyst | I7: L2 | J7: M038 | K7: Sophia Moreau | L7: Krakow | M7: Poland | N7: Lesser Poland | O7: 45858 | Q7: Active | R7: 44000 | S7: 2200 | T7: 3 | U7: 35 | V7: 25 | W7: 16 | X7: 74 | Y7: Not Promoted | Z7: Bachelor's | AA7: Agency | AB7: Remote | AC7: EU-CC102 | AD7: Full Time | AE7: 63.6 | AF7: 0.9 | AG7: <25 | AH7: €40k-€60k | AI7: Core Performer | AJ7: 0 | AK7: High Training | AL7: Watchlist | AM7: 63.6 | AN7: Data Issue
A8: E0004 | B8: Bram Visser | C8: Male | D8: 28 | E8: 35765 | F8: Legal | G8: Risk & Compliance | H8: Contracts Analyst | I8: L5 | J8: M011 | K8: Julia Marino | L8: Milan | M8: Italy | N8: Lombardy | O8: 44343 | Q8: Active | R8: 118000 | S8: 1200 | T8: 1 | U8: 27 | V8: 20 | W8: 27 | X8: 26 | Y8: Not Promoted | Z8: Bachelor's | AA8: Company Careers Page | AB8: Hybrid | AC8: EU-CC501 | AD8: Contract | AE8: 24.9 | AF8: 5 | AG8: 25-34 | AH8: €85k-€120k | AI8: Low Performer | AJ8: 0 | AK8: Moderate Training | AL8: Not Eligible | AM8: 24.9
A9: E0005 | B9: Kacper Brown | C9: Male | D9: 38 | E9: 32217 | F9: Marketing | G9: Revenue | H9: Marketing Executive | I9: L6 | J9: M006 | K9: Aleksander Fischer | L9: Madrid | M9: Spain | N9: Community of Madrid | O9: 43996 | Q9: Active | R9: 157000 | S9: 9400 | T9: 3 | U9: 15 | V9: 12 | W9: 11 | X9: 63 | Y9: Not Promoted | Z9: MBA | AA9: University Hiring | AB9: Hybrid | AC9: EU-CC203 | AD9: Full Time | AE9: 57.3 | AF9: 6 | AG9: 35-44 | AH9: €120k-€170k | AI9: Core Performer | AJ9: 0 | AK9: Moderate Training | AL9: Watchlist | AM9: 57.3
A10: E0006 | B10: Kacper Gustafsson | C10: Male | D10: 29 | E10: 35442 | F10: Customer Success | G10: Revenue | H10: Client Success Associate | I10: L3 | J10: M054 | K10: Isla Eriksson | L10: Stockholm | M10: Sweden | N10: Stockholm County | O10: 44665 | Q10: Active | R10: 79000 | S10: 7100 | T10: 4 | U10: 31 | V10: 23 | W10: 0 | X10: 84 | Y10: Not Promoted | Z10: Bachelor's | AA10: Agency | AB10: Hybrid | AC10: EU-CC202 | AD10: Full Time | AE10: 83.2 | AF10: 4.2 | AG10: 25-34 | AH10: €60k-€85k | AI10: High Performer | AJ10: 0 | AK10: High Training | AL10: Eligible | AM10: 83.2
A11: E0007 | B11: Ines Martinez | C11: Male | D11: 32 | E11: 34162 | F11: Engineering | G11: Product & Technology | H11: Engineering Lead | I11: L3 | J11: M048 | K11: Jack Schmidt | L11: Hamburg | M11: Germany | N11: Hamburg | O11: 45404 | Q11: Active | R11: 85000 | S11: 1700 | T11: 2 | U11: 57 | V11: 20 | W11: 0 | X11: 46 | Y11: Not Promoted | Z11: Bachelor's | AA11: University Hiring | AB11: Hybrid | AC11: EU-CC101 | AD11: Full Time | AE11: 54.1 | AF11: 2.1 | AG11: 25-34 | AH11: €85k-€120k | AI11: Low Performer | AJ11: 0 | AK11: High Training | AL11: Not Eligible | AM11: 54.1
A12: E0008 | B12: Alessandro Jansen | C12: Male | D12: 22 | E12: 38098 | F12: Operations | G12: Operations | H12: Workforce Planner | I12: L2 | J12: M010 | K12: Lotte Muller | L12: Eindhoven | M12: Netherlands | N12: North Brabant | O12: 45703 | P12: 46030 | Q12: Exited | R12: 56000 | S12: 7800 | T12: 5 | U12: 48 | V12: 10 | W12: 1 | X12: 57 | Y12: Not Promoted | Z12: Bachelor's | AA12: European Job Board | AB12: Remote | AC12: EU-CC401 | AD12: Full Time | AE12: 84.5 | AF12: 0.9 | AG12: <25 | AH12: €40k-€60k | AI12: High Performer | AJ12: 1 | AK12: High Training | AL12: Not Eligible | AM12: 84.5
A13: E0009 | B13: Javier Ricci | C13: Male | D13: 37 | E13: 32347 | F13: Data & Analytics | G13: Data & AI | H13: Data Scientist | I13: L4 | J13: M020 | K13: Alessandro Lewandowski | L13: Munich | M13: Germany | N13: Bavaria | O13: 42863 | Q13: Active | R13: 109000 | S13: 5400 | T13: 3 | U13: 29 | V13: 18 | W13: 7 | X13: 47 | Y13: Not Promoted | Z13: Diploma | AA13: Company Careers Page | AB13: Hybrid | AC13: EU-CC103 | AD13: Full Time | AE13: 57.2 | AF13: 9.1 | AG13: 35-44 | AH13: €85k-€120k | AI13: Core Performer | AJ13: 0 | AK13: Moderate Training | AL13: Not Eligible | AM13: 57.2
A14: E0010 | B14: Sophia Petit | C14: Female | D14: 46 | E14: 29087 | F14: Security | G14: Risk & Compliance | H14: Security Lead | I14: L1 | J14: M056 | K14: Emily Olsson | L14: London | M14: United Kingdom | N14: England | O14: 44040 | Q14: Active | R14: 49000 | S14: 2400 | T14: 3 | U14: 21 | V14: 2 | W14: 20 | X14: 54 | Y14: Not Promoted | Z14: Bachelor's | AA14: European Job Board | AB14: Office | AC14: EU-CC503 | AD14: Full Time | AE14: 51.1 | AF14: 5.9 | AG14: 45-54 | AH14: €40k-€60k | AI14: Core Performer | AJ14: 0 | AK14: Moderate Training | AL14: Not Eligible | AM14: 51.1 | AN14: Data Issue
A15: E0011 | B15: Francesco Ferreira | C15: Male | D15: 51 | E15: 27494 | F15: Corporate Strategy | G15: Corporate Services | H15: Transformation Lead | I15: L3 | J15: M015 | K15: Lea Ryan | L15: Manchester | M15: United Kingdom | N15: England | O15: 44414 | P15: 45280 | Q15: Exited | R15: 71000 | S15: 3600 | T15: 3 | U15: 18 | V15: 31 | W15: 0 | X15: 68 | Y15: Not Promoted | Z15: Bachelor's | AA15: LinkedIn | AB15: Remote | AC15: EU-CC303 | AD15: Full Time | AE15: 65.3 | AF15: 2.4 | AG15: 45-54 | AH15: €60k-€85k | AI15: Core Performer | AJ15: 1 | AK15: Moderate Training | AL15: Not Eligible | AM15: 65.3 | AN15: Data Issue
A16: E0012 | B16: Emily Fernandes | C16: Female | D16: 24 | E16: 37406 | F16: Security | G16: Risk & Compliance | H16: Security Analyst | I16: L2 | J16: M014 | K16: Elena Szymanski | L16: Berlin | M16: Germany | N16: Berlin | O16: 44246 | Q16: Active | R16: 57000 | S16: 2800 | T16: 3 | U16: 12 | V16: 22 | W16: 25 | X16: 57 | Y16: Not Promoted | Z16: Master's | AA16: Indeed | AB16: Remote | AC16: EU-CC503 | AD16: Full Time | AE16: 50 | AF16: 5.3 | AG16: <25 | AH16: €40k-€60k | AI16: Core Performer | AJ16: 0 | AK16: Moderate Training | AL16: Not Eligible | AM16: 50 | AN16: Data Issue
A17: E0013 | B17: Arthur Mulder | C17: Female | D17: 46 | E17: 29183 | F17: Procurement | G17: Operations | H17: Vendor Manager | I17: L2 | J17: M013 | K17: Ebba Kelly | L17: Stockholm | M17: Sweden | N17: Stockholm County | O17: 44155 | Q17: Active | R17: 66000 | S17: 3300 | T17: 3 | U17: 38 | V17: 17 | W17: 10 | X17: 60 | Y17: Not Promoted | Z17: Master's | AA17: LinkedIn | AB17: Remote | AC17: EU-CC402 | AD17: Contract | AE17: 62.5 | AF17: 5.6 | AG17: 45-54 | AH17: €60k-€85k | AI17: Core Performer | AJ17: 0 | AK17: High Training | AL17: Watchlist | AM17: 62.5 | AN17: Data Issue
A18: E0014 | B18: Maximilian Romano | C18: Female | D18: 51 | E18: 27197 | F18: Engineering | G18: Product & Technology | H18: Platform Engineer | I18: L2 | J18: M051 | K18: Eva Bianchi | L18: Munich | M18: Germany | N18: Bavaria | O18: 45560 | Q18: Active | R18: 60000 | S18: 5400 | T18: 4 | U18: 21 | V18: 28 | W18: 13 | X18: 65 | Y18: Not Promoted | Z18: Bachelor's | AA18: European Job Board | AB18: Hybrid | AC18: EU-CC101 | AD18: Full Time | AE18: 67.5 | AF18: 1.7 | AG18: 45-54 | AH18: €60k-€85k | AI18: High Performer | AJ18: 0 | AK18: Moderate Training | AL18: Watchlist | AM18: 67.5
A19: E0015 | B19: Aleksander Brown | C19: Female | D19: 42 | E19: 30754 | F19: Customer Success | G19: Revenue | H19: Client Success Associate | I19: L2 | J19: M050 | K19: Louis Szymanski | L19: Munich | M19: Germany | N19: Bavaria | O19: 44699 | P19: 45180 | Q19: Exited | R19: 53000 | S19: 4800 | T19: 4 | U19: 24 | V19: 4 | W19: 5 | X19: 52 | Y19: Not Promoted | Z19: Master's | AA19: Employee Referral | AB19: Hybrid | AC19: EU-CC202 | AD19: Full Time | AE19: 67.7 | AF19: 1.3 | AG19: 35-44 | AH19: €40k-€60k | AI19: High Performer | AJ19: 1 | AK19: Moderate Training | AL19: Not Eligible | AM19: 67.7
A20: E0016 | B20: Milan Mulder | C20: Female | D20: 45 | E20: 29509 | F20: Marketing | G20: Revenue | H20: SEO Specialist | I20: L2 | J20: M006 | K20: Aleksander Fischer | L20: Frankfurt | M20: Germany | N20: Hesse | O20: 44325 | Q20: Active | R20: 63000 | S20: 3200 | T20: 3 | U20: 22 | V20: 0 | W20: 9 | X20: 57 | Y20: Not Promoted | Z20: Master's | AA20: Internal Transfer | AB20: Hybrid | AC20: EU-CC203 | AD20: Part Time | AE20: 58 | AF20: 5.1 | AG20: 45-54 | AH20: €60k-€85k | AI20: Core Performer | AJ20: 0 | AK20: Moderate Training | AL20: Not Eligible | AM20: 58
A21: E0017 | B21: Valeria Olsson | C21: Male | D21: 28 | E21: 35861 | F21: Data & Analytics | G21: Data & AI | H21: Analytics Engineer | I21: L2 | J21: M003 | K21: Sarah Lopez | L21: Stockholm | M21: Sweden | N21: Stockholm County | O21: 42737 | Q21: Active | R21: 64000 | S21: 1300 | T21: 2 | U21: 33 | V21: 9 | W21: 20 | X21: 45 | Y21: Not Promoted | Z21: Bachelor's | AA21: European Job Board | AB21: Hybrid | AC21: EU-CC103 | AD21: Part Time | AE21: 42 | AF21: 9.4 | AG21: 25-34 | AH21: €60k-€85k | AI21: Low Performer | AJ21: 0 | AK21: High Training | AL21: Not Eligible | AM21: 42
A22: E0018 | B22: Luuk Rodriguez | C22: Male | D22: 26 | E22: 36486 | F22: Customer Success | G22: Revenue | H22: Customer Success Manager | I22: L3 | J22: M024 | K22: Noah Ryan | L22: Dublin | M22: Ireland | N22: Leinster | O22: 44684 | Q22: Active | R22: 72000 | S22: 6500 | T22: 4 | U22: 7 | V22: 7 | W22: 13 | X22: 84 | Y22: Not Promoted | Z22: Bachelor's | AA22: Company Careers Page | AB22: Hybrid | AC22: EU-CC202 | AD22: Full Time | AE22: 70.7 | AF22: 4.1 | AG22: 25-34 | AH22: €60k-€85k | AI22: High Performer | AJ22: 0 | AK22: Low Training | AL22: Eligible | AM22: 70.7 | AN22: Data Issue
A23: E0019 | B23: Linnea Costa | C23: Male | D23: 35 | E23: 33083 | F23: Product | G23: Product & Technology | H23: Product Manager | I23: L3 | J23: M028 | K23: Sara Fernandes | L23: Dublin | M23: Ireland | N23: Leinster | O23: 42749 | Q23: Active | R23: 85000 | S23: 4200 | T23: 3 | U23: 26 | V23: 25 | W23: 9 | X23: 52 | Y23: Not Promoted | Z23: Master's | AA23: Internal Transfer | AB23: Remote | AC23: EU-CC102 | AD23: Full Time | AE23: 57.2 | AF23: 9.4 | AG23: 35-44 | AH23: €85k-€120k | AI23: Core Performer | AJ23: 0 | AK23: Moderate Training | AL23: Not Eligible | AM23: 57.2
A24: E0020 | B24: Camille Bianchi | C24: Male | D24: 36 | E24: 32707 | F24: Engineering | G24: Product & Technology | H24: Senior Software Engineer | I24: L2 | J24: M001 | K24: Milan Leroy | L24: London | M24: United Kingdom | N24: England | O24: 45589 | Q24: Active | R24: 70000 | S24: 3500 | T24: 3 | U24: 13 | V24: 16 | W24: 6 | X24: 70 | Y24: Not Promoted | Z24: Bachelor's | AA24: European Job Board | AB24: Office | AC24: EU-CC101 | AD24: Full Time | AE24: 61.8 | AF24: 1.6 | AG24: 35-44 | AH24: €60k-€85k | AI24: Core Performer | AJ24: 0 | AK24: Moderate Training | AL24: Watchlist | AM24: 61.8
A25: E0021 | B25: Sofia Costa | C25: Male | D25: 38 | E25: 32295 | F25: Engineering | G25: Product & Technology | H25: Platform Engineer | I25: L6 | J25: M048 | K25: Jack Schmidt | L25: Remote - Europe | M25: Europe | N25: Remote | O25: 45988 | Q25: Active | R25: 149000 | S25: 14900 | T25: 4 | U25: 6 | V25: 16 | W25: 16 | X25: 65 | Y25: Not Promoted | Z25: Master's | AA25: European Job Board | AB25: Remote | AC25: EU-CC101 | AD25: Full Time | AE25: 62.2 | AF25: 0.5 | AG25: 35-44 | AH25: €120k-€170k | AI25: High Performer | AJ25: 0 | AK25: Low Training | AL25: Watchlist | AM25: 62.2 | AN25: Data Issue
A26: E0022 | B26: Marco Wisniewski | C26: Male | D26: 28 | E26: 35878 | F26: Sales | G26: Revenue | H26: Enterprise Account Manager | I26: L4 | J26: M026 | K26: Sergio Rodrigues | L26: Wroclaw | M26: Poland | N26: Lower Silesian | O26: 44776 | Q26: Active | R26: 68000 | S26: 9500 | T26: 5 | U26: 12 | V26: 19 | W26: 25 | X26: 72 | Y26: Not Promoted | Z26: Bachelor's | AA26: University Hiring | AB26: Hybrid | AC26: EU-CC201 | AD26: Full Time | AE26: 73.2 | AF26: 3.9 | AG26: 25-34 | AH26: €60k-€85k | AI26: High Performer | AJ26: 0 | AK26: Moderate Training | AL26: Eligible | AM26: 73.2
A27: E0023 | B27: Manuel Murphy | C27: Male | D27: 25 | E27: 36952 | F27: Data & Analytics | G27: Data & AI | H27: Analytics Engineer | I27: L2 | J27: M058 | K27: Lukas Esposito | L27: Brussels | M27: Belgium | N27: Brussels-Capital | O27: 44582 | Q27: Active | R27: 52000 | S27: 1000 | T27: 2 | U27: 9 | V27: 12 | W27: 35 | X27: 75 | Y27: Not Promoted | Z27: MBA | AA27: European Job Board | AB27: Remote | AC27: EU-CC103 | AD27: Full Time | AE27: 46.5 | AF27: 4.4 | AG27: 25-34 | AH27: €40k-€60k | AI27: Low Performer | AJ27: 0 | AK27: Low Training | AL27: Not Eligible | AM27: 46.5 | AN27: Data Issue
A28: E0024 | B28: Laura Fernandez | C28: Female | D28: 40 | E28: 31317 | F28: Human Resources | G28: Corporate Services | H28: People Operations Analyst | I28: L3 | J28: M060 | K28: Matteo Wagner | L28: Berlin | M28: Germany | N28: Berlin | O28: 44749 | Q28: Active | R28: 80000 | S28: 7200 | T28: 4 | U28: 30 | V28: 10 | W28: 14 | X28: 57 | Y28: Not Promoted | Z28: Bachelor's | AA28: LinkedIn | AB28: Hybrid | AC28: EU-CC302 | AD28: Full Time | AE28: 66.5 | AF28: 3.9 | AG28: 35-44 | AH28: €60k-€85k | AI28: High Performer | AJ28: 0 | AK28: Moderate Training | AL28: Not Eligible | AM28: 66.5 | AN28: Data Issue
A29: E0025 | B29: Elsa Eriksson | C29: Non-Binary | D29: 53 | E29: 26753 | F29: Customer Success | G29: Revenue | H29: Client Success Associate | I29: L3 | J29: M054 | K29: Isla Eriksson | L29: Lyon | M29: France | N29: Auvergne-Rhone-Alpes | O29: 43944 | Q29: Active | R29: 71000 | S29: 6400 | T29: 4 | U29: 15 | V29: 18 | W29: 0 | X29: 76 | Y29: Not Promoted | Z29: PhD | AA29: Indeed | AB29: Hybrid | AC29: EU-CC202 | AD29: Full Time | AE29: 76.3 | AF29: 6.1 | AG29: 45-54 | AH29: €60k-€85k | AI29: High Performer | AJ29: 0 | AK29: Moderate Training | AL29: Eligible | AM29: 76.3
A30: E0026 | B30: Sergio Larsson | C30: Male | D30: 28 | E30: 35735 | F30: Engineering | G30: Product & Technology | H30: Software Engineer | I30: L5 | J30: M051 | K30: Eva Bianchi | L30: Dublin | M30: Ireland | N30: Leinster | O30: 45354 | Q30: Active | R30: 167000 | S30: 10000 | T30: 3 | U30: 17 | V30: 5 | W30: 22 | X30: 43 | Y30: Not Promoted | Z30: Master's | AA30: Company Careers Page | AB30: Remote | AC30: EU-CC101 | AD30: Full Time | AE30: 46.3 | AF30: 2.3 | AG30: 25-34 | AH30: €120k-€170k | AI30: Core Performer | AJ30: 0 | AK30: Moderate Training | AL30: Not Eligible | AM30: 46.3
A31: E0027 | B31: Hugo Gomez | C31: Male | D31: 26 | E31: 36571 | F31: Finance | G31: Corporate Services | H31: Finance Manager | I31: L5 | J31: M007 | K31: Astrid Bakker | L31: Lyon | M31: France | N31: Auvergne-Rhone-Alpes | O31: 43062 | Q31: Active | R31: 131000 | S31: 13100 | T31: 4 | U31: 27 | V31: 13 | W31: 14 | X31: 60 | Y31: Not Promoted | Z31: Bachelor's | AA31: Company Careers Page | AB31: Hybrid | AC31: EU-CC301 | AD31: Full Time | AE31: 66.8 | AF31: 8.6 | AG31: 25-34 | AH31: €120k-€170k | AI31: High Performer | AJ31: 0 | AK31: Moderate Training | AL31: Watchlist | AM31: 66.8
A32: E0028 | B32: Gabriel Dubois | C32: Male | D32: 46 | E32: 29069 | F32: Human Resources | G32: Corporate Services | H32: Talent Acquisition Specialist | I32: L3 | J32: M033 | K32: Pieter Perez | L32: Lille | M32: France | N32: Hauts-de-France | O32: 43607 | P32: 45602 | Q32: Exited | R32: 79000 | S32: 1600 | T32: 2 | U32: 14 | V32: 22 | W32: 5 | X32: 41 | Y32: Not Promoted | Z32: Bachelor's | AA32: Internal Transfer | AB32: Office | AC32: EU-CC302 | AD32: Full Time | AE32: 43.4 | AF32: 5.5 | AG32: 45-54 | AH32: €60k-€85k | AI32: Low Performer | AJ32: 1 | AK32: Moderate Training | AL32: Not Eligible | AM32: 43.4
A33: E0029 | B33: Diego Fischer | C33: Male | D33: 58 | E33: 24820 | F33: Marketing | G33: Revenue | H33: Content Specialist | I33: L7 | J33: M006 | K33: Aleksander Fischer | L33: Remote - Europe | M33: Europe | N33: Remote | O33: 45047 | Q33: Active | R33: 233000 | S33: 23300 | T33: 4 | U33: 39 | V33: 17 | W33: 0 | X33: 72 | Y33: Not Promoted | Z33: Master's | AA33: Agency | AB33: Office | AC33: EU-CC203 | AD33: Full Time | AE33: 81 | AF33: 3.1 | AG33: 55+ | AH33: €170k+ | AI33: High Performer | AJ33: 0 | AK33: High Training | AL33: Eligible | AM33: 81 | AN33: Data Issue
A34: E0030 | B34: Luuk Byrne | C34: Female | D34: 30 | E34: 34909 | F34: Engineering | G34: Product & Technology | H34: Software Engineer | I34: L3 | J34: M039 | K34: Freya Martinez | L34: Krakow | M34: Poland | N34: Lesser Poland | O34: 42545 | Q34: Active | R34: 60000 | S34: 3000 | T34: 3 | U34: 17 | V34: 17 | W34: 16 | X34: 39 | Y34: Not Promoted | Z34: Bachelor's | AA34: Internal Transfer | AB34: Remote | AC34: EU-CC101 | AD34: Full Time | AE34: 46.9 | AF34: 10 | AG34: 25-34 | AH34: €60k-€85k | AI34: Core Performer | AJ34: 0 | AK34: Moderate Training | AL34: Not Eligible | AM34: 46.9
A35: E0031 | B35: Diego De Jong | C35: Female | D35: 43 | E35: 30423 | F35: Customer Success | G35: Revenue | H35: Support Specialist | I35: L1 | J35: M054 | K35: Isla Eriksson | L35: Remote - Europe | M35: Europe | N35: Remote | O35: 45446 | Q35: Active | R35: 32000 | S35: 1600 | T35: 3 | U35: 6 | V35: 17 | W35: 6 | X35: 51 | Y35: Not Promoted | Z35: Master's | AA35: Agency | AB35: Office | AC35: EU-CC202 | AD35: Full Time | AE35: 53.3 | AF35: 2 | AG35: 35-44 | AH35: <€40k | AI35: Core Performer | AJ35: 0 | AK35: Low Training | AL35: Not Eligible | AM35: 53.3
A36: E0032 | B36: Arthur Gustafsson | C36: Female | D36: 57 | E36: 25201 | F36: Procurement | G36: Operations | H36: Procurement Analyst | I36: L2 | J36: M049 | K36: Marco Gonzalez | L36: Milan | M36: Italy | N36: Lombardy | O36: 45798 | Q36: Active | R36: 45000 | S36: 6300 | T36: 5 | U36: 19 | V36: 22 | W36: 27 | X36: 88 | Y36: Promoted | Z36: Bachelor's | AA36: Company Careers Page | AB36: Hybrid | AC36: EU-CC402 | AD36: Full Time | AE36: 80.5 | AF36: 1.1 | AG36: 55+ | AH36: €40k-€60k | AI36: High Performer | AJ36: 0 | AK36: Moderate Training | AL36: Watchlist | AM36: 80.5
A37: E0033 | B37: Leonardo Walsh | C37: Male | D37: 53 | E37: 26514 | F37: Sales | G37: Revenue | H37: Account Executive | I37: L6 | J37: M023 | K37: Alice Greco | L37: Berlin | M37: Germany | N37: Berlin | O37: 44314 | Q37: Active | R37: 204000 | S37: 12200 | T37: 3 | U37: 38 | V37: 9 | W37: 18 | X37: 66 | Y37: Not Promoted | Z37: MBA | AA37: European Job Board | AB37: Office | AC37: EU-CC201 | AD37: Full Time | AE37: 60.6 | AF37: 5.1 | AG37: 45-54 | AH37: €170k+ | AI37: Core Performer | AJ37: 0 | AK37: High Training | AL37: Watchlist | AM37: 60.6
A38: E0034 | B38: Alice Taylor | C38: Male | D38: 43 | E38: 30357 | F38: Corporate Strategy | G38: Corporate Services | H38: Business Analyst | I38: L4 | J38: M015 | K38: Lea Ryan | L38: Milan | M38: Italy | N38: Lombardy | O38: 44841 | Q38: Active | R38: 88000 | S38: 7900 | T38: 4 | U38: 27 | V38: 5 | W38: 7 | X38: 98 | Y38: Not Promoted | Z38: Bachelor's | AA38: Indeed | AB38: Office | AC38: EU-CC303 | AD38: Contract | AE38: 83.5 | AF38: 3.7 | AG38: 35-44 | AH38: €85k-€120k | AI38: High Performer | AJ38: 0 | AK38: Moderate Training | AL38: Eligible | AM38: 83.5 | AN38: Data Issue
A39: E0035 | B39: Sofia Jones | C39: Male | D39: 37 | E39: 32372 | F39: Sales | G39: Revenue | H39: Account Executive | I39: L2 | J39: M016 | K39: Juliette Williams | L39: Warsaw | M39: Poland | N39: Masovian | O39: 44898 | Q39: Active | R39: 45000 | S39: 2200 | T39: 3 | U39: 35 | V39: 20 | W39: 14 | X39: 62 | Y39: Not Promoted | Z39: Master's | AA39: Internal Transfer | AB39: Hybrid | AC39: EU-CC201 | AD39: Part Time | AE39: 60.5 | AF39: 3.5 | AG39: 35-44 | AH39: €40k-€60k | AI39: Core Performer | AJ39: 0 | AK39: High Training | AL39: Watchlist | AM39: 60.5 | AN39: Data Issue
A40: E0036 | B40: Sophia Rodriguez | C40: Female | D40: 49 | E40: 27939 | F40: Engineering | G40: Product & Technology | H40: Frontend Engineer | I40: L4 | J40: M001 | K40: Milan Leroy | L40: Brussels | M40: Belgium | N40: Brussels-Capital | O40: 43893 | Q40: Active | R40: 109000 | S40: 5400 | T40: 3 | U40: 21 | V40: 8 | W40: 5 | X40: 59 | Y40: Not Promoted | Z40: Bachelor's | AA40: Company Careers Page | AB40: Office | AC40: EU-CC101 | AD40: Full Time | AE40: 60.4 | AF40: 6.3 | AG40: 45-54 | AH40: €85k-€120k | AI40: Core Performer | AJ40: 0 | AK40: Moderate Training | AL40: Not Eligible | AM40: 60.4
A41: E0037 | B41: Oscar Ferreira | C41: Female | D41: 49 | E41: 28059 | F41: Compliance | G41: Risk & Compliance | H41: Regulatory Specialist | I41: L3 | J41: M025 | K41: Elias De Jong | L41: Paris | M41: France | N41: Ile-de-France | O41: 42927 | Q41: Active | R41: 79000 | S41: 1600 | T41: 2 | U41: 27 | V41: 13 | W41: 13 | X41: 53 | Y41: Not Promoted | Z41: Diploma | AA41: Agency | AB41: Remote | AC41: EU-CC502 | AD41: Full Time | AE41: 46.8 | AF41: 8.9 | AG41: 45-54 | AH41: €60k-€85k | AI41: Low Performer | AJ41: 0 | AK41: Moderate Training | AL41: Not Eligible | AM41: 46.8
A42: E0038 | B42: Elsa Johansson | C42: Female | D42: 29 | E42: 35385 | F42: Sales | G42: Revenue | H42: Sales Development Representative | I42: L3 | J42: M004 | K42: Giovanni Leroy | L42: Remote - Europe | M42: Europe | N42: Remote | O42: 45081 | Q42: Active | R42: 66000 | S42: 5900 | T42: 4 | U42: 24 | V42: 18 | W42: 16 | X42: 60 | Y42: Not Promoted | Z42: Master's | AA42: Company Careers Page | AB42: Remote | AC42: EU-CC201 | AD42: Part Time | AE42: 65 | AF42: 3 | AG42: 25-34 | AH42: €60k-€85k | AI42: High Performer | AJ42: 0 | AK42: Moderate Training | AL42: Watchlist | AM42: 65 | AN42: Data Issue
A43: E0039 | B43: Molly Svensson | C43: Female | D43: 57 | E43: 25355 | F43: Finance | G43: Corporate Services | H43: Payroll Specialist | I43: L3 | J43: M007 | K43: Astrid Bakker | L43: Dublin | M43: Ireland | N43: Leinster | O43: 45057 | Q43: Active | R43: 74000 | S43: 1500 | T43: 2 | U43: 21 | V43: 12 | W43: 10 | X43: 26 | Y43: Not Promoted | Z43: Diploma | AA43: University Hiring | AB43: Hybrid | AC43: EU-CC301 | AD43: Full Time | AE43: 37.4 | AF43: 3.1 | AG43: 55+ | AH43: €60k-€85k | AI43: Low Performer | AJ43: 0 | AK43: Moderate Training | AL43: Not Eligible | AM43: 37.4
A44: E0040 | B44: Lucas Zielinski | C44: Male | D44: 42 | E44: 30557 | F44: Marketing | G44: Revenue | H44: Growth Marketer | I44: L5 | J44: M006 | K44: Aleksander Fischer | L44: Warsaw | M44: Poland | N44: Masovian | O44: 42409 | Q44: Active | R44: 101000 | S44: 6100 | T44: 3 | U44: 16 | V44: 17 | W44: 3 | X44: 64 | Y44: Not Promoted | Z44: Diploma | AA44: European Job Board | AB44: Hybrid | AC44: EU-CC203 | AD44: Full Time | AE44: 61.9 | AF44: 10.3 | AG44: 35-44 | AH44: €85k-€120k | AI44: Core Performer | AJ44: 0 | AK44: Moderate Training | AL44: Watchlist | AM44: 61.9
A45: E0041 | B45: Lea Rossi | C45: Non-Binary | D45: 25 | E45: 37053 | F45: Product | G45: Product & Technology | H45: Product Manager | I45: L6 | J45: M031 | K45: Felix Pereira | L45: Munich | M45: Germany | N45: Bavaria | O45: 42971 | Q45: Active | R45: 178000 | S45: 10700 | T45: 3 | U45: 25 | V45: 23 | W45: 7 | X45: 55 | Y45: Not Promoted | Z45: Bachelor's | AA45: LinkedIn | AB45: Hybrid | AC45: EU-CC102 | AD45: Full Time | AE45: 59 | AF45: 8.8 | AG45: 25-34 | AH45: €170k+ | AI45: Core Performer | AJ45: 0 | AK45: Moderate Training | AL45: Not Eligible | AM45: 59
A46: E0042 | B46: Charlotte Kowalski | C46: Female | D46: 58 | E46: 24796 | F46: IT | G46: Product & Technology | H46: IT Support Analyst | I46: L3 | J46: M041 | K46: Javier Jansen | L46: London | M46: United Kingdom | N46: England | O46: 44119 | Q46: Active | R46: 96000 | S46: 1900 | T46: 2 | U46: 29 | V46: 10 | W46: 2 | X46: 51 | Y46: Not Promoted | Z46: Bachelor's | AA46: Internal Transfer | AB46: Hybrid | AC46: EU-CC104 | AD46: Full Time | AE46: 52.1 | AF46: 5.7 | AG46: 55+ | AH46: €85k-€120k | AI46: Low Performer | AJ46: 0 | AK46: Moderate Training | AL46: Not Eligible | AM46: 52.1
A47: E0043 | B47: Gabriel Walker | C47: Female | D47: 29 | E47: 35324 | F47: Customer Success | G47: Revenue | H47: Client Success Associate | I47: L5 | J47: M050 | K47: Louis Szymanski | L47: Gothenburg | M47: Sweden | N47: Vastra Gotaland | O47: 45359 | P47: 45711 | Q47: Exited | R47: 122000 | S47: 7300 | T47: 3 | U47: 19 | V47: 11 | W47: 13 | X47: 42 | Y47: Not Promoted | Z47: Master's | AA47: European Job Board | AB47: Hybrid | AC47: EU-CC202 | AD47: Contract | AE47: 50 | AF47: 1 | AG47: 25-34 | AH47: €120k-€170k | AI47: Core Performer | AJ47: 1 | AK47: Moderate Training | AL47: Not Eligible | AM47: 50
A48: E0044 | B48: Molly Nowak | C48: Female | D48: 42 | E48: 30770 | F48: Customer Success | G48: Revenue | H48: Client Success Associate | I48: L3 | J48: M047 | K48: Alice Andersson | L48: Madrid | M48: Spain | N48: Community of Madrid | O48: 43871 | Q48: Active | R48: 58000 | S48: 2900 | T48: 3 | U48: 20 | V48: 24 | W48: 15 | X48: 63 | Y48: Not Promoted | Z48: Master's | AA48: Company Careers Page | AB48: Hybrid | AC48: EU-CC202 | AD48: Full Time | AE48: 56.5 | AF48: 6.3 | AG48: 35-44 | AH48: €40k-€60k | AI48: Core Performer | AJ48: 0 | AK48: Moderate Training | AL48: Watchlist | AM48: 56.5 | AN48: Data Issue
A49: E0045 | B49: Amelia Ricci | C49: Female | D49: 58 | E49: 24670 | F49: Product | G49: Product & Technology | H49: Lead Product Manager | I49: L3 | J49: M027 | K49: Miguel Persson | L49: Remote - Europe | M49: Europe | N49: Remote | O49: 44370 | P49: 45783 | Q49: Exited | R49: 65000 | S49: 3200 | T49: 3 | U49: 10 | V49: 18 | W49: 16 | X49: 65 | Y49: Not Promoted | Z49: Bachelor's | AA49: Company Careers Page | AB49: Remote | AC49: EU-CC102 | AD49: Full Time | AE49: 54.2 | AF49: 3.9 | AG49: 55+ | AH49: €60k-€85k | AI49: Core Performer | AJ49: 1 | AK49: Moderate Training | AL49: Not Eligible | AM49: 54.2 | AN49: Data Issue
A50: E0046 | B50: Ava Murphy | C50: Female | D50: 26 | E50: 36523 | F50: Engineering | G50: Product & Technology | H50: Backend Engineer | I50: L4 | J50: M039 | K50: Freya Martinez | L50: Gothenburg | M50: Sweden | N50: Vastra Gotaland | O50: 45227 | Q50: Active | R50: 87000 | S50: 7800 | T50: 4 | U50: 32 | V50: 11 | W50: 4 | X50: 56 | Y50: Promoted | Z50: Master's | AA50: Employee Referral | AB50: Hybrid | AC50: EU-CC101 | AD50: Full Time | AE50: 71.6 | AF50: 2.6 | AG50: 25-34 | AH50: €85k-€120k | AI50: High Performer | AJ50: 0 | AK50: High Training | AL50: Not Eligible | AM50: 71.6
A51: E0047 | B51: Kacper Wagner | C51: Female | D51: 55 | E51: 26051 | F51: Finance | G51: Corporate Services | H51: Payroll Specialist | I51: L3 | J51: M007 | K51: Astrid Bakker | L51: Frankfurt | M51: Germany | N51: Hesse | O51: 43201 | Q51: Active | R51: 81000 | S51: 4000 | T51: 3 | U51: 27 | V51: 17 | W51: 14 | X51: 59 | Y51: Not Promoted | Z51: Master's | AA51: LinkedIn | AB51: Hybrid | AC51: EU-CC301 | AD51: Contract | AE51: 57.4 | AF51: 8.2 | AG51: 55+ | AH51: €60k-€85k | AI51: Core Performer | AJ51: 0 | AK51: Moderate Training | AL51: Not Eligible | AM51: 57.4
A52: E0048 | B52: Agnes Wagner | C52: Female | D52: 31 | E52: 34781 | F52: Product | G52: Product & Technology | H52: Lead Product Manager | I52: L4 | J52: M027 | K52: Miguel Persson | L52: Gothenburg | M52: Sweden | N52: Vastra Gotaland | O52: 42543 | Q52: Active | R52: 114000 | S52: 5700 | T52: 3 | U52: 24 | V52: 2 | W52: 12 | X52: 73 | Y52: Not Promoted | Z52: MBA | AA52: European Job Board | AB52: Remote | AC52: EU-CC102 | AD52: Full Time | AE52: 62.5 | AF52: 10 | AG52: 25-34 | AH52: €85k-€120k | AI52: Core Performer | AJ52: 0 | AK52: Moderate Training | AL52: Watchlist | AM52: 62.5 | AN52: Data Issue
A53: E0049 | B53: Liam Colombo | C53: Male | D53: 40 | E53: 31382 | F53: Customer Success | G53: Revenue | H53: Support Specialist | I53: L3 | J53: M032 | K53: Hannah Wagner | L53: Wroclaw | M53: Poland | N53: Lower Silesian | O53: 43222 | Q53: Active | R53: 59000 | S53: 3000 | T53: 3 | U53: 42 | V53: 23 | W53: 16 | X53: 55 | Y53: Not Promoted | Z53: Master's | AA53: Internal Transfer | AB53: Hybrid | AC53: EU-CC202 | AD53: Full Time | AE53: 58.2 | AF53: 8.1 | AG53: 35-44 | AH53: €40k-€60k | AI53: Core Performer | AJ53: 0 | AK53: High Training | AL53: Not Eligible | AM53: 58.2
A54: E0050 | B54: Giulia Schmidt | C54: Female | D54: 36 | E54: 32808 | F54: Compliance | G54: Risk & Compliance | H54: Regulatory Specialist | I54: L5 | J54: M012 | K54: Zofia Petit | L54: Paris | M54: France | N54: Ile-de-France | O54: 44015 | Q54: Active | R54: 130000 | S54: 19500 | T54: 5 | U54: 33 | V54: 6 | W54: 13 | X54: 69 | Y54: Not Promoted | Z54: Master's | AA54: Indeed | AB54: Hybrid | AC54: EU-CC502 | AD54: Full Time | AE54: 80.9 | AF54: 5.9 | AG54: 35-44 | AH54: €120k-€170k | AI54: High Performer | AJ54: 0 | AK54: High Training | AL54: Watchlist | AM54: 80.9
A55: E0051 | B55: Freja Smith | C55: Female | D55: 23 | E55: 37655 | F55: Product | G55: Product & Technology | H55: Lead Product Manager | I55: L2 | J55: M053 | K55: Hugo Costa | L55: Paris | M55: France | N55: Ile-de-France | O55: 45392 | P55: 45726 | Q55: Exited | R55: 58000 | S55: 5200 | T55: 4 | U55: 43 | V55: 24 | W55: 10 | X55: 61 | Y55: Not Promoted | Z55: Bachelor's | AA55: University Hiring | AB55: Hybrid | AC55: EU-CC102 | AD55: Full Time | AE55: 72.3 | AF55: 0.9 | AG55: <25 | AH55: €40k-€60k | AI55: High Performer | AJ55: 1 | AK55: High Training | AL55: Not Eligible | AM55: 72.3 | AN55: Data Issue
A56: E0052 | B56: Oliver Svensson | C56: Male | D56: 58 | E56: 24790 | F56: Product | G56: Product & Technology | H56: Lead Product Manager | I56: L3 | J56: M038 | K56: Sophia Moreau | L56: London | M56: United Kingdom | N56: England | O56: 44830 | Q56: Active | R56: 86000 | S56: 4300 | T56: 3 | U56: 7 | V56: 16 | W56: 18 | X56: 62 | Y56: Not Promoted | Z56: High School | AA56: Employee Referral | AB56: Hybrid | AC56: EU-CC102 | AD56: Full Time | AE56: 51.5 | AF56: 3.7 | AG56: 55+ | AH56: €85k-€120k | AI56: Core Performer | AJ56: 0 | AK56: Low Training | AL56: Watchlist | AM56: 51.5
A57: E0053 | B57: Leon Sousa | C57: Female | D57: 43 | E57: 30413 | F57: Engineering | G57: Product & Technology | H57: Engineering Lead | I57: L3 | J57: M030 | K57: Sem Thomas | L57: Milan | M57: Italy | N57: Lombardy | O57: 45276 | Q57: Active | R57: 77000 | S57: 1500 | T57: 2 | U57: 26 | V57: 7 | W57: 11 | X57: 61 | Y57: Not Promoted | Z57: Bachelor's | AA57: LinkedIn | AB57: Hybrid | AC57: EU-CC101 | AD57: Full Time | AE57: 50.3 | AF57: 2.5 | AG57: 35-44 | AH57: €60k-€85k | AI57: Low Performer | AJ57: 0 | AK57: Moderate Training | AL57: Not Eligible | AM57: 50.3 | AN57: Data Issue
A58: E0054 | B58: Matteo Gomez | C58: Male | D58: 24 | E58: 37090 | F58: Product | G58: Product & Technology | H58: Product Analyst | I58: L2 | J58: M038 | K58: Sophia Moreau | L58: Munich | M58: Germany | N58: Bavaria | O58: 45486 | Q58: Active | R58: 69000 | S58: 3400 | T58: 3 | U58: 37 | V58: 13 | W58: 0 | X58: 66 | Y58: Not Promoted | Z58: Bachelor's | AA58: Employee Referral | AB58: Hybrid | AC58: EU-CC102 | AD58: Full Time | AE58: 69.3 | AF58: 1.9 | AG58: <25 | AH58: €60k-€85k | AI58: Core Performer | AJ58: 0 | AK58: High Training | AL58: Watchlist | AM58: 69.3
A59: E0055 | B59: Astrid Thomas | C59: Female | D59: 42 | E59: 30795 | F59: Engineering | G59: Product & Technology | H59: Backend Engineer | I59: L3 | J59: M044 | K59: Sophia Russo | L59: Madrid | M59: Spain | N59: Community of Madrid | O59: 44545 | Q59: Active | R59: 58000 | S59: 5200 | T59: 4 | U59: 0 | V59: 34 | W59: 8 | X59: 98 | Y59: Not Promoted | Z59: Diploma | AA59: Company Careers Page | AB59: Hybrid | AC59: EU-CC101 | AD59: Full Time | AE59: 76.3 | AF59: 4.5 | AG59: 35-44 | AH59: €40k-€60k | AI59: High Performer | AJ59: 0 | AK59: Low Training | AL59: Eligible | AM59: 76.3
A60: E0056 | B60: Lucas Brown | C60: Male | D60: 60 | E60: 23925 | F60: Operations | G60: Operations | H60: Operations Analyst | I60: L1 | J60: M010 | K60: Lotte Muller | L60: Krakow | M60: Poland | N60: Lesser Poland | O60: 44031 | P60: 44435 | Q60: Exited | R60: 29000 | S60: 4100 | T60: 5 | U60: 25 | V60: 5 | W60: 3 | X60: 67 | Y60: Not Promoted | Z60: Master's | AA60: University Hiring | AB60: Remote | AC60: EU-CC401 | AD60: Full Time | AE60: 83.2 | AF60: 1.1 | AG60: 55+ | AH60: <€40k | AI60: High Performer | AJ60: 1 | AK60: Moderate Training | AL60: Not Eligible | AM60: 83.2
A61: E0057 | B61: Nathan Fernandez | C61: Female | D61: 57 | E61: 25308 | F61: Data & Analytics | G61: Data & AI | H61: Data Scientist | I61: L2 | J61: M020 | K61: Alessandro Lewandowski | L61: Remote - Europe | M61: Europe | N61: Remote | O61: 44050 | P61: 45886 | Q61: Exited | R61: 45000 | S61: 900 | T61: 2 | U61: 45 | V61: 14 | W61: 37 | X61: 39 | Y61: Not Promoted | Z61: Master's | AA61: Employee Referral | AB61: Hybrid | AC61: EU-CC103 | AD61: Full Time | AE61: 41.6 | AF61: 5 | AG61: 55+ | AH61: €40k-€60k | AI61: Low Performer | AJ61: 1 | AK61: High Training | AL61: Not Eligible | AM61: 41.6 | AN61: Data Issue
A62: E0058 | B62: Fleur Martin | C62: Female | D62: 33 | E62: 33949 | F62: Customer Success | G62: Revenue | H62: Support Specialist | I62: L2 | J62: M024 | K62: Noah Ryan | L62: Berlin | M62: Germany | N62: Berlin | O62: 44730 | Q62: Active | R62: 57000 | S62: 8000 | T62: 5 | U62: 41 | V62: 25 | W62: 20 | X62: 79 | Y62: Not Promoted | Z62: Bachelor's | AA62: Company Careers Page | AB62: Hybrid | AC62: EU-CC202 | AD62: Contract | AE62: 82.7 | AF62: 4 | AG62: 25-34 | AH62: €40k-€60k | AI62: High Performer | AJ62: 0 | AK62: High Training | AL62: Eligible | AM62: 82.7
A63: E0059 | B63: Freya Wagner | C63: Non-Binary | D63: 26 | E63: 36461 | F63: Customer Success | G63: Revenue | H63: Support Specialist | I63: L3 | J63: M024 | K63: Noah Ryan | L63: Warsaw | M63: Poland | N63: Masovian | O63: 43006 | P63: 43604 | Q63: Exited | R63: 58000 | S63: 2900 | T63: 3 | U63: 28 | V63: 31 | W63: 4 | X63: 56 | Y63: Not Promoted | Z63: Diploma | AA63: University Hiring | AB63: Hybrid | AC63: EU-CC202 | AD63: Full Time | AE63: 61.6 | AF63: 1.6 | AG63: 25-34 | AH63: €40k-€60k | AI63: Core Performer | AJ63: 1 | AK63: Moderate Training | AL63: Not Eligible | AM63: 61.6
A64: E0060 | B64: Hannah Murphy | C64: Male | D64: 56 | E64: 25686 | F64: Customer Success | G64: Revenue | H64: Support Specialist | I64: L2 | J64: M024 | K64: Noah Ryan | L64: Barcelona | M64: Spain | N64: Catalonia | O64: 45210 | Q64: Active | R64: 51000 | S64: 4600 | T64: 4 | U64: 27 | V64: 15 | W64: 4 | X64: 59 | Y64: Not Promoted | Z64: Master's | AA64: Company Careers Page | AB64: Hybrid | AC64: EU-CC202 | AD64: Full Time | AE64: 71.4 | AF64: 2.7 | AG64: 55+ | AH64: €40k-€60k | AI64: High Performer | AJ64: 0 | AK64: Moderate Training | AL64: Not Eligible | AM64: 71.4
A65: E0061 | B65: Claudia De Jong | C65: Female | D65: 41 | E65: 30965 | F65: Data & Analytics | G65: Data & AI | H65: Data Scientist | I65: L4 | J65: M037 | K65: Elsa Andersson | L65: Lyon | M65: France | N65: Auvergne-Rhone-Alpes | O65: 45000 | Q65: Active | R65: 99000 | S65: 5000 | T65: 3 | U65: 38 | V65: 25 | W65: 0 | X65: 98 | Y65: Not Promoted | Z65: Bachelor's | AA65: Company Careers Page | AB65: Office | AC65: EU-CC103 | AD65: Full Time | AE65: 80.8 | AF65: 3.2 | AG65: 35-44 | AH65: €85k-€120k | AI65: Core Performer | AJ65: 0 | AK65: High Training | AL65: Watchlist | AM65: 80.8
